Workbook

Sheet BD Asesor
V1: =DAY(Listas!B2) -> 19 | X1: =MONTH(Listas!B2) -> 5
B3: Base de Datos asesor
D5: 2 meses antes | I5: Día de su cumpleaños
D6: 10 dias antes | I6: 5 dias antes
A7: Cliente | B7: Sexo | C7: Estado | D7: Emisión | E7: Número de póliza | F7: Prima anual | G7: Tipo de Moneda | H7: Forma de pago | I7: Cumpleaños | J7: Buen referenciador | K7: Modo de cobro | L7: Tipo de plan | M7: Nombre del plan | N7: Correo electrónico | O7: Teléfono | P7: Asesor | Q7: Mes | R7: Año | S7: DiaEm | T7: Diferencia de dia | U7: MesEm | V7: DiaCu | W7: Diferencia Cu | X7: MesCu | Y7: MesNum | Z7: Años | AA7: Bloques edad
A8: ABRAHAM GALICIA MANCERA | B8: H | C8: Activo | D8: 44238 | E8: GM0000512930 | F8: =1413.91*12 -> 16966.92 | G8: MXN | H8: Mensual | I8: 15-sep | J8: Sí | K8: TD | L8: Gastos Médicos | M8: Integro | N8: abraham.mancera92@hotmail.com | O8: 3322725657 | P8: =IF(A8="","", "DARINKA UREÑA CASILLAS") -> DARINKA UREÑA CASILLAS | Q8: =IF(D8="","",VLOOKUP(MONTH(D8),Listas!$C$2:$D$14,2,0)) -> Febrero | R8: =IF(D8="","",YEAR(D8)) -> 2021 | S8: =IF(D8="","",(DAY(D8))) -> 11 | T8: =IF(D8="","",S8-$W$1) -> 11 | U8: =IF(D8="","",(MONTH(D8))) -> 2 | V8: =IF(I8="","",(DAY(I8))) -> 15 | W8: =IF(I8="","",V8-$W$1) -> 15 | X8: =IF(I8="","",(MONTH(I8))) -> 9 | Y8: =IF(D8="","",(MONTH(D8))) -> 2 | Z8: =IFERROR(IF(I8="","", DATEDIF(I8, TODAY(), "Y")),0) -> 0 | AA8: =IF(Z8="","", IFS(Z8 >= 61, "61+ años", Z8 >= 51, "51-60 años", Z8 >= 40, "40-50 años", Z8 >= 20, "20-39 años", TRUE, "-20 años")) -> -20 años
A9: ABRAHAM GALICIA MANCERA | B9: H | C9: Activo | D9: 44247 | E9: VI0002585905 | F9: =727.3*12*7.65 -> 66766.14 | G9: UDIS | H9: Mensual | I9: 15-sep | J9: Sí | K9: TD | L9: Vida | M9: Orvi | N9: abraham.mancera92@hotmail.com | O9: 3322725657 | P9: =IF(A9="","", "DARINKA UREÑA CASILLAS") -> DARINKA UREÑA CASILLAS | Q9: =IF(D9="","",VLOOKUP(MONTH(D9),Listas!$C$2:$D$14,2,0)) -> Febrero | R9: =IF(D9="","",YEAR(D9)) -> 2021 | S9: =IF(D9="","",(DAY(D9))) -> 20 | T9: =IF(D9="","",S9-$W$1) -> 20 | U9: =IF(D9="","",(MONTH(D9))) -> 2 | V9: =IF(I9="","",(DAY(I9))) -> 15 | W9: =IF(I9="","",V9-$W$1) -> 15 | X9: =IF(I9="","",(MONTH(I9))) -> 9 | Y9: =IF(D9="","",(MONTH(D9))) -> 2 | Z9: =IFERROR(IF(I9="","", DATEDIF(I9, TODAY(), "Y")),0) -> 0 | AA9: =IF(Z9="","", IFS(Z9 >= 61, "61+ años", Z9 >= 51, "51-60 años", Z9 >= 40, "40-50 años", Z9 >= 20, "20-39 años", TRUE, "-20 años")) -> -20 años
A10: ADRIAN ALEJANDRO RAMIREZ MORALES | B10: H | C10: Activo | D10: 44581 | E10: GM0000551209 | F10: =11035.51*2 -> 22071.02 | G10: MXN | H10: Semestral | I10: 44707 | K10: TD | L10: Gastos Médicos | M10: Practico | N10: adriangtsramirez261144@gmail.com | O10: 3335785031 | P10: =IF(A10="","", "DARINKA UREÑA CASILLAS") -> DARINKA UREÑA CASILLAS | Q10: =IF(D10="","",VLOOKUP(MONTH(D10),Listas!$C$2:$D$14,2,0)) -> Enero | R10: =IF(D10="","",YEAR(D10)) -> 2022 | S10: =IF(D10="","",(DAY(D10))) -> 20 | T10: =IF(D10="","",S10-$W$1) -> 20 | U10: =IF(D10="","",(MONTH(D10))) -> 1 | V10: =IF(I10="","",(DAY(I10))) -> 26 | W10: =IF(I10="","",V10-$W$1) -> 26 | X10: =IF(I10="","",(MONTH(I10))) -> 5 | Y10: =IF(D10="","",(MONTH(D10))) -> 1 | Z10: =IFERROR(IF(I10="","", DATEDIF(I10, TODAY(), "Y")),0) -> 3 | AA10: =IF(Z10="","", IFS(Z10 >= 61, "61+ años", Z10 >= 51, "51-60 años", Z10 >= 40, "40-50 años", Z10 >= 20, "20-39 años", TRUE, "-20 años")) -> -20 años
A11: ADRIAN ALEJANDRO RAMIREZ MORALES | B11: H | C11: Activo | D11: 44576 | E11: VI0002645864 | F11: =572.77*12*7.65 -> 52580.286 | G11: UDIS | H11: Mensual | I11: 44707 | K11: TC | L11: Vida | M11: Orvi | N11: adriangtsramirez261144@gmail.com | O11: 3335785031 | P11: =IF(A11="","", "DARINKA UREÑA CASILLAS") -> DARINKA UREÑA CASILLAS | Q11: =IF(D11="","",VLOOKUP(MONTH(D11),Listas!$C$2:$D$14,2,0)) -> Enero | R11: =IF(D11="","",YEAR(D11)) -> 2022 | S11: =IF(D11="","",(DAY(D11))) -> 15 | T11: =IF(D11="","",S11-$W$1) -> 15 | U11: =IF(D11="","",(MONTH(D11))) -> 1 | V11: =IF(I11="","",(DAY(I11))) -> 26 | W11: =IF(I11="","",V11-$W$1) -> 26 | X11: =IF(I11="","",(MONTH(I11))) -> 5 | Y11: =IF(D11="","",(MONTH(D11))) -> 1 | Z11: =IFERROR(IF(I11="","", DATEDIF(I11, TODAY(), "Y")),0) -> 3 | AA11: =IF(Z11="","", IFS(Z11 >= 61, "61+ años", Z11 >= 51, "51-60 años", Z11 >= 40, "40-50 años", Z11 >= 20, "20-39 años", TRUE, "-20 años")) -> -20 años
A12: AIDA GRACIELA FLORES BARBA | B12: M | C12: Activo | D12: 44168 | E12: VI0002570983 | F12: =3637.65*7.65 -> 27828.022 | G12: UDIS | H12: Anual | I12: 44704 | K12: TC | L12: Vida | M12: Orvi | N12: ajj_07@hotmail.com | O12: 3314550115 | P12: =IF(A12="","", "DARINKA UREÑA CASILLAS") -> DARINKA UREÑA CASILLAS | Q12: =IF(D12="","",VLOOKUP(MONTH(D12),Listas!$C$2:$D$14,2,0)) -> Diciembre | R12: =IF(D12="","",YEAR(D12)) -> 2020 | S12: =IF(D12="","",(DAY(D12))) -> 3 | T12: =IF(D12="","",S12-$W$1) -> 3 | U12: =IF(D12="","",(MONTH(D12))) -> 12 | V12: =IF(I12="","",(DAY(I12))) -> 23 | W12: =IF(I12="","",V12-$W$1) -> 23 | X12: =IF(I12="","",(MONTH(I12))) -> 5 | Y12: =IF(D12="","",(MONTH(D12))) -> 12 | Z12: =IFERROR(IF(I12="","", DATEDIF(I12, TODAY(), "Y")),0) -> 3 | AA12: =IF(Z12="","", IFS(Z12 >= 61, "61+ años", Z12 >= 51, "51-60 años", Z12 >= 40, "40-50 años", Z12 >= 20, "20-39 años", TRUE, "-20 años")) -> -20 años
A13: ALEJANDRA DEL CARMEN UREÑA CASILLAS | B13: M | C13: Activo | D13: 44008 | E13: GM0000478411 | F13: 10660.33 | G13: MXN | H13: Anual | I13: 45206 | K13: TC | L13: Gastos Médicos | M13: Integro | N13: ale_u_casillas@hotmail.com | O13: 3322590323 | P13: =IF(A13="","", "DARINKA UREÑA CASILLAS") -> DARINKA UREÑA CASILLAS | Q13: =IF(D13="","",VLOOKUP(MONTH(D13),Listas!$C$2:$D$14,2,0)) -> Junio | R13: =IF(D13="","",YEAR(D13)) -> 2020 | S13: =IF(D13="","",(DAY(D13))) -> 26 | T13: =IF(D13="","",S13-$W$1) -> 26 | U13: =IF(D13="","",(MONTH(D13))) -> 6 | V13: =IF(I13="","",(DAY(I13))) -> 7 | W13: =IF(I13="","",V13-$W$1) -> 7 | X13: =IF(I13="","",(MONTH(I13))) -> 10 | Y13: =IF(D13="","",(MONTH(D13))) -> 6 | Z13: =IFERROR(IF(I13="","", DATEDIF(I13, TODAY(), "Y")),0) -> 2 | AA13: =IF(Z13="","", IFS(Z13 >= 61, "61+ años", Z13 >= 51, "51-60 años", Z13 >= 40, "40-50 años", Z13 >= 20, "20-39 años", TRUE, "-20 años")) -> -20 años
A14: ALEJANDRA DEL CARMEN UREÑA CASILLAS | B14: M | C14: Activo | D14: 44844 | E14: GM0000579437 | F14: =6745*2 -> 13490 | G14: MXN | H14: Semestral | I14: 45170 | K14: TC | L14: Gastos Médicos | M14: Practico | N14: ale_u_casillas@hotmail.com | O14: 3322590323 | P14: =IF(A14="","", "DARINKA UREÑA CASILLAS") -> DARINKA UREÑA CASILLAS | Q14: =IF(D14="","",VLOOKUP(MONTH(D14),Listas!$C$2:$D$14,2,0)) -> Octubre | R14: =IF(D14="","",YEAR(D14)) -> 2022 | S14: =IF(D14="","",(DAY(D14))) -> 10 | T14: =IF(D14="","",S14-$W$1) -> 10 | U14: =IF(D14="","",(MONTH(D14))) -> 10 | V14: =IF(I14="","",(DAY(I14))) -> 1 | W14: =IF(I14="","",V14-$W$1) -> 1 | X14: =IF(I14="","",(MONTH(I14))) -> 9 | Y14: =IF(D14="","",(MONTH(D14))) -> 10 | Z14: =IFERROR(IF(I14="","", DATEDIF(I14, TODAY(), "Y")),0) -> 2 | AA14: =IF(Z14="","", IFS(Z14 >= 61, "61+ años", Z14 >= 51, "51-60 años", Z14 >= 40, "40-50 años", Z14 >= 20, "20-39 años", TRUE, "-20 años")) -> -20 años
A15: ALEJANDRA DEL CARMEN UREÑA CASILLAS | B15: M | C15: Activo | D15: 43893 | E15: VI0002521501 | F15: =5302.35*7.65 -> 40562.978 | G15: UDIS | H15: Anual | I15: 44805 | K15: TD | L15: Vida | M15: Orvi | N15: ale_u_casillas@hotmail.com | O15: 3322590323 | P15: =IF(A15="","", "DARINKA UREÑA CASILLAS") -> DARINKA UREÑA CASILLAS | Q15: =IF(D15="","",VLOOKUP(MONTH(D15),Listas!$C$2:$D$14,2,0)) -> Marzo | R15: =IF(D15="","",YEAR(D15)) -> 2020 | S15: =IF(D15="","",(DAY(D15))) -> 3 | T15: =IF(D15="","",S15-$W$1) -> 3 | U15: =IF(D15="","",(MONTH(D15))) -> 3 | V15: =IF(I15="","",(DAY(I15))) -> 1 | W15: =IF(I15="","",V15-$W$1) -> 1 | X15: =IF(I15="","",(MONTH(I15))) -> 9 | Y15: =IF(D15="","",(MONTH(D15))) -> 3 | Z15: =IFERROR(IF(I15="","", DATEDIF(I15, TODAY(), "Y")),0) -> 3 | AA15: =IF(Z15="","", IFS(Z15 >= 61, "61+ años", Z15 >= 51, "51-60 años", Z15 >= 40, "40-50 años", Z15 >= 20, "20-39 años", TRUE, "-20 años")) -> -20 años
A16: ALEJANDRO ARTURO LOMELI OROZCO | B16: H | C16: Activo | D16: 44753 | E16: VI0002678022 | F16: =1674.59*2*7.65 -> 25621.227 | G16: UDIS | H16: Semestral | I16: 45024 | K16: TD | L16: Vida | M16: Orvi | N16: aa.lomeli8@gmail.com | O16: 3322278793 | P16: =IF(A16="","", "DARINKA UREÑA CASILLAS") -> DARINKA UREÑA CASILLAS | Q16: =IF(D16="","",VLOOKUP(MONTH(D16),Listas!$C$2:$D$14,2,0)) -> Julio | R16: =IF(D16="","",YEAR(D16)) -> 2022 | S16: =IF(D16="","",(DAY(D16))) -> 11 | T16: =IF(D16="","",S16-$W$1) -> 11 | U16: =IF(D16="","",(MONTH(D16))) -> 7 | V16: =IF(I16="","",(DAY(I16))) -> 8 | W16: =IF(I16="","",V16-$W$1) -> 8 | X16: =IF(I16="","",(MONTH(I16))) -> 4 | Y16: =IF(D16="","",(MONTH(D16))) -> 7 | Z16: =IFERROR(IF(I16="","", DATEDIF(I16, TODAY(), "Y")),0) -> 3 | AA16: =IF(Z16="","", IFS(Z16 >= 61, "61+ años", Z16 >= 51, "51-60 años", Z16 >= 40, "40-50 años", Z16 >= 20, "20-39 años", TRUE, "-20 años")) -> -20 años
A17: ALEJANDRO MORENO TRUJILLO | B17: H | C17: Activo | D17: 44581 | E17: GM0000551319 | F17: 25192.01 | G17: MXN | H17: Anual | I17: 44656 | K17: TC | L17: Gastos Médicos | M17: Practico | N17: alejandromorenotrujillo1@gmail.com | O17: 3324945143 | P17: =IF(A17="","", "DARINKA UREÑA CASILLAS") -> DARINKA UREÑA CASILLAS | Q17: =IF(D17="","",VLOOKUP(MONTH(D17),Listas!$C$2:$D$14,2,0)) -> Enero | R17: =IF(D17="","",YEAR(D17)) -> 2022 | S17: =IF(D17="","",(DAY(D17))) -> 20 | T17: =IF(D17="","",S17-$W$1) -> 20 | U17: =IF(D17="","",(MONTH(D17))) -> 1 | V17: =IF(I17="","",(DAY(I17))) -> 5 | W17: =IF(I17="","",V17-$W$1) -> 5 | X17: =IF(I17="","",(MONTH(I17))) -> 4 | Y17: =IF(D17="","",(MONTH(D17))) -> 1 | Z17: =IFERROR(IF(I17="","", DATEDIF(I17, TODAY(), "Y")),0) -> 4 | AA17: =IF(Z17="","", IFS(Z17 >= 61, "61+ años", Z17 >= 51, "51-60 años", Z17 >= 40, "40-50 años", Z17 >= 20, "20-39 años", TRUE, "-20 años")) -> -20 años
A18: ALEJANDRO MORENO TRUJILLO | B18: H | C18: Activo | D18: 44603 | E18: VI0002650072 | F18: =5531.93*2*7.65 -> 84638.529 | G18: UDIS | H18: Semestral | I18: 44656 | K18: TD | L18: Vida | M18: Orvi | N18: alejandromorenotrujillo1@gmail.com | O18: 3324945143 | P18: =IF(A18="","", "DARINKA UREÑA CASILLAS") -> DARINKA UREÑA CASILLAS | Q18: =IF(D18="","",VLOOKUP(MONTH(D18),Listas!$C$2:$D$14,2,0)) -> Febrero | R18: =IF(D18="","",YEAR(D18)) -> 2022 | S18: =IF(D18="","",(DAY(D18))) -> 11 | T18: =IF(D18="","",S18-$W$1) -> 11 | U18: =IF(D18="","",(MONTH(D18))) -> 2 | V18: =IF(I18="","",(DAY(I18))) -> 5 | W18: =IF(I18="","",V18-$W$1) -> 5 | X18: =IF(I18="","",(MONTH(I18))) -> 4 | Y18: =IF(D18="","",(MONTH(D18))) -> 2 | Z18: =IFERROR(IF(I18="","", DATEDIF(I18, TODAY(), "Y")),0) -> 4 | AA18: =IF(Z18="","", IFS(Z18 >= 61, "61+ años", Z18 >= 51, "51-60 años", Z18 >= 40, "40-50 años", Z18 >= 20, "20-39 años", TRUE, "-20 años")) -> -20 años
A19: ALEJANDRO SOTO ELIZALDE | B19: H | C19: Activo | D19: 44467 | E19: GM0000540142 | F19: 15641.78 | G19: MXN | H19: Semestral | I19: 44590 | K19: TD | L19: Gastos Médicos | M19: Integro | N19: soto.564@hotmail.com | O19: 3339561889 | P19: =IF(A19="","", "DARINKA UREÑA CASILLAS") -> DARINKA UREÑA CASILLAS | Q19: =IF(D19="","",VLOOKUP(MONTH(D19),Listas!$C$2:$D$14,2,0)) -> Septiembre | R19: =IF(D19="","",YEAR(D19)) -> 2021 | S19: =IF(D19="","",(DAY(D19))) -> 28 | T19: =IF(D19="","",S19-$W$1) -> 28 | U19: =IF(D19="","",(MONTH(D19))) -> 9 | V19: =IF(I19="","",(DAY(I19))) -> 29 | W19: =IF(I19="","",V19-$W$1) -> 29 | X19: =IF(I19="","",(MONTH(I19))) -> 1 | Y19: =IF(D19="","",(MONTH(D19))) -> 9 | Z19: =IFERROR(IF(I19="","", DATEDIF(I19, TODAY(), "Y")),0) -> 4 | AA19: =IF(Z19="","", IFS(Z19 >= 61, "61+ años", Z19 >= 51, "51-60 años", Z19 >= 40, "40-50 años", Z19 >= 20, "20-39 años", TRUE, "-20 años")) -> -20 años
A20: ALEJANDRO VAZQUEZ RODRIGUEZ | B20: H | C20: Activo | D20: 44042 | E20: VI0002546462 | F20: =324.24*12*7.65 -> 29765.232 | G20: UDIS | H20: Mensual | I20: 44769 | K20: TC | L20: Vida | M20: Orvi | N20: a.vazquez.rodriguez@outlook.com | O20: 3318332966 | P20: =IF(A20="","", "DARINKA UREÑA CASILLAS") -> DARINKA UREÑA CASILLAS | Q20: =IF(D20="","",VLOOKUP(MONTH(D20),Listas!$C$2:$D$14,2,0)) -> Julio | R20: =IF(D20="","",YEAR(D20)) -> 2020 | S20: =IF(D20="","",(DAY(D20))) -> 30 | T20: =IF(D20="","",S20-$W$1) -> 30 | U20: =IF(D20="","",(MONTH(D20))) -> 7 | V20: =IF(I20="","",(DAY(I20))) -> 27 | W20: =IF(I20="","",V20-$W$1) -> 27 | X20: =IF(I20="","",(MONTH(I20))) -> 7 | Y20: =IF(D20="","",(MONTH(D20))) -> 7 | Z20: =IFERROR(IF(I20="","", DATEDIF(I20, TODAY(), "Y")),0) -> 3 | AA20: =IF(Z20="","", IFS(Z20 >= 61, "61+ años", Z20 >= 51, "51-60 años", Z20 >= 40, "40-50 años", Z20 >= 20, "20-39 años", TRUE, "-20 años")) -> -20 años
A21: ALEXA GISELLE INFANTE JAIME | B21: M | C21: Activo | D21: 44125 | E21: GM0000496075 | F21: =1542.83*12 -> 18513.96 | G21: MXN | H21: Mensual | I21: 44634 | K21: TC | L21: Gastos Médicos | M21: Practico | N21: giselleinfante92@gmail.com | O21: 3312415016 | P21: =IF(A21="","", "DARINKA UREÑA CASILLAS") -> DARINKA UREÑA CASILLAS | Q21: =IF(D21="","",VLOOKUP(MONTH(D21),Listas!$C$2:$D$14,2,0)) -> Octubre | R21: =IF(D21="","",YEAR(D21)) -> 2020 | S21: =IF(D21="","",(DAY(D21))) -> 21 | T21: =IF(D21="","",S21-$W$1) -> 21 | U21: =IF(D21="","",(MONTH(D21))) -> 10 | V21: =IF(I21="","",(DAY(I21))) -> 14 | W21: =IF(I21="","",V21-$W$1) -> 14 | X21: =IF(I21="","",(MONTH(I21))) -> 3 | Y21: =IF(D21="","",(MONTH(D21))) -> 10 | Z21: =IFERROR(IF(I21="","", DATEDIF(I21, TODAY(), "Y")),0) -> 4 | AA21: =IF(Z21="","", IFS(Z21 >= 61, "61+ años", Z21 >= 51, "51-60 años", Z21 >= 40, "40-50 años", Z21 >= 20, "20-39 años", TRUE, "-20 años")) -> -20 años
A22: ANA KAREN MUÑIZ CHAVEZ | B22: M | C22: Activo | D22: 44241 | E22: GM0000513096 | F22: =1542.83*12 -> 18513.96 | G22: MXN | H22: Mensual | I22: 44801 | K22: TD | L22: Gastos Médicos | M22: Practico | N22: lupithamuniz0015@gmail.com | O22: 3314946421 | P22: =IF(A22="","", "DARINKA UREÑA CASILLAS") -> DARINKA UREÑA CASILLAS | Q22: =IF(D22="","",VLOOKUP(MONTH(D22),Listas!$C$2:$D$14,2,0)) -> Febrero | R22: =IF(D22="","",YEAR(D22)) -> 2021 | S22: =IF(D22="","",(DAY(D22))) -> 14 | T22: =IF(D22="","",S22-$W$1) -> 14 | U22: =IF(D22="","",(MONTH(D22))) -> 2 | V22: =IF(I22="","",(DAY(I22))) -> 28 | W22: =IF(I22="","",V22-$W$1) -> 28 | X22: =IF(I22="","",(MONTH(I22))) -> 8 | Y22: =IF(D22="","",(MONTH(D22))) -> 2 | Z22: =IFERROR(IF(I22="","", DATEDIF(I22, TODAY(), "Y")),0) -> 3 | AA22: =IF(Z22="","", IFS(Z22 >= 61, "61+ años", Z22 >= 51, "51-60 años", Z22 >= 40, "40-50 años", Z22 >= 20, "20-39 años", TRUE, "-20 años")) -> -20 años
A23: ANA PAULA GONZALEZ LUNA NIÑO | B23: M | C23: Activo | D23: 44146 | E23: VI0002566080 | F23: =320.91*12*7.118 -> 27410.849 | G23: UDIS | H23: Mensual | I23: 44804 | K23: TD | L23: Vida | M23: Orvi | N23: apgln@hotmail.com | O23: 3312799019 | P23: =IF(A23="","", "DARINKA UREÑA CASILLAS") -> DARINKA UREÑA CASILLAS | Q23: =IF(D23="","",VLOOKUP(MONTH(D23),Listas!$C$2:$D$14,2,0)) -> Noviembre | R23: =IF(D23="","",YEAR(D23)) -> 2020 | S23: =IF(D23="","",(DAY(D23))) -> 11 | T23: =IF(D23="","",S23-$W$1) -> 11 | U23: =IF(D23="","",(MONTH(D23))) -> 11 | V23: =IF(I23="","",(DAY(I23))) -> 31 | W23: =IF(I23="","",V23-$W$1) -> 31 | X23: =IF(I23="","",(MONTH(I23))) -> 8 | Y23: =IF(D23="","",(MONTH(D23))) -> 11 | Z23: =IFERROR(IF(I23="","", DATEDIF(I23, TODAY(), "Y")),0) -> 3 | AA23: =IF(Z23="","", IFS(Z23 >= 61, "61+ años", Z23 >= 51, "51-60 años", Z23 >= 40, "40-50 años", Z23 >= 20, "20-39 años", TRUE, "-20 años")) -> -20 años
A24: ANDREA HERNANDEZ MERCADO | B24: M | C24: Activo | D24: 44278 | E24: VI0002591407 | F24: =2143.12*7.118 -> 15254.728 | G24: UDIS | H24: ANUAL | I24: 06-sep | K24: TC | L24: Vida | M24: Orvi | N24: andreahdz_09@hotmail.com | O24: 3353312319 | P24: =IF(A24="","", "DARINKA UREÑA CASILLAS") -> DARINKA UREÑA CASILLAS | Q24: =IF(D24="","",VLOOKUP(MONTH(D24),Listas!$C$2:$D$14,2,0)) -> Marzo | R24: =IF(D24="","",YEAR(D24)) -> 2021 | S24: =IF(D24="","",(DAY(D24))) -> 23 | T24: =IF(D24="","",S24-$W$1) -> 23 | U24: =IF(D24="","",(MONTH(D24))) -> 3 | V24: =IF(I24="","",(DAY(I24))) -> 6 | W24: =IF(I24="","",V24-$W$1) -> 6 | X24: =IF(I24="","",(MONTH(I24))) -> 9 | Y24: =IF(D24="","",(MONTH(D24))) -> 3 | Z24: =IFERROR(IF(I24="","", DATEDIF(I24, TODAY(), "Y")),0) -> 0 | AA24: =IF(Z24="","", IFS(Z24 >= 61, "61+ años", Z24 >= 51, "51-60 años", Z24 >= 40, "40-50 años", Z24 >= 20, "20-39 años", TRUE, "-20 años")) -> -20 años
A25: ANGELICA ALEJANDRA SANCHEZ DURAN | B25: M | C25: Activo | D25: 44185 | E25: VI0002573965 | F25: =709.12*4*7.118 -> 20190.065 | G25: UDIS | H25: Trimestral | I25: 44596 | K25: TC | L25: Vida | M25: Orvi | N25: angelicaduran.4@hotmail.com | O25: 3314077658 | P25: =IF(A25="","", "DARINKA UREÑA CASILLAS") -> DARINKA UREÑA CASILLAS | Q25: =IF(D25="","",VLOOKUP(MONTH(D25),Listas!$C$2:$D$14,2,0)) -> Diciembre | R25: =IF(D25="","",YEAR(D25)) -> 2020 | S25: =IF(D25="","",(DAY(D25))) -> 20 | T25: =IF(D25="","",S25-$W$1) -> 20 | U25: =IF(D25="","",(MONTH(D25))) -> 12 | V25: =IF(I25="","",(DAY(I25))) -> 4 | W25: =IF(I25="","",V25-$W$1) -> 4 | X25: =IF(I25="","",(MONTH(I25))) -> 2 | Y25: =IF(D25="","",(MONTH(D25))) -> 12 | Z25: =IFERROR(IF(I25="","", DATEDIF(I25, TODAY(), "Y")),0) -> 4 | AA25: =IF(Z25="","", IFS(Z25 >= 61, "61+ años", Z25 >= 51, "51-60 años", Z25 >= 40, "40-50 años", Z25 >= 20, "20-39 años", TRUE, "-20 años")) -> -20 años
A26: ARNOLD SANCHEZ SANCHEZ | B26: H | C26: Activo | D26: 43878 | E26: VI0002517934 | F26: =163.05*12*7.118 -> 13927.079 | G26: UDIS | H26: Mensual | I26: 44605 | K26: TC | L26: Vida | M26: Orvi | N26: sanchez.201024835@outlook.com | O26: 2223716744 | P26: =IF(A26="","", "DARINKA UREÑA CASILLAS") -> DARINKA UREÑA CASILLAS | Q26: =IF(D26="","",VLOOKUP(MONTH(D26),Listas!$C$2:$D$14,2,0)) -> Febrero | R26: =IF(D26="","",YEAR(D26)) -> 2020 | S26: =IF(D26="","",(DAY(D26))) -> 17 | T26: =IF(D26="","",S26-$W$1) -> 17 | U26: =IF(D26="","",(MONTH(D26))) -> 2 | V26: =IF(I26="","",(DAY(I26))) -> 13 | W26: =IF(I26="","",V26-$W$1) -> 13 | X26: =IF(I26="","",(MONTH(I26))) -> 2 | Y26: =IF(D26="","",(MONTH(D26))) -> 2 | Z26: =IFERROR(IF(I26="","", DATEDIF(I26, TODAY(), "Y")),0) -> 4 | AA26: =IF(Z26="","", IFS(Z26 >= 61, "61+ años", Z26 >= 51, "51-60 años", Z26 >= 40, "40-50 años", Z26 >= 20, "20-39 años", TRUE, "-20 años")) -> -20 años
A27: BERNARDO GARCIA GOMEZ | B27: H | C27: Activo | D27: 44859 | E27: VI0002697696 | F27: =7989.92*7.65 -> 61122.888 | G27: UDIS | H27: Anual | I27: 45225 | K27: TC | L27: Vida | M27: Imagina ser | N27: bernigarcia365@icloud.com | O27: 3317070106 | P27: =IF(A27="","", "DARINKA UREÑA CASILLAS") -> DARINKA UREÑA CASILLAS | Q27: =IF(D27="","",VLOOKUP(MONTH(D27),Listas!$C$2:$D$14,2,0)) -> Octubre | R27: =IF(D27="","",YEAR(D27)) -> 2022 | S27: =IF(D27="","",(DAY(D27))) -> 25 | T27: =IF(D27="","",S27-$W$1) -> 25 | U27: =IF(D27="","",(MONTH(D27))) -> 10 | V27: =IF(I27="","",(DAY(I27))) -> 26 | W27: =IF(I27="","",V27-$W$1) -> 26 | X27: =IF(I27="","",(MONTH(I27))) -> 10 | Y27: =IF(D27="","",(MONTH(D27))) -> 10 | Z27: =IFERROR(IF(I27="","", DATEDIF(I27, TODAY(), "Y")),0) -> 2 | AA27: =IF(Z27="","", IFS(Z27 >= 61, "61+ años", Z27 >= 51, "51-60 años", Z27 >= 40, "40-50 años", Z27 >= 20, "20-39 años", TRUE, "-20 años")) -> -20 años
A28: BERNARDO GARCIA GOMEZ | B28: H | C28: Activo | D28: 44859 | E28: VI0002698084 | F28: =3187.51*7.65 -> 24384.451 | G28: UDIS | H28: Anual | I28: 45225 | K28: TC | L28: Vida | M28: Orvi | N28: bernigarcia365@icloud.com | O28: 3317070106 | P28: =IF(A28="","", "DARINKA UREÑA CASILLAS") -> DARINKA UREÑA CASILLAS | Q28: =IF(D28="","",VLOOKUP(MONTH(D28),Listas!$C$2:$D$14,2,0)) -> Octubre | R28: =IF(D28="","",YEAR(D28)) -> 2022 | S28: =IF(D28="","",(DAY(D28))) -> 25 | T28: =IF(D28="","",S28-$W$1) -> 25 | U28: =IF(D28="","",(MONTH(D28))) -> 10 | V28: =IF(I28="","",(DAY(I28))) -> 26 | W28: =IF(I28="","",V28-$W$1) -> 26 | X28: =IF(I28="","",(MONTH(I28))) -> 10 | Y28: =IF(D28="","",(MONTH(D28))) -> 10 | Z28: =IFERROR(IF(I28="","", DATEDIF(I28, TODAY(), "Y")),0) -> 2 | AA28: =IF(Z28="","", IFS(Z28 >= 61, "61+ años", Z28 >= 51, "51-60 años", Z28 >= 40, "40-50 años", Z28 >= 20, "20-39 años", TRUE, "-20 años")) -> -20 años
A29: BETH SUA MONTEJANO CARMONA | B29: M | C29: Activo | D29: 44104 | E29: VI0002558023 | F29: =3665.66*7.118 -> 26092.168 | G29: UDIS | H29: Anual | I29: 17-sep | K29: TC | L29: Vida | M29: Orvi | N29: moncar1709@gmail.com | O29: 3313875424 | P29: =IF(A29="","", "DARINKA UREÑA CASILLAS") -> DARINKA UREÑA CASILLAS | Q29: =IF(D29="","",VLOOKUP(MONTH(D29),Listas!$C$2:$D$14,2,0)) -> Septiembre | R29: =IF(D29="","",YEAR(D29)) -> 2020 | S29: =IF(D29="","",(DAY(D29))) -> 30 | T29: =IF(D29="","",S29-$W$1) -> 30 | U29: =IF(D29="","",(MONTH(D29))) -> 9 | V29: =IF(I29="","",(DAY(I29))) -> 17 | W29: =IF(I29="","",V29-$W$1) -> 17 | X29: =IF(I29="","",(MONTH(I29))) -> 9 | Y29: =IF(D29="","",(MONTH(D29))) -> 9 | Z29: =IFERROR(IF(I29="","", DATEDIF(I29, TODAY(), "Y")),0) -> 0 | AA29: =IF(Z29="","", IFS(Z29 >= 61, "61+ años", Z29 >= 51, "51-60 años", Z29 >= 40, "40-50 años", Z29 >= 20, "20-39 años", TRUE, "-20 años")) -> -20 años
A30: BLANCA CAROLINA MAGAÑA CASTELLON | B30: M | C30: Activo | D30: 44930 | E30: GM0000588897 | F30: =8616.38*4 -> 34465.52 | G30: MXN | H30: Trimestral | I30: 45131 | K30: AGENTE | L30: Gastos Médicos | M30: Integro | N30: aideflores.arellano@gmail.com | O30: 3314239602 | P30: =IF(A30="","", "DARINKA UREÑA CASILLAS") -> DARINKA UREÑA CASILLAS | Q30: =IF(D30="","",VLOOKUP(MONTH(D30),Listas!$C$2:$D$14,2,0)) -> Enero | R30: =IF(D30="","",YEAR(D30)) -> 2023 | S30: =IF(D30="","",(DAY(D30))) -> 4 | T30: =IF(D30="","",S30-$W$1) -> 4 | U30: =IF(D30="","",(MONTH(D30))) -> 1 | V30: =IF(I30="","",(DAY(I30))) -> 24 | W30: =IF(I30="","",V30-$W$1) -> 24 | X30: =IF(I30="","",(MONTH(I30))) -> 7 | Y30: =IF(D30="","",(MONTH(D30))) -> 1 | Z30: =IFERROR(IF(I30="","", DATEDIF(I30, TODAY(), "Y")),0) -> 2 | AA30: =IF(Z30="","", IFS(Z30 >= 61, "61+ años", Z30 >= 51, "51-60 años", Z30 >= 40, "40-50 años", Z30 >= 20, "20-39 años", TRUE, "-20 años")) -> -20 años
A31: CARLA ANDREA MARTINEZ LAGOS | B31: M | C31: Activo | D31: 44632 | E31: VI0002654798 | F31: 36597.675 | G31: UDIS | H31: Anual | I31: 44938 | K31: TD | L31: Vida | M31: Orvi | N31: carla.martineez@hotmail.com | O31: 3334453680 | P31: =IF(A31="","", "DARINKA UREÑA CASILLAS") -> DARINKA UREÑA CASILLAS | Q31: =IF(D31="","",VLOOKUP(MONTH(D31),Listas!$C$2:$D$14,2,0)) -> Marzo | R31: =IF(D31="","",YEAR(D31)) -> 2022 | S31: =IF(D31="","",(DAY(D31))) -> 12 | T31: =IF(D31="","",S31-$W$1) -> 12 | U31: =IF(D31="","",(MONTH(D31))) -> 3 | V31: =IF(I31="","",(DAY(I31))) -> 12 | W31: =IF(I31="","",V31-$W$1) -> 12 | X31: =IF(I31="","",(MONTH(I31))) -> 1 | Y31: =IF(D31="","",(MONTH(D31))) -> 3 | Z31: =IFERROR(IF(I31="","", DATEDIF(I31, TODAY(), "Y")),0) -> 3 | AA31: =IF(Z31="","", IFS(Z31 >= 61, "61+ años", Z31 >= 51, "51-60 años", Z31 >= 40, "40-50 años", Z31 >= 20, "20-39 años", TRUE, "-20 años")) -> -20 años
A32: CARLOS ALBERTO MORALES NOGUEDA | B32: M | C32: Activo | D32: 44773 | E32: VI0002682439 | F32: =3240*7.65 -> 24786 | G32: UDIS | H32: Anual | I32: 44989 | K32: TC | L32: Vida | M32: Segubeca | N32: walazamn@hotmail.com | O32: 3314537802 | P32: =IF(A32="","", "DARINKA UREÑA CASILLAS") -> DARINKA UREÑA CASILLAS | Q32: =IF(D32="","",VLOOKUP(MONTH(D32),Listas!$C$2:$D$14,2,0)) -> Julio | R32: =IF(D32="","",YEAR(D32)) -> 2022 | S32: =IF(D32="","",(DAY(D32))) -> 31 | T32: =IF(D32="","",S32-$W$1) -> 31 | U32: =IF(D32="","",(MONTH(D32))) -> 7 | V32: =IF(I32="","",(DAY(I32))) -> 4 | W32: =IF(I32="","",V32-$W$1) -> 4 | X32: =IF(I32="","",(MONTH(I32))) -> 3 | Y32: =IF(D32="","",(MONTH(D32))) -> 7 | Z32: =IFERROR(IF(I32="","", DATEDIF(I32, TODAY(), "Y")),0) -> 3 | AA32: =IF(Z32="","", IFS(Z32 >= 61, "61+ años", Z32 >= 51, "51-60 años", Z32 >= 40, "40-50 años", Z32 >= 20, "20-39 años", TRUE, "-20 años")) -> -20 años
A33: CARLOS CASTRO PALAZUELOS | B33: H | C33: Activo | D33: 44677 | E33: VI0002662475 | F33: =441.69*12*7.31 -> 38745.047 | G33: UDIS | H33: Mensual | I33: 45101 | K33: TC | L33: Vida | M33: Orvi | N33: tekilopalazuelos@gmail.com | O33: 9985779227 | P33: =IF(A33="","", "DARINKA UREÑA CASILLAS") -> DARINKA UREÑA CASILLAS | Q33: =IF(D33="","",VLOOKUP(MONTH(D33),Listas!$C$2:$D$14,2,0)) -> Abril | R33: =IF(D33="","",YEAR(D33)) -> 2022 | S33: =IF(D33="","",(DAY(D33))) -> 26 | T33: =IF(D33="","",S33-$W$1) -> 26 | U33: =IF(D33="","",(MONTH(D33))) -> 4 | V33: =IF(I33="","",(DAY(I33))) -> 24 | W33: =IF(I33="","",V33-$W$1) -> 24 | X33: =IF(I33="","",(MONTH(I33))) -> 6 | Y33: =IF(D33="","",(MONTH(D33))) -> 4 | Z33: =IFERROR(IF(I33="","", DATEDIF(I33, TODAY(), "Y")),0) -> 2 | AA33: =IF(Z33="","", IFS(Z33 >= 61, "61+ años", Z33 >= 51, "51-60 años", Z33 >= 40, "40-50 años", Z33 >= 20, "20-39 años", TRUE, "-20 años")) -> -20 años
A34: CARLOS DAVID AVILA URRUCHUA | B34: H | C34: Activo | D34: 44389 | E34: VI0002613039 | F34: =793.59*12*7.118 -> 67785.283 | G34: UDIS | H34: Mensual | I34: 12-sep | K34: TD | L34: Vida | M34: Segubeca | N34: carlos_a_u@hotmail.com | O34: 9841309280 | P34: =IF(A34="","", "DARINKA UREÑA CASILLAS") -> DARINKA UREÑA CASILLAS | Q34: =IF(D34="","",VLOOKUP(MONTH(D34),Listas!$C$2:$D$14,2,0)) -> Julio | R34: =IF(D34="","",YEAR(D34)) -> 2021 | S34: =IF(D34="","",(DAY(D34))) -> 12 | T34: =IF(D34="","",S34-$W$1) -> 12 | U34: =IF(D34="","",(MONTH(D34))) -> 7 | V34: =IF(I34="","",(DAY(I34))) -> 12 | W34: =IF(I34="","",V34-$W$1) -> 12 | X34: =IF(I34="","",(MONTH(I34))) -> 9 | Y34: =IF(D34="","",(MONTH(D34))) -> 7 | Z34: =IFERROR(IF(I34="","", DATEDIF(I34, TODAY(), "Y")),0) -> 0 | AA34: =IF(Z34="","", IFS(Z34 >= 61, "61+ años", Z34 >= 51, "51-60 años", Z34 >= 40, "40-50 años", Z34 >= 20, "20-39 años", TRUE, "-20 años")) -> -20 años
A35: CARLOS HUMBERTO VILLANUEVA CARMONA | B35: H | C35: Activo | D35: 44646 | E35: VI0002657416 | F35: =228.16*12*7.24 -> 19822.541 | G35: UDIS | H35: Mensual | I35: 44810 | K35: TC | L35: Vida | M35: Orvi | N35: carloshum3888@gmail.com | O35: 3313033649 | P35: =IF(A35="","", "DARINKA UREÑA CASILLAS") -> DARINKA UREÑA CASILLAS | Q35: =IF(D35="","",VLOOKUP(MONTH(D35),Listas!$C$2:$D$14,2,0)) -> Marzo | R35: =IF(D35="","",YEAR(D35)) -> 2022 | S35: =IF(D35="","",(DAY(D35))) -> 26 | T35: =IF(D35="","",S35-$W$1) -> 26 | U35: =IF(D35="","",(MONTH(D35))) -> 3 | V35: =IF(I35="","",(DAY(I35))) -> 6 | W35: =IF(I35="","",V35-$W$1) -> 6 | X35: =IF(I35="","",(MONTH(I35))) -> 9 | Y35: =IF(D35="","",(MONTH(D35))) -> 3 | Z35: =IFERROR(IF(I35="","", DATEDIF(I35, TODAY(), "Y")),0) -> 3 | AA35: =IF(Z35="","", IFS(Z35 >= 61, "61+ años", Z35 >= 51, "51-60 años", Z35 >= 40, "40-50 años", Z35 >= 20, "20-39 años", TRUE, "-20 años")) -> -20 años
A36: CARLOS VERDUZO FAVELA | B36: H | C36: Activo | D36: 44831 | E36: VI0002692302 | F36: =2540.52*2*7.65 -> 38869.956 | G36: UDIS | H36: Semestral | I36: 45137 | K36: TD | L36: Vida | M36: Orvi | N36: carlos.verduzcof@gmail.com | O36: 3316696345 | P36: =IF(A36="","", "DARINKA UREÑA CASILLAS") -> DARINKA UREÑA CASILLAS | Q36: =IF(D36="","",VLOOKUP(MONTH(D36),Listas!$C$2:$D$14,2,0)) -> Septiembre | R36: =IF(D36="","",YEAR(D36)) -> 2022 | S36: =IF(D36="","",(DAY(D36))) -> 27 | T36: =IF(D36="","",S36-$W$1) -> 27 | U36: =IF(D36="","",(MONTH(D36))) -> 9 | V36: =IF(I36="","",(DAY(I36))) -> 30 | W36: =IF(I36="","",V36-$W$1) -> 30 | X36: =IF(I36="","",(MONTH(I36))) -> 7 | Y36: =IF(D36="","",(MONTH(D36))) -> 9 | Z36: =IFERROR(IF(I36="","", DATEDIF(I36, TODAY(), "Y")),0) -> 2 | AA36: =IF(Z36="","", IFS(Z36 >= 61, "61+ años", Z36 >= 51, "51-60 años", Z36 >= 40, "40-50 años", Z36 >= 20, "20-39 años", TRUE, "-20 años")) -> -20 años
A37: CARLOS XAVIER BARBA LOPEZ | B37: H | C37: Activo | D37: 44560 | E37: GM0000549543 | F37: =4581.86*4 -> 18327.44 | G37: MXN | H37: Trimestral | I37: 44713 | K37: TD | L37: Gastos Médicos | M37: Integro | N37: eagletijuana@gmail.com | O37: 3324962545 | P37: =IF(A37="","", "DARINKA UREÑA CASILLAS") -> DARINKA UREÑA CASILLAS | Q37: =IF(D37="","",VLOOKUP(MONTH(D37),Listas!$C$2:$D$14,2,0)) -> Diciembre | R37: =IF(D37="","",YEAR(D37)) -> 2021 | S37: =IF(D37="","",(DAY(D37))) -> 30 | T37: =IF(D37="","",S37-$W$1) -> 30 | U37: =IF(D37="","",(MONTH(D37))) -> 12 | V37: =IF(I37="","",(DAY(I37))) -> 1 | W37: =IF(I37="","",V37-$W$1) -> 1 | X37: =IF(I37="","",(MONTH(I37))) -> 6 | Y37: =IF(D37="","",(MONTH(D37))) -> 12 | Z37: =IFERROR(IF(I37="","", DATEDIF(I37, TODAY(), "Y")),0) -> 3 | AA37: =IF(Z37="","", IFS(Z37 >= 61, "61+ años", Z37 >= 51, "51-60 años", Z37 >= 40, "40-50 años", Z37 >= 20, "20-39 años", TRUE, "-20 años")) -> -20 años
A38: CECILIA ARCEO CERVANTES | B38: M | C38: Activo | D38: 44333 | E38: VI0002601742 | F38: =2266.93*2*7.118 -> 32272.015 | G38: UDIS | H38: Semestral | I38: 44877 | K38: TC | L38: Vida | M38: Orvi | N38: cecyarceo@hotmail.com | O38: 3311741926 | P38: =IF(A38="","", "DARINKA UREÑA CASILLAS") -> DARINKA UREÑA CASILLAS | Q38: =IF(D38="","",VLOOKUP(MONTH(D38),Listas!$C$2:$D$14,2,0)) -> Mayo | R38: =IF(D38="","",YEAR(D38)) -> 2021 | S38: =IF(D38="","",(DAY(D38))) -> 17 | T38: =IF(D38="","",S38-$W$1) -> 17 | U38: =IF(D38="","",(MONTH(D38))) -> 5 | V38: =IF(I38="","",(DAY(I38))) -> 12 | W38: =IF(I38="","",V38-$W$1) -> 12 | X38: =IF(I38="","",(MONTH(I38))) -> 11 | Y38: =IF(D38="","",(MONTH(D38))) -> 5 | Z38: =IFERROR(IF(I38="","", DATEDIF(I38, TODAY(), "Y")),0) -> 3 | AA38: =IF(Z38="","", IFS(Z38 >= 61, "61+ años", Z38 >= 51, "51-60 años", Z38 >= 40, "40-50 años", Z38 >= 20, "20-39 años", TRUE, "-20 años")) -> -20 años
A39: CESAR ISRRAEL HERNANDEZ SANCHEZ | B39: H | C39: Activo | D39: 44728 | E39: VI0002672529 | F39: =3194.49*4*7.41 -> 94684.684 | G39: UDIS | H39: Trimestral | I39: 45163 | K39: TD | L39: Vida | M39: Orvi | N39: cesar25941@outlook.com | O39: 3311249925 | P39: =IF(A39="","", "DARINKA UREÑA CASILLAS") -> DARINKA UREÑA CASILLAS | Q39: =IF(D39="","",VLOOKUP(MONTH(D39),Listas!$C$2:$D$14,2,0)) -> Junio | R39: =IF(D39="","",YEAR(D39)) -> 2022 | S39: =IF(D39="","",(DAY(D39))) -> 16 | T39: =IF(D39="","",S39-$W$1) -> 16 | U39: =IF(D39="","",(MONTH(D39))) -> 6 | V39: =IF(I39="","",(DAY(I39))) -> 25 | W39: =IF(I39="","",V39-$W$1) -> 25 | X39: =IF(I39="","",(MONTH(I39))) -> 8 | Y39: =IF(D39="","",(MONTH(D39))) -> 6 | Z39: =IFERROR(IF(I39="","", DATEDIF(I39, TODAY(), "Y")),0) -> 2 | AA39: =IF(Z39="","", IFS(Z39 >= 61, "61+ años", Z39 >= 51, "51-60 años", Z39 >= 40, "40-50 años", Z39 >= 20, "20-39 años", TRUE, "-20 años")) -> -20 años
A40: CESAR ISRRAEL HERNANDEZ SANCHEZ | B40: M | C40: Activo | D40: 44755 | E40: VI0002678390 | F40: =1091.28*2*7.41 -> 16172.77 | G40: UDIS | H40: Semestral | I40: 45127 | K40: TD | L40: Vida | M40: Orvi | N40: cesar25941@outlook.com | O40: 3311249925 | P40: =IF(A40="","", "DARINKA UREÑA CASILLAS") -> DARINKA UREÑA CASILLAS | Q40: =IF(D40="","",VLOOKUP(MONTH(D40),Listas!$C$2:$D$14,2,0)) -> Julio | R40: =IF(D40="","",YEAR(D40)) -> 2022 | S40: =IF(D40="","",(DAY(D40))) -> 13 | T40: =IF(D40="","",S40-$W$1) -> 13 | U40: =IF(D40="","",(MONTH(D40))) -> 7 | V40: =IF(I40="","",(DAY(I40))) -> 20 | W40: =IF(I40="","",V40-$W$1) -> 20 | X40: =IF(I40="","",(MONTH(I40))) -> 7 | Y40: =IF(D40="","",(MONTH(D40))) -> 7 | Z40: =IFERROR(IF(I40="","", DATEDIF(I40, TODAY(), "Y")),0) -> 2 | AA40: =IF(Z40="","", IFS(Z40 >= 61, "61+ años", Z40 >= 51, "51-60 años", Z40 >= 40, "40-50 años", Z40 >= 20, "20-39 años", TRUE, "-20 años")) -> -20 años
A41: CINTHIA NOEMI JASSO TORRES | B41: M | C41: Activo | D41: 44826 | E41: VI0002690934 | F41: =425.4*7.65*12 -> 39051.72 | G41: UDIS | H41: Mensual | I41: 45276 | K41: TC | L41: Vida | M41: Orvi | N41: noemijass1982@gmail.com | O41: 3321643018 | P41: =IF(A41="","", "DARINKA UREÑA CASILLAS") -> DARINKA UREÑA CASILLAS | Q41: =IF(D41="","",VLOOKUP(MONTH(D41),Listas!$C$2:$D$14,2,0)) -> Septiembre | R41: =IF(D41="","",YEAR(D41)) -> 2022 | S41: =IF(D41="","",(DAY(D41))) -> 22 | T41: =IF(D41="","",S41-$W$1) -> 22 | U41: =IF(D41="","",(MONTH(D41))) -> 9 | V41: =IF(I41="","",(DAY(I41))) -> 16 | W41: =IF(I41="","",V41-$W$1) -> 16 | X41: =IF(I41="","",(MONTH(I41))) -> 12 | Y41: =IF(D41="","",(MONTH(D41))) -> 9 | Z41: =IFERROR(IF(I41="","", DATEDIF(I41, TODAY(), "Y")),0) -> 2 | AA41: =IF(Z41="","", IFS(Z41 >= 61, "61+ años", Z41 >= 51, "51-60 años", Z41 >= 40, "40-50 años", Z41 >= 20, "20-39 años", TRUE, "-20 años")) -> -20 años
A42: CLAUDIO ALBERTO MARTIN LOPEZ | B42: H | C42: Activo | D42: 44616 | E42: VI0002652270 | F42: 60000 | G42: UDIS | H42: Semestral | I42: 44952 | K42: TC | L42: Vida | M42: Orvi | N42: innsmouth26@gmail.com | O42: 3311582572 | P42: =IF(A42="","", "DARINKA UREÑA CASILLAS") -> DARINKA UREÑA CASILLAS | Q42: =IF(D42="","",VLOOKUP(MONTH(D42),Listas!$C$2:$D$14,2,0)) -> Febrero | R42: =IF(D42="","",YEAR(D42)) -> 2022 | S42: =IF(D42="","",(DAY(D42))) -> 24 | T42: =IF(D42="","",S42-$W$1) -> 24 | U42: =IF(D42="","",(MONTH(D42))) -> 2 | V42: =IF(I42="","",(DAY(I42))) -> 26 | W42: =IF(I42="","",V42-$W$1) -> 26 | X42: =IF(I42="","",(MONTH(I42))) -> 1 | Y42: =IF(D42="","",(MONTH(D42))) -> 2 | Z42: =IFERROR(IF(I42="","", DATEDIF(I42, TODAY(), "Y")),0) -> 3 | AA42: =IF(Z42="","", IFS(Z42 >= 61, "61+ años", Z42 >= 51, "51-60 años", Z42 >= 40, "40-50 años", Z42 >= 20, "20-39 años", TRUE, "-20 años")) -> -20 años
A43: CRISTINA GUADALUPE ALVAREZ HERNANDEZ | B43: M | C43: Activo | D43: 44439 | E43: GM0000537417 | F43: 18615.96 | G43: MXN | H43: Anual | I43: 16-sep | K43: TC | L43: Gastos Médicos | M43: Practico | N43: crig91@hotmail.com | O43: 3315709079 | P43: =IF(A43="","", "DARINKA UREÑA CASILLAS") -> DARINKA UREÑA CASILLAS | Q43: =IF(D43="","",VLOOKUP(MONTH(D43),Listas!$C$2:$D$14,2,0)) -> Agosto | R43: =IF(D43="","",YEAR(D43)) -> 2021 | S43: =IF(D43="","",(DAY(D43))) -> 31 | T43: =IF(D43="","",S43-$W$1) -> 31 | U43: =IF(D43="","",(MONTH(D43))) -> 8 | V43: =IF(I43="","",(DAY(I43))) -> 16 | W43: =IF(I43="","",V43-$W$1) -> 16 | X43: =IF(I43="","",(MONTH(I43))) -> 9 | Y43: =IF(D43="","",(MONTH(D43))) -> 8 | Z43: =IFERROR(IF(I43="","", DATEDIF(I43, TODAY(), "Y")),0) -> 0 | AA43: =IF(Z43="","", IFS(Z43 >= 61, "61+ años", Z43 >= 51, "51-60 años", Z43 >= 40, "40-50 años", Z43 >= 20, "20-39 años", TRUE, "-20 años")) -> -20 años
A44: CRISTINA LETICIA RODRIGUEZ DE LA TORRE | B44: M | C44: Activo | D44: 44916 | E44: VI0002709431 | F44: =11079.55*7.65 -> 84758.557 | G44: UDIS | H44: Anual | I44: 45006 | K44: TC | L44: Vida | M44: Nuevo Plenitud | N44: cristinarodriguezdelatorre@gmail.com | O44: 6142212111 | P44: =IF(A44="","", "DARINKA UREÑA CASILLAS") -> DARINKA UREÑA CASILLAS | Q44: =IF(D44="","",VLOOKUP(MONTH(D44),Listas!$C$2:$D$14,2,0)) -> Diciembre | R44: =IF(D44="","",YEAR(D44)) -> 2022 | S44: =IF(D44="","",(DAY(D44))) -> 21 | T44: =IF(D44="","",S44-$W$1) -> 21 | U44: =IF(D44="","",(MONTH(D44))) -> 12 | V44: =IF(I44="","",(DAY(I44))) -> 21 | W44: =IF(I44="","",V44-$W$1) -> 21 | X44: =IF(I44="","",(MONTH(I44))) -> 3 | Y44: =IF(D44="","",(MONTH(D44))) -> 12 | Z44: =IFERROR(IF(I44="","", DATEDIF(I44, TODAY(), "Y")),0) -> 3 | AA44: =IF(Z44="","", IFS(Z44 >= 61, "61+ años", Z44 >= 51, "51-60 años", Z44 >= 40, "40-50 años", Z44 >= 20, "20-39 años", TRUE, "-20 años")) -> -20 años
A45: CYNTHIA ELIZABETH MORALES ORTEGA | B45: M | C45: Activo | D45: 44224 | E45: GM0000510955 | F45: =5363.44*2 -> 10726.88 | G45: MXN | H45: Semestral | I45: 44796 | K45: TD | L45: Gastos Médicos | M45: Practico | N45: cynthi_lizi@hotmail.com | O45: 3329196044 | P45: =IF(A45="","", "DARINKA UREÑA CASILLAS") -> DARINKA UREÑA CASILLAS | Q45: =IF(D45="","",VLOOKUP(MONTH(D45),Listas!$C$2:$D$14,2,0)) -> Enero | R45: =IF(D45="","",YEAR(D45)) -> 2021 | S45: =IF(D45="","",(DAY(D45))) -> 28 | T45: =IF(D45="","",S45-$W$1) -> 28 | U45: =IF(D45="","",(MONTH(D45))) -> 1 | V45: =IF(I45="","",(DAY(I45))) -> 23 | W45: =IF(I45="","",V45-$W$1) -> 23 | X45: =IF(I45="","",(MONTH(I45))) -> 8 | Y45: =IF(D45="","",(MONTH(D45))) -> 1 | Z45: =IFERROR(IF(I45="","", DATEDIF(I45, TODAY(), "Y")),0) -> 3 | AA45: =IF(Z45="","", IFS(Z45 >= 61, "61+ años", Z45 >= 51, "51-60 años", Z45 >= 40, "40-50 años", Z45 >= 20, "20-39 años", TRUE, "-20 años")) -> -20 años
A46: CYNTHIA ELIZABETH MORALES ORTEGA | B46: M | C46: Activo | D46: 44225 | E46: VI0002582479 | F46: =3874.31*2*7.118 -> 55154.677 | G46: UDIS | H46: Semestral | I46: 44796 | K46: Agente | L46: Vida | M46: Orvi | N46: cynthi_lizi@hotmail.com | O46: 3329196044 | P46: =IF(A46="","", "DARINKA UREÑA CASILLAS") -> DARINKA UREÑA CASILLAS | Q46: =IF(D46="","",VLOOKUP(MONTH(D46),Listas!$C$2:$D$14,2,0)) -> Enero | R46: =IF(D46="","",YEAR(D46)) -> 2021 | S46: =IF(D46="","",(DAY(D46))) -> 29 | T46: =IF(D46="","",S46-$W$1) -> 29 | U46: =IF(D46="","",(MONTH(D46))) -> 1 | V46: =IF(I46="","",(DAY(I46))) -> 23 | W46: =IF(I46="","",V46-$W$1) -> 23 | X46: =IF(I46="","",(MONTH(I46))) -> 8 | Y46: =IF(D46="","",(MONTH(D46))) -> 1 | Z46: =IFERROR(IF(I46="","", DATEDIF(I46, TODAY(), "Y")),0) -> 3 | AA46: =IF(Z46="","", IFS(Z46 >= 61, "61+ años", Z46 >= 51, "51-60 años", Z46 >= 40, "40-50 años", Z46 >= 20, "20-39 años", TRUE, "-20 años")) -> -20 años
A47: CYNTHIA ELIZABETH MORALES ORTEGA | B47: M | C47: Activo | D47: 44536 | E47: GM0000546753 | F47: =2*8926.33 -> 17852.66 | G47: MXN | H47: Semestral | I47: 44796 | K47: TD | L47: Gastos Médicos | M47: Practico | N47: cynthi_lizi@hotmail.com | O47: 3329196044 | P47: =IF(A47="","", "DARINKA UREÑA CASILLAS") -> DARINKA UREÑA CASILLAS | Q47: =IF(D47="","",VLOOKUP(MONTH(D47),Listas!$C$2:$D$14,2,0)) -> Diciembre | R47: =IF(D47="","",YEAR(D47)) -> 2021 | S47: =IF(D47="","",(DAY(D47))) -> 6 | T47: =IF(D47="","",S47-$W$1) -> 6 | U47: =IF(D47="","",(MONTH(D47))) -> 12 | V47: =IF(I47="","",(DAY(I47))) -> 23 | W47: =IF(I47="","",V47-$W$1) -> 23 | X47: =IF(I47="","",(MONTH(I47))) -> 8 | Y47: =IF(D47="","",(MONTH(D47))) -> 12 | Z47: =IFERROR(IF(I47="","", DATEDIF(I47, TODAY(), "Y")),0) -> 3 | AA47: =IF(Z47="","", IFS(Z47 >= 61, "61+ años", Z47 >= 51, "51-60 años", Z47 >= 40, "40-50 años", Z47 >= 20, "20-39 años", TRUE, "-20 años")) -> -20 años
A48: DANIELA CABRAL ROMO | B48: M | C48: Activo | D48: 44413 | E48: VI0002617376 | F48: =271.35*12*7.118 -> 23177.632 | G48: UDIS | H48: Mensual | I48: 44724 | K48: TC | L48: Vida | M48: Orvi | N48: dacaro_22@hotmail.com | O48: 3314439698 | P48: =IF(A48="","", "DARINKA UREÑA CASILLAS") -> DARINKA UREÑA CASILLAS | Q48: =IF(D48="","",VLOOKUP(MONTH(D48),Listas!$C$2:$D$14,2,0)) -> Agosto | R48: =IF(D48="","",YEAR(D48)) -> 2021 | S48: =IF(D48="","",(DAY(D48))) -> 5 | T48: =IF(D48="","",S48-$W$1) -> 5 | U48: =IF(D48="","",(MONTH(D48))) -> 8 | V48: =IF(I48="","",(DAY(I48))) -> 12 | W48: =IF(I48="","",V48-$W$1) -> 12 | X48: =IF(I48="","",(MONTH(I48))) -> 6 | Y48: =IF(D48="","",(MONTH(D48))) -> 8 | Z48: =IFERROR(IF(I48="","", DATEDIF(I48, TODAY(), "Y")),0) -> 3 | AA48: =IF(Z48="","", IFS(Z48 >= 61, "61+ años", Z48 >= 51, "51-60 años", Z48 >= 40, "40-50 años", Z48 >= 20, "20-39 años", TRUE, "-20 años")) -> -20 años
A49: DANIELA GUADALUPE PEREGRINA GONZALEZ | B49: M | C49: Activo | D49: 43965 | E49: VI0002531698 | F49: =2340.03*7.118 -> 16656.334 | G49: UDIS | H49: Anual | I49: 03-sep | K49: TC | L49: Vida | M49: Orvi | N49: peregrinadaniela0@gmail.com | O49: 3314669252 | P49: =IF(A49="","", "DARINKA UREÑA CASILLAS") -> DARINKA UREÑA CASILLAS | Q49: =IF(D49="","",VLOOKUP(MONTH(D49),Listas!$C$2:$D$14,2,0)) -> Mayo | R49: =IF(D49="","",YEAR(D49)) -> 2020 | S49: =IF(D49="","",(DAY(D49))) -> 14 | T49: =IF(D49="","",S49-$W$1) -> 14 | U49: =IF(D49="","",(MONTH(D49))) -> 5 | V49: =IF(I49="","",(DAY(I49))) -> 3 | W49: =IF(I49="","",V49-$W$1) -> 3 | X49: =IF(I49="","",(MONTH(I49))) -> 9 | Y49: =IF(D49="","",(MONTH(D49))) -> 5 | Z49: =IFERROR(IF(I49="","", DATEDIF(I49, TODAY(), "Y")),0) -> 0 | AA49: =IF(Z49="","", IFS(Z49 >= 61, "61+ años", Z49 >= 51, "51-60 años", Z49 >= 40, "40-50 años", Z49 >= 20, "20-39 años", TRUE, "-20 años")) -> -20 años
A50: DANIELA GUADALUPE PEREGRINA GONZALEZ | B50: M | C50: Activo | D50: 44779 | E50: GM0000573459 | F50: 16569.27 | G50: MXN | H50: Anual | I50: 03-sep | K50: TC | L50: Gastos Médicos | M50: Practico | N50: peregrinadaniela0@gmail.com | O50: 3314669252 | P50: =IF(A50="","", "DARINKA UREÑA CASILLAS") -> DARINKA UREÑA CASILLAS | Q50: =IF(D50="","",VLOOKUP(MONTH(D50),Listas!$C$2:$D$14,2,0)) -> Agosto | R50: =IF(D50="","",YEAR(D50)) -> 2022 | S50: =IF(D50="","",(DAY(D50))) -> 6 | T50: =IF(D50="","",S50-$W$1) -> 6 | U50: =IF(D50="","",(MONTH(D50))) -> 8 | V50: =IF(I50="","",(DAY(I50))) -> 3 | W50: =IF(I50="","",V50-$W$1) -> 3 | X50: =IF(I50="","",(MONTH(I50))) -> 9 | Y50: =IF(D50="","",(MONTH(D50))) -> 8 | Z50: =IFERROR(IF(I50="","", DATEDIF(I50, TODAY(), "Y")),0) -> 0 | AA50: =IF(Z50="","", IFS(Z50 >= 61, "61+ años", Z50 >= 51, "51-60 años", Z50 >= 40, "40-50 años", Z50 >= 20, "20-39 años", TRUE, "-20 años")) -> -20 años
A51: DANIELA NIETO MORAN | B51: M | C51: Activo | D51: 44235 | E51: VI0002583535 | F51: =371.93*12*7.118 -> 31768.773 | G51: UDIS | H51: Mensual | I51: 44872 | K51: TC | L51: Vida | M51: Orvi | N51: daniela.nietom@outlook.com | O51: 3312198584 | P51: =IF(A51="","", "DARINKA UREÑA CASILLAS") -> DARINKA UREÑA CASILLAS | Q51: =IF(D51="","",VLOOKUP(MONTH(D51),Listas!$C$2:$D$14,2,0)) -> Febrero | R51: =IF(D51="","",YEAR(D51)) -> 2021 | S51: =IF(D51="","",(DAY(D51))) -> 8 | T51: =IF(D51="","",S51-$W$1) -> 8 | U51: =IF(D51="","",(MONTH(D51))) -> 2 | V51: =IF(I51="","",(DAY(I51))) -> 7 | W51: =IF(I51="","",V51-$W$1) -> 7 | X51: =IF(I51="","",(MONTH(I51))) -> 11 | Y51: =IF(D51="","",(MONTH(D51))) -> 2 | Z51: =IFERROR(IF(I51="","", DATEDIF(I51, TODAY(), "Y")),0) -> 3 | AA51: =IF(Z51="","", IFS(Z51 >= 61, "61+ años", Z51 >= 51, "51-60 años", Z51 >= 40, "40-50 años", Z51 >= 20, "20-39 años", TRUE, "-20 años")) -> -20 años
A52: DARINKA UREÑA CASILLAS | B52: M | C52: Activo | D52: 44131 | E52: VI0002563282 | F52: =5345.56*7.118 -> 38049.696 | G52: UDIS | H52: Anual | I52: 44645 | K52: Agente | L52: Vida | M52: Orvi | N52: darinkasm7@gmail.com | O52: 3323714729 | P52: =IF(A52="","", "DARINKA UREÑA CASILLAS") -> DARINKA UREÑA CASILLAS | Q52: =IF(D52="","",VLOOKUP(MONTH(D52),Listas!$C$2:$D$14,2,0)) -> Octubre | R52: =IF(D52="","",YEAR(D52)) -> 2020 | S52: =IF(D52="","",(DAY(D52))) -> 27 | T52: =IF(D52="","",S52-$W$1) -> 27 | U52: =IF(D52="","",(MONTH(D52))) -> 10 | V52: =IF(I52="","",(DAY(I52))) -> 25 | W52: =IF(I52="","",V52-$W$1) -> 25 | X52: =IF(I52="","",(MONTH(I52))) -> 3 | Y52: =IF(D52="","",(MONTH(D52))) -> 10 | Z52: =IFERROR(IF(I52="","", DATEDIF(I52, TODAY(), "Y")),0) -> 4 | AA52: =IF(Z52="","", IFS(Z52 >= 61, "61+ años", Z52 >= 51, "51-60 años", Z52 >= 40, "40-50 años", Z52 >= 20, "20-39 años", TRUE, "-20 años")) -> -20 años
A53: DARINKA UREÑA CASILLAS | B53: M | C53: Activo | D53: 44343 | E53: GM0000526123 | F53: =1421.26*12 -> 17055.12 | G53: MXN | H53: Mensual | I53: 44645 | K53: TC | L53: Gastos Médicos | M53: Practico | N53: darinkasm7@gmail.com | O53: 3323714729 | P53: =IF(A53="","", "DARINKA UREÑA CASILLAS") -> DARINKA UREÑA CASILLAS | Q53: =IF(D53="","",VLOOKUP(MONTH(D53),Listas!$C$2:$D$14,2,0)) -> Mayo | R53: =IF(D53="","",YEAR(D53)) -> 2021 | S53: =IF(D53="","",(DAY(D53))) -> 27 | T53: =IF(D53="","",S53-$W$1) -> 27 | U53: =IF(D53="","",(MONTH(D53))) -> 5 | V53: =IF(I53="","",(DAY(I53))) -> 25 | W53: =IF(I53="","",V53-$W$1) -> 25 | X53: =IF(I53="","",(MONTH(I53))) -> 3 | Y53: =IF(D53="","",(MONTH(D53))) -> 5 | Z53: =IFERROR(IF(I53="","", DATEDIF(I53, TODAY(), "Y")),0) -> 4 | AA53: =IF(Z53="","", IFS(Z53 >= 61, "61+ años", Z53 >= 51, "51-60 años", Z53 >= 40, "40-50 años", Z53 >= 20, "20-39 años", TRUE, "-20 años")) -> -20 años
A54: DAVID MORENO NERI | B54: H | C54: Activo | D54: 42982 | E54: GM0000351999 | F54: =1486.35*12 -> 17836.2 | G54: MXN | H54: Mensual | I54: 44848 | K54: TC | L54: Gastos Médicos | M54: Integro | N54: davidmneri1490@gmail.com | O54: 3314551462 | P54: =IF(A54="","", "DARINKA UREÑA CASILLAS") -> DARINKA UREÑA CASILLAS | Q54: =IF(D54="","",VLOOKUP(MONTH(D54),Listas!$C$2:$D$14,2,0)) -> Septiembre | R54: =IF(D54="","",YEAR(D54)) -> 2017 | S54: =IF(D54="","",(DAY(D54))) -> 4 | T54: =IF(D54="","",S54-$W$1) -> 4 | U54: =IF(D54="","",(MONTH(D54))) -> 9 | V54: =IF(I54="","",(DAY(I54))) -> 14 | W54: =IF(I54="","",V54-$W$1) -> 14 | X54: =IF(I54="","",(MONTH(I54))) -> 10 | Y54: =IF(D54="","",(MONTH(D54))) -> 9 | Z54: =IFERROR(IF(I54="","", DATEDIF(I54, TODAY(), "Y")),0) -> 3 | AA54: =IF(Z54="","", IFS(Z54 >= 61, "61+ años", Z54 >= 51, "51-60 años", Z54 >= 40, "40-50 años", Z54 >= 20, "20-39 años", TRUE, "-20 años")) -> -20 años
A55: DAVID MORENO NERI | B55: H | C55: Activo | D55: 44064 | E55: VI0002550138 | F55: =407.83*12*7.118 -> 34835.207 | G55: UDIS | H55: Mensual | I55: 44848 | K55: TC | L55: Vida | M55: Orvi | N55: davidmneri1490@gmail.com | O55: 3314551462 | P55: =IF(A55="","", "DARINKA UREÑA CASILLAS") -> DARINKA UREÑA CASILLAS | Q55: =IF(D55="","",VLOOKUP(MONTH(D55),Listas!$C$2:$D$14,2,0)) -> Agosto | R55: =IF(D55="","",YEAR(D55)) -> 2020 | S55: =IF(D55="","",(DAY(D55))) -> 21 | T55: =IF(D55="","",S55-$W$1) -> 21 | U55: =IF(D55="","",(MONTH(D55))) -> 8 | V55: =IF(I55="","",(DAY(I55))) -> 14 | W55: =IF(I55="","",V55-$W$1) -> 14 | X55: =IF(I55="","",(MONTH(I55))) -> 10 | Y55: =IF(D55="","",(MONTH(D55))) -> 8 | Z55: =IFERROR(IF(I55="","", DATEDIF(I55, TODAY(), "Y")),0) -> 3 | AA55: =IF(Z55="","", IFS(Z55 >= 61, "61+ años", Z55 >= 51, "51-60 años", Z55 >= 40, "40-50 años", Z55 >= 20, "20-39 años", TRUE, "-20 años")) -> -20 años
A56: DENISSE CARDENAS GONZALEZ | B56: M | C56: Activo | D56: 44173 | E56: VI0002571494 | F56: =3643.56*7.118 -> 25934.86 | G56: UDIS | H56: Trimestral | I56: 44626 | K56: TC | L56: Vida | M56: Orvi | N56: denisse.cgonzalez@hotmail.com | O56: 3315994003 | P56: =IF(A56="","", "DARINKA UREÑA CASILLAS") -> DARINKA UREÑA CASILLAS | Q56: =IF(D56="","",VLOOKUP(MONTH(D56),Listas!$C$2:$D$14,2,0)) -> Diciembre | R56: =IF(D56="","",YEAR(D56)) -> 2020 | S56: =IF(D56="","",(DAY(D56))) -> 8 | T56: =IF(D56="","",S56-$W$1) -> 8 | U56: =IF(D56="","",(MONTH(D56))) -> 12 | V56: =IF(I56="","",(DAY(I56))) -> 6 | W56: =IF(I56="","",V56-$W$1) -> 6 | X56: =IF(I56="","",(MONTH(I56))) -> 3 | Y56: =IF(D56="","",(MONTH(D56))) -> 12 | Z56: =IFERROR(IF(I56="","", DATEDIF(I56, TODAY(), "Y")),0) -> 4 | AA56: =IF(Z56="","", IFS(Z56 >= 61, "61+ años", Z56 >= 51, "51-60 años", Z56 >= 40, "40-50 años", Z56 >= 20, "20-39 años", TRUE, "-20 años")) -> -20 años
A57: DIEGO IVAN AGUAYO RAMIREZ | B57: H | C57: Activo | D57: 44895 | E57: GM0000585100 | F57: =26906.04*2 -> 53812.08 | G57: MXN | H57: Semestral | I57: 45207 | K57: Agente | L57: Gastos Médicos | M57: Integro | N57: diegoivanaguayorodriguez@gmail.com | O57: 3319866597 | P57: =IF(A57="","", "DARINKA UREÑA CASILLAS") -> DARINKA UREÑA CASILLAS | Q57: =IF(D57="","",VLOOKUP(MONTH(D57),Listas!$C$2:$D$14,2,0)) -> Noviembre | R57: =IF(D57="","",YEAR(D57)) -> 2022 | S57: =IF(D57="","",(DAY(D57))) -> 30 | T57: =IF(D57="","",S57-$W$1) -> 30 | U57: =IF(D57="","",(MONTH(D57))) -> 11 | V57: =IF(I57="","",(DAY(I57))) -> 8 | W57: =IF(I57="","",V57-$W$1) -> 8 | X57: =IF(I57="","",(MONTH(I57))) -> 10 | Y57: =IF(D57="","",(MONTH(D57))) -> 11 | Z57: =IFERROR(IF(I57="","", DATEDIF(I57, TODAY(), "Y")),0) -> 2 | AA57: =IF(Z57="","", IFS(Z57 >= 61, "61+ años", Z57 >= 51, "51-60 años", Z57 >= 40, "40-50 años", Z57 >= 20, "20-39 años", TRUE, "-20 años")) -> -20 años
A58: DIEGO LEONARDO UREÑA GUARNEROS | B58: H | C58: Activo | D58: 44034 | E58: GM0000482513 | F58: 13642.72 | G58: MXN | H58: Anual | I58: 44562 | K58: TD | L58: Gastos Médicos | M58: Integro | N58: guarnerosleo4e@gmail.com | O58: 3324010177 | P58: =IF(A58="","", "DARINKA UREÑA CASILLAS") -> DARINKA UREÑA CASILLAS | Q58: =IF(D58="","",VLOOKUP(MONTH(D58),Listas!$C$2:$D$14,2,0)) -> Julio | R58: =IF(D58="","",YEAR(D58)) -> 2020 | S58: =IF(D58="","",(DAY(D58))) -> 22 | T58: =IF(D58="","",S58-$W$1) -> 22 | U58: =IF(D58="","",(MONTH(D58))) -> 7 | V58: =IF(I58="","",(DAY(I58))) -> 1 | W58: =IF(I58="","",V58-$W$1) -> 1 | X58: =IF(I58="","",(MONTH(I58))) -> 1 | Y58: =IF(D58="","",(MONTH(D58))) -> 7 | Z58: =IFERROR(IF(I58="","", DATEDIF(I58, TODAY(), "Y")),0) -> 4 | AA58: =IF(Z58="","", IFS(Z58 >= 61, "61+ años", Z58 >= 51, "51-60 años", Z58 >= 40, "40-50 años", Z58 >= 20, "20-39 años", TRUE, "-20 años")) -> -20 años
A59: DIGNA MARIA BAÑUELOS ZAMORA | B59: M | C59: Activo | D59: 44249 | E59: VI0002585935 | F59: =2698.78*7.118 -> 19209.916 | G59: UDIS | H59: Trimestral | I59: 44917 | K59: TC | L59: Vida | M59: Orvi | N59: digna.baza@gmail.com | O59: 3316366711 | P59: =IF(A59="","", "DARINKA UREÑA CASILLAS") -> DARINKA UREÑA CASILLAS | Q59: =IF(D59="","",VLOOKUP(MONTH(D59),Listas!$C$2:$D$14,2,0)) -> Febrero | R59: =IF(D59="","",YEAR(D59)) -> 2021 | S59: =IF(D59="","",(DAY(D59))) -> 22 | T59: =IF(D59="","",S59-$W$1) -> 22 | U59: =IF(D59="","",(MONTH(D59))) -> 2 | V59: =IF(I59="","",(DAY(I59))) -> 22 | W59: =IF(I59="","",V59-$W$1) -> 22 | X59: =IF(I59="","",(MONTH(I59))) -> 12 | Y59: =IF(D59="","",(MONTH(D59))) -> 2 | Z59: =IFERROR(IF(I59="","", DATEDIF(I59, TODAY(), "Y")),0) -> 3 | AA59: =IF(Z59="","", IFS(Z59 >= 61, "61+ años", Z59 >= 51, "51-60 años", Z59 >= 40, "40-50 años", Z59 >= 20, "20-39 años", TRUE, "-20 años")) -> -20 años
A60: EDER EMMANUEL ALCALA GUTIERREZ | B60: H | C60: Activo | D60: 44395 | E60: VI0002613934 | F60: =3531.76*7.118 -> 25139.068 | G60: UDIS | H60: Anual | I60: 44874 | K60: TC | L60: Vida | M60: Orvi | N60: ederemmanuel.alcala19@jaliscoedu.mx | O60: 3334414617 | P60: =IF(A60="","", "DARINKA UREÑA CASILLAS") -> DARINKA UREÑA CASILLAS | Q60: =IF(D60="","",VLOOKUP(MONTH(D60),Listas!$C$2:$D$14,2,0)) -> Julio | R60: =IF(D60="","",YEAR(D60)) -> 2021 | S60: =IF(D60="","",(DAY(D60))) -> 18 | T60: =IF(D60="","",S60-$W$1) -> 18 | U60: =IF(D60="","",(MONTH(D60))) -> 7 | V60: =IF(I60="","",(DAY(I60))) -> 9 | W60: =IF(I60="","",V60-$W$1) -> 9 | X60: =IF(I60="","",(MONTH(I60))) -> 11 | Y60: =IF(D60="","",(MONTH(D60))) -> 7 | Z60: =IFERROR(IF(I60="","", DATEDIF(I60, TODAY(), "Y")),0) -> 3 | AA60: =IF(Z60="","", IFS(Z60 >= 61, "61+ años", Z60 >= 51, "51-60 años", Z60 >= 40, "40-50 años", Z60 >= 20, "20-39 años", TRUE, "-20 años")) -> -20 años
A61: EDGAR SANCHEZ GONZALEZ | B61: H | C61: Activo | D61: 44923 | E61: VI0002711484 | F61: =206.75*12*7.65 -> 18979.65 | G61: UDIS | H61: Mensual | I61: 45213 | K61: TD | L61: Vida | M61: Orvi | N61: esanchez_glez@outlook.com | O61: 6692407705 | P61: =IF(A61="","", "DARINKA UREÑA CASILLAS") -> DARINKA UREÑA CASILLAS | Q61: =IF(D61="","",VLOOKUP(MONTH(D61),Listas!$C$2:$D$14,2,0)) -> Diciembre | R61: =IF(D61="","",YEAR(D61)) -> 2022 | S61: =IF(D61="","",(DAY(D61))) -> 28 | T61: =IF(D61="","",S61-$W$1) -> 28 | U61: =IF(D61="","",(MONTH(D61))) -> 12 | V61: =IF(I61="","",(DAY(I61))) -> 14 | W61: =IF(I61="","",V61-$W$1) -> 14 | X61: =IF(I61="","",(MONTH(I61))) -> 10 | Y61: =IF(D61="","",(MONTH(D61))) -> 12 | Z61: =IFERROR(IF(I61="","", DATEDIF(I61, TODAY(), "Y")),0) -> 2 | AA61: =IF(Z61="","", IFS(Z61 >= 61, "61+ años", Z61 >= 51, "51-60 años", Z61 >= 40, "40-50 años", Z61 >= 20, "20-39 años", TRUE, "-20 años")) -> -20 años
A62: EDUARDO ERNESTO VALLES JARILLO | B62: H | C62: Activo | D62: 44622 | E62: GM0000556025 | F62: 38717.24 | G62: MXN | H62: Semestral | I62: 44587 | K62: TC | L62: Gastos Médicos | M62: Integro | N62: evalles.0311@gmail.com | O62: 5535683014 | P62: =IF(A62="","", "DARINKA UREÑA CASILLAS") -> DARINKA UREÑA CASILLAS | Q62: =IF(D62="","",VLOOKUP(MONTH(D62),Listas!$C$2:$D$14,2,0)) -> Marzo | R62: =IF(D62="","",YEAR(D62)) -> 2022 | S62: =IF(D62="","",(DAY(D62))) -> 2 | T62: =IF(D62="","",S62-$W$1) -> 2 | U62: =IF(D62="","",(MONTH(D62))) -> 3 | V62: =IF(I62="","",(DAY(I62))) -> 26 | W62: =IF(I62="","",V62-$W$1) -> 26 | X62: =IF(I62="","",(MONTH(I62))) -> 1 | Y62: =IF(D62="","",(MONTH(D62))) -> 3 | Z62: =IFERROR(IF(I62="","", DATEDIF(I62, TODAY(), "Y")),0) -> 4 | AA62: =IF(Z62="","", IFS(Z62 >= 61, "61+ años", Z62 >= 51, "51-60 años", Z62 >= 40, "40-50 años", Z62 >= 20, "20-39 años", TRUE, "-20 años")) -> -20 años
A63: EDUARDO RAMIRO TORRES ALVAREZ | B63: H | C63: Activo | D63: 44053 | E63: VI0002548210 | F63: =324.25*12*7.118 -> 27696.138 | G63: UDIS | H63: Mensual | I63: 44915 | K63: TC | L63: Vida | M63: Orvi | N63: e_torres_alvarez@outlook.com | O63: 3339705750 | P63: =IF(A63="","", "DARINKA UREÑA CASILLAS") -> DARINKA UREÑA CASILLAS | Q63: =IF(D63="","",VLOOKUP(MONTH(D63),Listas!$C$2:$D$14,2,0)) -> Agosto | R63: =IF(D63="","",YEAR(D63)) -> 2020 | S63: =IF(D63="","",(DAY(D63))) -> 10 | T63: =IF(D63="","",S63-$W$1) -> 10 | U63: =IF(D63="","",(MONTH(D63))) -> 8 | V63: =IF(I63="","",(DAY(I63))) -> 20 | W63: =IF(I63="","",V63-$W$1) -> 20 | X63: =IF(I63="","",(MONTH(I63))) -> 12 | Y63: =IF(D63="","",(MONTH(D63))) -> 8 | Z63: =IFERROR(IF(I63="","", DATEDIF(I63, TODAY(), "Y")),0) -> 3 | AA63: =IF(Z63="","", IFS(Z63 >= 61, "61+ años", Z63 >= 51, "51-60 años", Z63 >= 40, "40-50 años", Z63 >= 20, "20-39 años", TRUE, "-20 años")) -> -20 años
A64: EMMANUEL CONTRERAS RIOS | B64: H | C64: Activo | D64: 44280 | E64: VI00025924219 | F64: =1828.53*2*7.118 -> 26030.953 | G64: UDIS | H64: Semestral | I64: 05-sep | K64: TD | L64: Vida | M64: Orvi | N64: emmanuel.palmasal@gmail.com | O64: 3316119244 | P64: =IF(A64="","", "DARINKA UREÑA CASILLAS") -> DARINKA UREÑA CASILLAS | Q64: =IF(D64="","",VLOOKUP(MONTH(D64),Listas!$C$2:$D$14,2,0)) -> Marzo | R64: =IF(D64="","",YEAR(D64)) -> 2021 | S64: =IF(D64="","",(DAY(D64))) -> 25 | T64: =IF(D64="","",S64-$W$1) -> 25 | U64: =IF(D64="","",(MONTH(D64))) -> 3 | V64: =IF(I64="","",(DAY(I64))) -> 5 | W64: =IF(I64="","",V64-$W$1) -> 5 | X64: =IF(I64="","",(MONTH(I64))) -> 9 | Y64: =IF(D64="","",(MONTH(D64))) -> 3 | Z64: =IFERROR(IF(I64="","", DATEDIF(I64, TODAY(), "Y")),0) -> 0 | AA64: =IF(Z64="","", IFS(Z64 >= 61, "61+ años", Z64 >= 51, "51-60 años", Z64 >= 40, "40-50 años", Z64 >= 20, "20-39 años", TRUE, "-20 años")) -> -20 años
A65: EMMANUEL ORTEGA GUTIERREZ | B65: H | C65: Activo | D65: 44096 | E65: GM0000492375 | F65: =14800.98*4 -> 59203.92 | G65: MXN | H65: Trimestral | I65: 44964 | K65: TC | L65: Gastos Médicos | M65: Practico | N65: minerliz109@hotmail.com | O65: 3325701779 | P65: =IF(A65="","", "DARINKA UREÑA CASILLAS") -> DARINKA UREÑA CASILLAS | Q65: =IF(D65="","",VLOOKUP(MONTH(D65),Listas!$C$2:$D$14,2,0)) -> Septiembre | R65: =IF(D65="","",YEAR(D65)) -> 2020 | S65: =IF(D65="","",(DAY(D65))) -> 22 | T65: =IF(D65="","",S65-$W$1) -> 22 | U65: =IF(D65="","",(MONTH(D65))) -> 9 | V65: =IF(I65="","",(DAY(I65))) -> 7 | W65: =IF(I65="","",V65-$W$1) -> 7 | X65: =IF(I65="","",(MONTH(I65))) -> 2 | Y65: =IF(D65="","",(MONTH(D65))) -> 9 | Z65: =IFERROR(IF(I65="","", DATEDIF(I65, TODAY(), "Y")),0) -> 3 | AA65: =IF(Z65="","", IFS(Z65 >= 61, "61+ años", Z65 >= 51, "51-60 años", Z65 >= 40, "40-50 años", Z65 >= 20, "20-39 años", TRUE, "-20 años")) -> -20 años
A66: ESTEFANI ALEYOIS CONTRERAS RIOS | B66: M | C66: Activo | D66: 44916 | E66: GM0000586871 | F66: 30717.59 | G66: MXN | H66: Anual | I66: 44803 | K66: TD | L66: Gastos Médicos | M66: Practico | N66: aleyois.cr@gmail.com | O66: 3316119244 | P66: =IF(A66="","", "DARINKA UREÑA CASILLAS") -> DARINKA UREÑA CASILLAS | Q66: =IF(D66="","",VLOOKUP(MONTH(D66),Listas!$C$2:$D$14,2,0)) -> Diciembre | R66: =IF(D66="","",YEAR(D66)) -> 2022 | S66: =IF(D66="","",(DAY(D66))) -> 21 | T66: =IF(D66="","",S66-$W$1) -> 21 | U66: =IF(D66="","",(MONTH(D66))) -> 12 | V66: =IF(I66="","",(DAY(I66))) -> 30 | W66: =IF(I66="","",V66-$W$1) -> 30 | X66: =IF(I66="","",(MONTH(I66))) -> 8 | Y66: =IF(D66="","",(MONTH(D66))) -> 12 | Z66: =IFERROR(IF(I66="","", DATEDIF(I66, TODAY(), "Y")),0) -> 3 | AA66: =IF(Z66="","", IFS(Z66 >= 61, "61+ años", Z66 >= 51, "51-60 años", Z66 >= 40, "40-50 años", Z66 >= 20, "20-39 años", TRUE, "-20 años")) -> -20 años
A67: ESTEFANI ALEYOIS CONTRERAS RIOS | B67: M | C67: Activo | D67: 44276 | E67: VI0002591210 | F67: =2*4577.17*7.118 -> 65160.592 | G67: UDIS | H67: Semestral | I67: 44803 | K67: TD | L67: Vida | M67: Orvi | N67: aleyois.cr@gmail.com | O67: 3316119244 | P67: =IF(A67="","", "DARINKA UREÑA CASILLAS") -> DARINKA UREÑA CASILLAS | Q67: =IF(D67="","",VLOOKUP(MONTH(D67),Listas!$C$2:$D$14,2,0)) -> Marzo | R67: =IF(D67="","",YEAR(D67)) -> 2021 | S67: =IF(D67="","",(DAY(D67))) -> 21 | T67: =IF(D67="","",S67-$W$1) -> 21 | U67: =IF(D67="","",(MONTH(D67))) -> 3 | V67: =IF(I67="","",(DAY(I67))) -> 30 | W67: =IF(I67="","",V67-$W$1) -> 30 | X67: =IF(I67="","",(MONTH(I67))) -> 8 | Y67: =IF(D67="","",(MONTH(D67))) -> 3 | Z67: =IFERROR(IF(I67="","", DATEDIF(I67, TODAY(), "Y")),0) -> 3 | AA67: =IF(Z67="","", IFS(Z67 >= 61, "61+ años", Z67 >= 51, "51-60 años", Z67 >= 40, "40-50 años", Z67 >= 20, "20-39 años", TRUE, "-20 años")) -> -20 años
A68: FELICITAS CASILLAS GALINDO | B68: M | C68: Activo | D68: 44092 | E68: VI0002555595 | F68: =3057.2*7.118 -> 21761.15 | G68: UDIS | H68: Anual | I68: 44916 | K68: TC | L68: Vida | M68: Orvi | N68: felicitascasillas@hotmail.com | O68: 3331919169 | P68: =IF(A68="","", "DARINKA UREÑA CASILLAS") -> DARINKA UREÑA CASILLAS | Q68: =IF(D68="","",VLOOKUP(MONTH(D68),Listas!$C$2:$D$14,2,0)) -> Septiembre | R68: =IF(D68="","",YEAR(D68)) -> 2020 | S68: =IF(D68="","",(DAY(D68))) -> 18 | T68: =IF(D68="","",S68-$W$1) -> 18 | U68: =IF(D68="","",(MONTH(D68))) -> 9 | V68: =IF(I68="","",(DAY(I68))) -> 21 | W68: =IF(I68="","",V68-$W$1) -> 21 | X68: =IF(I68="","",(MONTH(I68))) -> 12 | Y68: =IF(D68="","",(MONTH(D68))) -> 9 | Z68: =IFERROR(IF(I68="","", DATEDIF(I68, TODAY(), "Y")),0) -> 3 | AA68: =IF(Z68="","", IFS(Z68 >= 61, "61+ años", Z68 >= 51, "51-60 años", Z68 >= 40, "40-50 años", Z68 >= 20, "20-39 años", TRUE, "-20 años")) -> -20 años
A69: FLORENCIA LILIANA CORONA GARNICA | B69: M | C69: Activo | D69: 44020 | E69: VI0002542137 | F69: =5586.81*7.118 -> 39766.914 | G69: UDIS | H69: Anual | I69: 44674 | K69: TD | L69: Vida | M69: Orvi | N69: florcorona8@gmail.com | O69: 3331838401 | P69: =IF(A69="","", "DARINKA UREÑA CASILLAS") -> DARINKA UREÑA CASILLAS | Q69: =IF(D69="","",VLOOKUP(MONTH(D69),Listas!$C$2:$D$14,2,0)) -> Julio | R69: =IF(D69="","",YEAR(D69)) -> 2020 | S69: =IF(D69="","",(DAY(D69))) -> 8 | T69: =IF(D69="","",S69-$W$1) -> 8 | U69: =IF(D69="","",(MONTH(D69))) -> 7 | V69: =IF(I69="","",(DAY(I69))) -> 23 | W69: =IF(I69="","",V69-$W$1) -> 23 | X69: =IF(I69="","",(MONTH(I69))) -> 4 | Y69: =IF(D69="","",(MONTH(D69))) -> 7 | Z69: =IFERROR(IF(I69="","", DATEDIF(I69, TODAY(), "Y")),0) -> 4 | AA69: =IF(Z69="","", IFS(Z69 >= 61, "61+ años", Z69 >= 51, "51-60 años", Z69 >= 40, "40-50 años", Z69 >= 20, "20-39 años", TRUE, "-20 años")) -> -20 años
A70: FRANCISCO JAVIER VALENCIA PRADO | B70: H | C70: Activo | D70: 44012 | E70: GM0000479419 | F70: =1349.06*12 -> 16188.72 | G70: MXN | H70: Mensual | I70: 44865 | K70: TD | L70: Gastos Médicos | M70: Integro | N70: javiz-94@hotmail.com | O70: 3310448631 | P70: =IF(A70="","", "DARINKA UREÑA CASILLAS") -> DARINKA UREÑA CASILLAS | Q70: =IF(D70="","",VLOOKUP(MONTH(D70),Listas!$C$2:$D$14,2,0)) -> Junio | R70: =IF(D70="","",YEAR(D70)) -> 2020 | S70: =IF(D70="","",(DAY(D70))) -> 30 | T70: =IF(D70="","",S70-$W$1) -> 30 | U70: =IF(D70="","",(MONTH(D70))) -> 6 | V70: =IF(I70="","",(DAY(I70))) -> 31 | W70: =IF(I70="","",V70-$W$1) -> 31 | X70: =IF(I70="","",(MONTH(I70))) -> 10 | Y70: =IF(D70="","",(MONTH(D70))) -> 6 | Z70: =IFERROR(IF(I70="","", DATEDIF(I70, TODAY(), "Y")),0) -> 3 | AA70: =IF(Z70="","", IFS(Z70 >= 61, "61+ años", Z70 >= 51, "51-60 años", Z70 >= 40, "40-50 años", Z70 >= 20, "20-39 años", TRUE, "-20 años")) -> -20 años
A71: FRANCISCO JAVIER VALENCIA PRADO | B71: H | C71: Activo | D71: 44019 | E71: VI0002541931 | F71: =326.69*12*7.118 -> 27904.553 | G71: UDIS | H71: Mensual | I71: 44865 | K71: TD | L71: Vida | M71: Orvi | N71: javiz-94@hotmail.com | O71: 3310448631 | P71: =IF(A71="","", "DARINKA UREÑA CASILLAS") -> DARINKA UREÑA CASILLAS | Q71: =IF(D71="","",VLOOKUP(MONTH(D71),Listas!$C$2:$D$14,2,0)) -> Julio | R71: =IF(D71="","",YEAR(D71)) -> 2020 | S71: =IF(D71="","",(DAY(D71))) -> 7 | T71: =IF(D71="","",S71-$W$1) -> 7 | U71: =IF(D71="","",(MONTH(D71))) -> 7 | V71: =IF(I71="","",(DAY(I71))) -> 31 | W71: =IF(I71="","",V71-$W$1) -> 31 | X71: =IF(I71="","",(MONTH(I71))) -> 10 | Y71: =IF(D71="","",(MONTH(D71))) -> 7 | Z71: =IFERROR(IF(I71="","", DATEDIF(I71, TODAY(), "Y")),0) -> 3 | AA71: =IF(Z71="","", IFS(Z71 >= 61, "61+ años", Z71 >= 51, "51-60 años", Z71 >= 40, "40-50 años", Z71 >= 20, "20-39 años", TRUE, "-20 años")) -> -20 años
A72: FRANCISCO JAVIER VALENCIA PRADO | B72: H | C72: Activo | D72: 44467 | E72: GM0000540124 | F72: =9364.78*2 -> 18729.56 | G72: MXN | H72: Semestral | I72: 44865 | K72: TD | L72: Gastos Médicos | M72: Integro | N72: javiz-94@hotmail.com | O72: 3310448631 | P72: =IF(A72="","", "DARINKA UREÑA CASILLAS") -> DARINKA UREÑA CASILLAS | Q72: =IF(D72="","",VLOOKUP(MONTH(D72),Listas!$C$2:$D$14,2,0)) -> Septiembre | R72: =IF(D72="","",YEAR(D72)) -> 2021 | S72: =IF(D72="","",(DAY(D72))) -> 28 | T72: =IF(D72="","",S72-$W$1) -> 28 | U72: =IF(D72="","",(MONTH(D72))) -> 9 | V72: =IF(I72="","",(DAY(I72))) -> 31 | W72: =IF(I72="","",V72-$W$1) -> 31 | X72: =IF(I72="","",(MONTH(I72))) -> 10 | Y72: =IF(D72="","",(MONTH(D72))) -> 9 | Z72: =IFERROR(IF(I72="","", DATEDIF(I72, TODAY(), "Y")),0) -> 3 | AA72: =IF(Z72="","", IFS(Z72 >= 61, "61+ años", Z72 >= 51, "51-60 años", Z72 >= 40, "40-50 años", Z72 >= 20, "20-39 años", TRUE, "-20 años")) -> -20 años
A73: FRANCISCO JOSE MARTIN LOPEZ | B73: H | C73: Activo | D73: 44641 | E73: VI0002656531 | F73: 50638.264 | G73: UDIS | H73: Anual | I73: 44858 | K73: TC | L73: Vida | M73: Orvi | N73: fcomartin@gmail.com | O73: 3331675304 | P73: =IF(A73="","", "DARINKA UREÑA CASILLAS") -> DARINKA UREÑA CASILLAS | Q73: =IF(D73="","",VLOOKUP(MONTH(D73),Listas!$C$2:$D$14,2,0)) -> Marzo | R73: =IF(D73="","",YEAR(D73)) -> 2022 | S73: =IF(D73="","",(DAY(D73))) -> 21 | T73: =IF(D73="","",S73-$W$1) -> 21 | U73: =IF(D73="","",(MONTH(D73))) -> 3 | V73: =IF(I73="","",(DAY(I73))) -> 24 | W73: =IF(I73="","",V73-$W$1) -> 24 | X73: =IF(I73="","",(MONTH(I73))) -> 10 | Y73: =IF(D73="","",(MONTH(D73))) -> 3 | Z73: =IFERROR(IF(I73="","", DATEDIF(I73, TODAY(), "Y")),0) -> 3 | AA73: =IF(Z73="","", IFS(Z73 >= 61, "61+ años", Z73 >= 51, "51-60 años", Z73 >= 40, "40-50 años", Z73 >= 20, "20-39 años", TRUE, "-20 años")) -> -20 años
A74: GLENDA GISELA CASIANO VEGA | B74: M | C74: Activo | D74: 43867 | E74: GM0000452776 | F74: =1431.36*12 -> 17176.32 | G74: MXN | H74: Mensual | I74: 44589 | K74: TC | L74: Gastos Médicos | M74: Practico | N74: glencacasiano@hotmail.com | O74: 3323382232 | P74: =IF(A74="","", "DARINKA UREÑA CASILLAS") -> DARINKA UREÑA CASILLAS | Q74: =IF(D74="","",VLOOKUP(MONTH(D74),Listas!$C$2:$D$14,2,0)) -> Febrero | R74: =IF(D74="","",YEAR(D74)) -> 2020 | S74: =IF(D74="","",(DAY(D74))) -> 6 | T74: =IF(D74="","",S74-$W$1) -> 6 | U74: =IF(D74="","",(MONTH(D74))) -> 2 | V74: =IF(I74="","",(DAY(I74))) -> 28 | W74: =IF(I74="","",V74-$W$1) -> 28 | X74: =IF(I74="","",(MONTH(I74))) -> 1 | Y74: =IF(D74="","",(MONTH(D74))) -> 2 | Z74: =IFERROR(IF(I74="","", DATEDIF(I74, TODAY(), "Y")),0) -> 4 | AA74: =IF(Z74="","", IFS(Z74 >= 61, "61+ años", Z74 >= 51, "51-60 años", Z74 >= 40, "40-50 años", Z74 >= 20, "20-39 años", TRUE, "-20 años")) -> -20 años
A75: GUSTAVO GUTIERREZ PLASCENCIA | B75: H | C75: Activo | D75: 44362 | E75: VI0002607534 | F75: =3346.79*7.118 -> 23822.451 | G75: UDIS | H75: Anual | I75: 44726 | K75: TC | L75: Vida | M75: Orvi | N75: gpgustavo@yahoo.com | O75: 3339540399 | P75: =IF(A75="","", "DARINKA UREÑA CASILLAS") -> DARINKA UREÑA CASILLAS | Q75: =IF(D75="","",VLOOKUP(MONTH(D75),Listas!$C$2:$D$14,2,0)) -> Junio | R75: =IF(D75="","",YEAR(D75)) -> 2021 | S75: =IF(D75="","",(DAY(D75))) -> 15 | T75: =IF(D75="","",S75-$W$1) -> 15 | U75: =IF(D75="","",(MONTH(D75))) -> 6 | V75: =IF(I75="","",(DAY(I75))) -> 14 | W75: =IF(I75="","",V75-$W$1) -> 14 | X75: =IF(I75="","",(MONTH(I75))) -> 6 | Y75: =IF(D75="","",(MONTH(D75))) -> 6 | Z75: =IFERROR(IF(I75="","", DATEDIF(I75, TODAY(), "Y")),0) -> 3 | AA75: =IF(Z75="","", IFS(Z75 >= 61, "61+ años", Z75 >= 51, "51-60 años", Z75 >= 40, "40-50 años", Z75 >= 20, "20-39 años", TRUE, "-20 años")) -> -20 años
A76: HEBER RAMIREZ LUNA | B76: H | C76: Activo | D76: 43955 | E76: VI0002530480 | F76: =3731.53*7.118 -> 26561.031 | G76: UDIS | H76: Anual | I76: 44648 | K76: TC | L76: Vida | M76: Orvi | N76: heber.ramirez.luna@gmail.com | O76: 3338162151 | P76: =IF(A76="","", "DARINKA UREÑA CASILLAS") -> DARINKA UREÑA CASILLAS | Q76: =IF(D76="","",VLOOKUP(MONTH(D76),Listas!$C$2:$D$14,2,0)) -> Mayo | R76: =IF(D76="","",YEAR(D76)) -> 2020 | S76: =IF(D76="","",(DAY(D76))) -> 4 | T76: =IF(D76="","",S76-$W$1) -> 4 | U76: =IF(D76="","",(MONTH(D76))) -> 5 | V76: =IF(I76="","",(DAY(I76))) -> 28 | W76: =IF(I76="","",V76-$W$1) -> 28 | X76: =IF(I76="","",(MONTH(I76))) -> 3 | Y76: =IF(D76="","",(MONTH(D76))) -> 5 | Z76: =IFERROR(IF(I76="","", DATEDIF(I76, TODAY(), "Y")),0) -> 4 | AA76: =IF(Z76="","", IFS(Z76 >= 61, "61+ años", Z76 >= 51, "51-60 años", Z76 >= 40, "40-50 años", Z76 >= 20, "20-39 años", TRUE, "-20 años")) -> -20 años
A77: IZCHEL IRAIS GONZALEZ DIAZ | B77: M | C77: Activo | D77: 44366 | E77: VI0002608269 | F77: =205.78*12*7.118 -> 17576.904 | G77: UDIS | H77: Mensual | I77: 44730 | K77: TD | L77: Vida | M77: Orvi | N77: expayupi.13@gmail.com | O77: 3314851938 | P77: =IF(A77="","", "DARINKA UREÑA CASILLAS") -> DARINKA UREÑA CASILLAS | Q77: =IF(D77="","",VLOOKUP(MONTH(D77),Listas!$C$2:$D$14,2,0)) -> Junio | R77: =IF(D77="","",YEAR(D77)) -> 2021 | S77: =IF(D77="","",(DAY(D77))) -> 19 | T77: =IF(D77="","",S77-$W$1) -> 19 | U77: =IF(D77="","",(MONTH(D77))) -> 6 | V77: =IF(I77="","",(DAY(I77))) -> 18 | W77: =IF(I77="","",V77-$W$1) -> 18 | X77: =IF(I77="","",(MONTH(I77))) -> 6 | Y77: =IF(D77="","",(MONTH(D77))) -> 6 | Z77: =IFERROR(IF(I77="","", DATEDIF(I77, TODAY(), "Y")),0) -> 3 | AA77: =IF(Z77="","", IFS(Z77 >= 61, "61+ años", Z77 >= 51, "51-60 años", Z77 >= 40, "40-50 años", Z77 >= 20, "20-39 años", TRUE, "-20 años")) -> -20 años
A78: JAVIER ALEJANDRO OCHOA FLORES | B78: H | C78: Activo | D78: 44516 | E78: VI0002634302 | F78: =228.16*12*7.118 -> 19488.515 | G78: MXN | H78: Mensual | I78: 44568 | K78: TD | L78: Vida | M78: Orvi | N78: alexocho88@gmail.com | O78: 3339445412 | P78: =IF(A78="","", "DARINKA UREÑA CASILLAS") -> DARINKA UREÑA CASILLAS | Q78: =IF(D78="","",VLOOKUP(MONTH(D78),Listas!$C$2:$D$14,2,0)) -> Noviembre | R78: =IF(D78="","",YEAR(D78)) -> 2021 | S78: =IF(D78="","",(DAY(D78))) -> 16 | T78: =IF(D78="","",S78-$W$1) -> 16 | U78: =IF(D78="","",(MONTH(D78))) -> 11 | V78: =IF(I78="","",(DAY(I78))) -> 7 | W78: =IF(I78="","",V78-$W$1) -> 7 | X78: =IF(I78="","",(MONTH(I78))) -> 1 | Y78: =IF(D78="","",(MONTH(D78))) -> 11 | Z78: =IFERROR(IF(I78="","", DATEDIF(I78, TODAY(), "Y")),0) -> 4 | AA78: =IF(Z78="","", IFS(Z78 >= 61, "61+ años", Z78 >= 51, "51-60 años", Z78 >= 40, "40-50 años", Z78 >= 20, "20-39 años", TRUE, "-20 años")) -> -20 años
A79: JAVIER RAMOS BARAJAS | B79: H | C79: Activo | D79: 44059 | E79: VI0002549354 | F79: =8303.73*7.118 -> 59105.95 | G79: UDIS | H79: Anual | I79: 44617 | K79: TD | L79: Vida | M79: Orvi | N79: jaramos89@yahoo.com | O79: 3336264624 | P79: =IF(A79="","", "DARINKA UREÑA CASILLAS") -> DARINKA UREÑA CASILLAS | Q79: =IF(D79="","",VLOOKUP(MONTH(D79),Listas!$C$2:$D$14,2,0)) -> Agosto | R79: =IF(D79="","",YEAR(D79)) -> 2020 | S79: =IF(D79="","",(DAY(D79))) -> 16 | T79: =IF(D79="","",S79-$W$1) -> 16 | U79: =IF(D79="","",(MONTH(D79))) -> 8 | V79: =IF(I79="","",(DAY(I79))) -> 25 | W79: =IF(I79="","",V79-$W$1) -> 25 | X79: =IF(I79="","",(MONTH(I79))) -> 2 | Y79: =IF(D79="","",(MONTH(D79))) -> 8 | Z79: =IFERROR(IF(I79="","", DATEDIF(I79, TODAY(), "Y")),0) -> 4 | AA79: =IF(Z79="","", IFS(Z79 >= 61, "61+ años", Z79 >= 51, "51-60 años", Z79 >= 40, "40-50 años", Z79 >= 20, "20-39 años", TRUE, "-20 años")) -> -20 años
A80: JAZMIN ALICIA ROMERO JOHNSON | B80: M | C80: Activo | D80: 44177 | E80: VI0002572565 | F80: =5457.98*7.118 -> 38849.902 | G80: UDIS | H80: Anual | I80: 44922 | K80: TC | L80: Vida | M80: Orvi | N80: jazmin_ro_jo@hotmail.com | O80: 3314251081 | P80: =IF(A80="","", "DARINKA UREÑA CASILLAS") -> DARINKA UREÑA CASILLAS | Q80: =IF(D80="","",VLOOKUP(MONTH(D80),Listas!$C$2:$D$14,2,0)) -> Diciembre | R80: =IF(D80="","",YEAR(D80)) -> 2020 | S80: =IF(D80="","",(DAY(D80))) -> 12 | T80: =IF(D80="","",S80-$W$1) -> 12 | U80: =IF(D80="","",(MONTH(D80))) -> 12 | V80: =IF(I80="","",(DAY(I80))) -> 27 | W80: =IF(I80="","",V80-$W$1) -> 27 | X80: =IF(I80="","",(MONTH(I80))) -> 12 | Y80: =IF(D80="","",(MONTH(D80))) -> 12 | Z80: =IFERROR(IF(I80="","", DATEDIF(I80, TODAY(), "Y")),0) -> 3 | AA80: =IF(Z80="","", IFS(Z80 >= 61, "61+ años", Z80 >= 51, "51-60 años", Z80 >= 40, "40-50 años", Z80 >= 20, "20-39 años", TRUE, "-20 años")) -> -20 años
A81: JAZMIN ALICIA ROMERO JOHNSON | B81: M | C81: Activo | D81: 43249 | E81: VI0002379720 | F81: =4602.9*7.41 -> 34107.489 | G81: UDIS | H81: Anual | I81: 44922 | K81: TC | L81: Vida | M81: Orvi | N81: jazmin_ro_jo@hotmail.com | O81: 3314251081 | P81: =IF(A81="","", "DARINKA UREÑA CASILLAS") -> DARINKA UREÑA CASILLAS | Q81: =IF(D81="","",VLOOKUP(MONTH(D81),Listas!$C$2:$D$14,2,0)) -> Mayo | R81: =IF(D81="","",YEAR(D81)) -> 2018 | S81: =IF(D81="","",(DAY(D81))) -> 29 | T81: =IF(D81="","",S81-$W$1) -> 29 | U81: =IF(D81="","",(MONTH(D81))) -> 5 | V81: =IF(I81="","",(DAY(I81))) -> 27 | W81: =IF(I81="","",V81-$W$1) -> 27 | X81: =IF(I81="","",(MONTH(I81))) -> 12 | Y81: =IF(D81="","",(MONTH(D81))) -> 5 | Z81: =IFERROR(IF(I81="","", DATEDIF(I81, TODAY(), "Y")),0) -> 3 | AA81: =IF(Z81="","", IFS(Z81 >= 61, "61+ años", Z81 >= 51, "51-60 años", Z81 >= 40, "40-50 años", Z81 >= 20, "20-39 años", TRUE, "-20 años")) -> -20 años
A82: JAZMIN JUDITH HERNANDEZ AGUIRRE | B82: M | C82: Activo | D82: 44740 | E82: VI0002675317 | F82: =2260.19*7.41 -> 16748.008 | G82: UDIS | H82: Anual | I82: 45015 | K82: TC | L82: Vida | M82: Segubeca | N82: jhernan8212@gmail.com | O82: 3310813799 | P82: =IF(A82="","", "DARINKA UREÑA CASILLAS") -> DARINKA UREÑA CASILLAS | Q82: =IF(D82="","",VLOOKUP(MONTH(D82),Listas!$C$2:$D$14,2,0)) -> Junio | R82: =IF(D82="","",YEAR(D82)) -> 2022 | S82: =IF(D82="","",(DAY(D82))) -> 28 | T82: =IF(D82="","",S82-$W$1) -> 28 | U82: =IF(D82="","",(MONTH(D82))) -> 6 | V82: =IF(I82="","",(DAY(I82))) -> 30 | W82: =IF(I82="","",V82-$W$1) -> 30 | X82: =IF(I82="","",(MONTH(I82))) -> 3 | Y82: =IF(D82="","",(MONTH(D82))) -> 6 | Z82: =IFERROR(IF(I82="","", DATEDIF(I82, TODAY(), "Y")),0) -> 3 | AA82: =IF(Z82="","", IFS(Z82 >= 61, "61+ años", Z82 >= 51, "51-60 años", Z82 >= 40, "40-50 años", Z82 >= 20, "20-39 años", TRUE, "-20 años")) -> -20 años
A83: JENIFER RIVERA LIRA | B83: M | C83: Activo | D83: 44848 | E83: VI0002695547 | F83: =241.19*12*7.65 -> 22141.242 | G83: UDIS | H83: Mensual | I83: 45260 | K83: TC | L83: Vida | M83: Vida Mujer | N83: jenilira@gmail.com | O83: 3328326940 | P83: =IF(A83="","", "DARINKA UREÑA CASILLAS") -> DARINKA UREÑA CASILLAS | Q83: =IF(D83="","",VLOOKUP(MONTH(D83),Listas!$C$2:$D$14,2,0)) -> Octubre | R83: =IF(D83="","",YEAR(D83)) -> 2022 | S83: =IF(D83="","",(DAY(D83))) -> 14 | T83: =IF(D83="","",S83-$W$1) -> 14 | U83: =IF(D83="","",(MONTH(D83))) -> 10 | V83: =IF(I83="","",(DAY(I83))) -> 30 | W83: =IF(I83="","",V83-$W$1) -> 30 | X83: =IF(I83="","",(MONTH(I83))) -> 11 | Y83: =IF(D83="","",(MONTH(D83))) -> 10 | Z83: =IFERROR(IF(I83="","", DATEDIF(I83, TODAY(), "Y")),0) -> 2 | AA83: =IF(Z83="","", IFS(Z83 >= 61, "61+ años", Z83 >= 51, "51-60 años", Z83 >= 40, "40-50 años", Z83 >= 20, "20-39 años", TRUE, "-20 años")) -> -20 años
A84: JENNIFER GODINEZ CASILLAS | B84: M | C84: Activo | D84: 43683 | E84: VI0002475012 | F84: =3636.96*7.65 -> 27822.744 | G84: UDIS | H84: Mensual | I84: 45157 | K84: TC | L84: Vida | M84: Imagina ser | N84: jennifer.godinez.c@hotmail.com | O84: 3324972428 | P84: =IF(A84="","", "DARINKA UREÑA CASILLAS") -> DARINKA UREÑA CASILLAS | Q84: =IF(D84="","",VLOOKUP(MONTH(D84),Listas!$C$2:$D$14,2,0)) -> Agosto | R84: =IF(D84="","",YEAR(D84)) -> 2019 | S84: =IF(D84="","",(DAY(D84))) -> 6 | T84: =IF(D84="","",S84-$W$1) -> 6 | U84: =IF(D84="","",(MONTH(D84))) -> 8 | V84: =IF(I84="","",(DAY(I84))) -> 19 | W84: =IF(I84="","",V84-$W$1) -> 19 | X84: =IF(I84="","",(MONTH(I84))) -> 8 | Y84: =IF(D84="","",(MONTH(D84))) -> 8 | Z84: =IFERROR(IF(I84="","", DATEDIF(I84, TODAY(), "Y")),0) -> 2 | AA84: =IF(Z84="","", IFS(Z84 >= 61, "61+ años", Z84 >= 51, "51-60 años", Z84 >= 40, "40-50 años", Z84 >= 20, "20-39 años", TRUE, "-20 años")) -> -20 años
A85: JESUS ADRIAN AVILA CABRAL | B85: H | C85: Activo | D85: 44091 | E85: VI0002554845 | F85: =1222.72*2*7.118 -> 17406.642 | G85: UDIS | H85: Semestral | I85: 44919 | K85: TC | L85: Vida | M85: Orvi | N85: jeadila@gmail.com | O85: 3314493281 | P85: =IF(A85="","", "DARINKA UREÑA CASILLAS") -> DARINKA UREÑA CASILLAS | Q85: =IF(D85="","",VLOOKUP(MONTH(D85),Listas!$C$2:$D$14,2,0)) -> Septiembre | R85: =IF(D85="","",YEAR(D85)) -> 2020 | S85: =IF(D85="","",(DAY(D85))) -> 17 | T85: =IF(D85="","",S85-$W$1) -> 17 | U85: =IF(D85="","",(MONTH(D85))) -> 9 | V85: =IF(I85="","",(DAY(I85))) -> 24 | W85: =IF(I85="","",V85-$W$1) -> 24 | X85: =IF(I85="","",(MONTH(I85))) -> 12 | Y85: =IF(D85="","",(MONTH(D85))) -> 9 | Z85: =IFERROR(IF(I85="","", DATEDIF(I85, TODAY(), "Y")),0) -> 3 | AA85: =IF(Z85="","", IFS(Z85 >= 61, "61+ años", Z85 >= 51, "51-60 años", Z85 >= 40, "40-50 años", Z85 >= 20, "20-39 años", TRUE, "-20 años")) -> -20 años
A86: JORGE FRANCISCO AREVALO CONTRERAS | B86: H | C86: Activo | D86: 44441 | E86: GM0000537792 | F86: 50624.26 | G86: MXN | H86: Anual | I86: 15-sep | K86: TD | L86: Gastos Médicos | M86: Integro | N86: jorge.fcoarevalo@gmail.com | O86: 3316996266 | P86: =IF(A86="","", "DARINKA UREÑA CASILLAS") -> DARINKA UREÑA CASILLAS | Q86: =IF(D86="","",VLOOKUP(MONTH(D86),Listas!$C$2:$D$14,2,0)) -> Septiembre | R86: =IF(D86="","",YEAR(D86)) -> 2021 | S86: =IF(D86="","",(DAY(D86))) -> 2 | T86: =IF(D86="","",S86-$W$1) -> 2 | U86: =IF(D86="","",(MONTH(D86))) -> 9 | V86: =IF(I86="","",(DAY(I86))) -> 15 | W86: =IF(I86="","",V86-$W$1) -> 15 | X86: =IF(I86="","",(MONTH(I86))) -> 9 | Y86: =IF(D86="","",(MONTH(D86))) -> 9 | Z86: =IFERROR(IF(I86="","", DATEDIF(I86, TODAY(), "Y")),0) -> 0 | AA86: =IF(Z86="","", IFS(Z86 >= 61, "61+ años", Z86 >= 51, "51-60 años", Z86 >= 40, "40-50 años", Z86 >= 20, "20-39 años", TRUE, "-20 años")) -> -20 años
A87: JORGE FRANCISCO AREVALO CONTRERAS | B87: H | C87: Activo | D87: 44544 | E87: VI0002639310 | F87: =4*7.118*1937.82 -> 55173.611 | G87: UDIS | H87: Trimestral | I87: 15-sep | K87: TD | L87: Vida | M87: Segubeca | N87: jorge.fcoarevalo@gmail.com | O87: 3316996266 | P87: =IF(A87="","", "DARINKA UREÑA CASILLAS") -> DARINKA UREÑA CASILLAS | Q87: =IF(D87="","",VLOOKUP(MONTH(D87),Listas!$C$2:$D$14,2,0)) -> Diciembre | R87: =IF(D87="","",YEAR(D87)) -> 2021 | S87: =IF(D87="","",(DAY(D87))) -> 14 | T87: =IF(D87="","",S87-$W$1) -> 14 | U87: =IF(D87="","",(MONTH(D87))) -> 12 | V87: =IF(I87="","",(DAY(I87))) -> 15 | W87: =IF(I87="","",V87-$W$1) -> 15 | X87: =IF(I87="","",(MONTH(I87))) -> 9 | Y87: =IF(D87="","",(MONTH(D87))) -> 12 | Z87: =IFERROR(IF(I87="","", DATEDIF(I87, TODAY(), "Y")),0) -> 0 | AA87: =IF(Z87="","", IFS(Z87 >= 61, "61+ años", Z87 >= 51, "51-60 años", Z87 >= 40, "40-50 años", Z87 >= 20, "20-39 años", TRUE, "-20 años")) -> -20 años
A88: JOSE DANIEL FLORES ARELLANO | B88: H | C88: Activo | D88: 43878 | E88: VI0002517688 | F88: =2*7.118*1341.86 -> 19102.719 | G88: UDIS | H88: Mensual | I88: 44908 | K88: TC | L88: Vida | M88: Orvi | N88: j.daniel.f.arellano@gmail.com | O88: 3325364430 | P88: =IF(A88="","", "DARINKA UREÑA CASILLAS") -> DARINKA UREÑA CASILLAS | Q88: =IF(D88="","",VLOOKUP(MONTH(D88),Listas!$C$2:$D$14,2,0)) -> Febrero | R88: =IF(D88="","",YEAR(D88)) -> 2020 | S88: =IF(D88="","",(DAY(D88))) -> 17 | T88: =IF(D88="","",S88-$W$1) -> 17 | U88: =IF(D88="","",(MONTH(D88))) -> 2 | V88: =IF(I88="","",(DAY(I88))) -> 13 | W88: =IF(I88="","",V88-$W$1) -> 13 | X88: =IF(I88="","",(MONTH(I88))) -> 12 | Y88: =IF(D88="","",(MONTH(D88))) -> 2 | Z88: =IFERROR(IF(I88="","", DATEDIF(I88, TODAY(), "Y")),0) -> 3 | AA88: =IF(Z88="","", IFS(Z88 >= 61, "61+ años", Z88 >= 51, "51-60 años", Z88 >= 40, "40-50 años", Z88 >= 20, "20-39 años", TRUE, "-20 años")) -> -20 años
A89: JOSE FRANCISCO SEDA CEJA | B89: H | C89: Activo | D89: 44818 | E89: VI0002689899 | F89: =2030.95*7.65 -> 15536.767 | G89: UDIS | H89: Anual | I89: 45248 | K89: tc | L89: Vida | M89: Orvi | N89: fsedaceja@gmail.com | O89: 3338715628 | P89: =IF(A89="","", "DARINKA UREÑA CASILLAS") -> DARINKA UREÑA CASILLAS | Q89: =IF(D89="","",VLOOKUP(MONTH(D89),Listas!$C$2:$D$14,2,0)) -> Septiembre | R89: =IF(D89="","",YEAR(D89)) -> 2022 | S89: =IF(D89="","",(DAY(D89))) -> 14 | T89: =IF(D89="","",S89-$W$1) -> 14 | U89: =IF(D89="","",(MONTH(D89))) -> 9 | V89: =IF(I89="","",(DAY(I89))) -> 18 | W89: =IF(I89="","",V89-$W$1) -> 18 | X89: =IF(I89="","",(MONTH(I89))) -> 11 | Y89: =IF(D89="","",(MONTH(D89))) -> 9 | Z89: =IFERROR(IF(I89="","", DATEDIF(I89, TODAY(), "Y")),0) -> 2 | AA89: =IF(Z89="","", IFS(Z89 >= 61, "61+ años", Z89 >= 51, "51-60 años", Z89 >= 40, "40-50 años", Z89 >= 20, "20-39 años", TRUE, "-20 años")) -> -20 años
A90: JOSEFINA GALVEZ | B90: M | C90: Activo | D90: 44507 | E90: GM0000544016 | F90: =7032.06*4 -> 28128.24 | G90: UDIS | H90: Mensual | I90: 44780 | K90: TC | L90: Gastos Médicos | M90: Practico | N90: josie_gg@hotmail.com | O90: 3318007866 | P90: =IF(A90="","", "DARINKA UREÑA CASILLAS") -> DARINKA UREÑA CASILLAS | Q90: =IF(D90="","",VLOOKUP(MONTH(D90),Listas!$C$2:$D$14,2,0)) -> Noviembre | R90: =IF(D90="","",YEAR(D90)) -> 2021 | S90: =IF(D90="","",(DAY(D90))) -> 7 | T90: =IF(D90="","",S90-$W$1) -> 7 | U90: =IF(D90="","",(MONTH(D90))) -> 11 | V90: =IF(I90="","",(DAY(I90))) -> 7 | W90: =IF(I90="","",V90-$W$1) -> 7 | X90: =IF(I90="","",(MONTH(I90))) -> 8 | Y90: =IF(D90="","",(MONTH(D90))) -> 11 | Z90: =IFERROR(IF(I90="","", DATEDIF(I90, TODAY(), "Y")),0) -> 3 | AA90: =IF(Z90="","", IFS(Z90 >= 61, "61+ años", Z90 >= 51, "51-60 años", Z90 >= 40, "40-50 años", Z90 >= 20, "20-39 años", TRUE, "-20 años")) -> -20 años
A91: JUAN ANTONIO VELAZQUEZ ALVAREZ | B91: H | C91: Activo | D91: 44693 | E91: VI0002666463 | F91: =4161.05*7.33 -> 30500.497 | G91: UDIS | H91: Anual | I91: 44993 | K91: TC | L91: Vida | M91: Orvi | N91: antonio.velazquez.alvarez@hotmail.com | O91: 8166551910 | P91: =IF(A91="","", "DARINKA UREÑA CASILLAS") -> DARINKA UREÑA CASILLAS | Q91: =IF(D91="","",VLOOKUP(MONTH(D91),Listas!$C$2:$D$14,2,0)) -> Mayo | R91: =IF(D91="","",YEAR(D91)) -> 2022 | S91: =IF(D91="","",(DAY(D91))) -> 12 | T91: =IF(D91="","",S91-$W$1) -> 12 | U91: =IF(D91="","",(MONTH(D91))) -> 5 | V91: =IF(I91="","",(DAY(I91))) -> 8 | W91: =IF(I91="","",V91-$W$1) -> 8 | X91: =IF(I91="","",(MONTH(I91))) -> 3 | Y91: =IF(D91="","",(MONTH(D91))) -> 5 | Z91: =IFERROR(IF(I91="","", DATEDIF(I91, TODAY(), "Y")),0) -> 3 | AA91: =IF(Z91="","", IFS(Z91 >= 61, "61+ años", Z91 >= 51, "51-60 años", Z91 >= 40, "40-50 años", Z91 >= 20, "20-39 años", TRUE, "-20 años")) -> -20 años
A92: JUAN CARLOS CONTRERAS VAZQUEZ | B92: H | C92: Activo | D92: 44174 | E92: VI0002571751 | F92: =1870.5*2*7.118 -> 26628.438 | G92: UDIS | H92: Semestral | I92: 44857 | K92: TD | L92: Vida | M92: Orvi | N92: juanleon1439@gmail.com | O92: 3331009288 | P92: =IF(A92="","", "DARINKA UREÑA CASILLAS") -> DARINKA UREÑA CASILLAS | Q92: =IF(D92="","",VLOOKUP(MONTH(D92),Listas!$C$2:$D$14,2,0)) -> Diciembre | R92: =IF(D92="","",YEAR(D92)) -> 2020 | S92: =IF(D92="","",(DAY(D92))) -> 9 | T92: =IF(D92="","",S92-$W$1) -> 9 | U92: =IF(D92="","",(MONTH(D92))) -> 12 | V92: =IF(I92="","",(DAY(I92))) -> 23 | W92: =IF(I92="","",V92-$W$1) -> 23 | X92: =IF(I92="","",(MONTH(I92))) -> 10 | Y92: =IF(D92="","",(MONTH(D92))) -> 12 | Z92: =IFERROR(IF(I92="","", DATEDIF(I92, TODAY(), "Y")),0) -> 3 | AA92: =IF(Z92="","", IFS(Z92 >= 61, "61+ años", Z92 >= 51, "51-60 años", Z92 >= 40, "40-50 años", Z92 >= 20, "20-39 años", TRUE, "-20 años")) -> -20 años
A93: KAREN DENISSE SEDA MUÑOZ | B93: M | C93: Activo | D93: 44576 | E93: VI0002645729 | F93: =2542.17*7.118 -> 18095.166 | G93: UDIS | H93: Anual | I93: 44595 | K93: TC | L93: Vida | M93: Orvi | N93: kdenisseseda@gmail.com | O93: 3312952384 | P93: =IF(A93="","", "DARINKA UREÑA CASILLAS") -> DARINKA UREÑA CASILLAS | Q93: =IF(D93="","",VLOOKUP(MONTH(D93),Listas!$C$2:$D$14,2,0)) -> Enero | R93: =IF(D93="","",YEAR(D93)) -> 2022 | S93: =IF(D93="","",(DAY(D93))) -> 15 | T93: =IF(D93="","",S93-$W$1) -> 15 | U93: =IF(D93="","",(MONTH(D93))) -> 1 | V93: =IF(I93="","",(DAY(I93))) -> 3 | W93: =IF(I93="","",V93-$W$1) -> 3 | X93: =IF(I93="","",(MONTH(I93))) -> 2 | Y93: =IF(D93="","",(MONTH(D93))) -> 1 | Z93: =IFERROR(IF(I93="","", DATEDIF(I93, TODAY(), "Y")),0) -> 4 | AA93: =IF(Z93="","", IFS(Z93 >= 61, "61+ años", Z93 >= 51, "51-60 años", Z93 >= 40, "40-50 años", Z93 >= 20, "20-39 años", TRUE, "-20 años")) -> -20 años
A94: KAREN ENRIQUEZ LEDEZMA | B94: M | C94: Activo | D94: 44678 | E94: VI0002662801 | F94: =219.13*12*7.31 -> 19222.084 | G94: UDIS | H94: Mensual | I94: 45154 | K94: TC | L94: Vida | M94: Orvi | N94: enriquezledezmakaren2@gmail.com | O94: 9875646190 | P94: =IF(A94="","", "DARINKA UREÑA CASILLAS") -> DARINKA UREÑA CASILLAS | Q94: =IF(D94="","",VLOOKUP(MONTH(D94),Listas!$C$2:$D$14,2,0)) -> Abril | R94: =IF(D94="","",YEAR(D94)) -> 2022 | S94: =IF(D94="","",(DAY(D94))) -> 27 | T94: =IF(D94="","",S94-$W$1) -> 27 | U94: =IF(D94="","",(MONTH(D94))) -> 4 | V94: =IF(I94="","",(DAY(I94))) -> 16 | W94: =IF(I94="","",V94-$W$1) -> 16 | X94: =IF(I94="","",(MONTH(I94))) -> 8 | Y94: =IF(D94="","",(MONTH(D94))) -> 4 | Z94: =IFERROR(IF(I94="","", DATEDIF(I94, TODAY(), "Y")),0) -> 2 | AA94: =IF(Z94="","", IFS(Z94 >= 61, "61+ años", Z94 >= 51, "51-60 años", Z94 >= 40, "40-50 años", Z94 >= 20, "20-39 años", TRUE, "-20 años")) -> -20 años
A95: KEVIN IVAN MARCHENA DUEÑAS | B95: H | C95: Activo | D95: 44309 | E95: VI0002597383 | F95: =7.118*4*922.34 -> 26260.864 | G95: UDIS | H95: Trimestral | I95: 44857 | K95: TC | L95: Vida | M95: Orvi | N95: markador_23@hotmail.com | O95: 3339527328 | P95: =IF(A95="","", "DARINKA UREÑA CASILLAS") -> DARINKA UREÑA CASILLAS | Q95: =IF(D95="","",VLOOKUP(MONTH(D95),Listas!$C$2:$D$14,2,0)) -> Abril | R95: =IF(D95="","",YEAR(D95)) -> 2021 | S95: =IF(D95="","",(DAY(D95))) -> 23 | T95: =IF(D95="","",S95-$W$1) -> 23 | U95: =IF(D95="","",(MONTH(D95))) -> 4 | V95: =IF(I95="","",(DAY(I95))) -> 23 | W95: =IF(I95="","",V95-$W$1) -> 23 | X95: =IF(I95="","",(MONTH(I95))) -> 10 | Y95: =IF(D95="","",(MONTH(D95))) -> 4 | Z95: =IFERROR(IF(I95="","", DATEDIF(I95, TODAY(), "Y")),0) -> 3 | AA95: =IF(Z95="","", IFS(Z95 >= 61, "61+ años", Z95 >= 51, "51-60 años", Z95 >= 40, "40-50 años", Z95 >= 20, "20-39 años", TRUE, "-20 años")) -> -20 años
A96: KIMBERLY MONTSERRAT SEDA MUÑOZ | B96: M | C96: Activo | D96: 44782 | E96: VI0002683192 | F96: =2061.92*7.65 -> 15773.688 | G96: UDIS | H96: Anual | I96: 45027 | K96: TC | L96: Vida | M96: Orvi | N96: kimberlysm00@gmail.com | O96: 3315544084 | P96: =IF(A96="","", "DARINKA UREÑA CASILLAS") -> DARINKA UREÑA CASILLAS | Q96: =IF(D96="","",VLOOKUP(MONTH(D96),Listas!$C$2:$D$14,2,0)) -> Agosto | R96: =IF(D96="","",YEAR(D96)) -> 2022 | S96: =IF(D96="","",(DAY(D96))) -> 9 | T96: =IF(D96="","",S96-$W$1) -> 9 | U96: =IF(D96="","",(MONTH(D96))) -> 8 | V96: =IF(I96="","",(DAY(I96))) -> 11 | W96: =IF(I96="","",V96-$W$1) -> 11 | X96: =IF(I96="","",(MONTH(I96))) -> 4 | Y96: =IF(D96="","",(MONTH(D96))) -> 8 | Z96: =IFERROR(IF(I96="","", DATEDIF(I96, TODAY(), "Y")),0) -> 3 | AA96: =IF(Z96="","", IFS(Z96 >= 61, "61+ años", Z96 >= 51, "51-60 años", Z96 >= 40, "40-50 años", Z96 >= 20, "20-39 años", TRUE, "-20 años")) -> -20 años
A97: LUCIA ORTEGA RAMIREZ | B97: M | C97: Activo | D97: 44278 | E97: VI0002591305 | F97: =420.27*12*7.118 -> 35897.782 | G97: UDIS | H97: Mensual | I97: 44769 | K97: TD | L97: Vida | M97: Orvi | N97: luciaortega2707@gmail.com | O97: 3316693326 | P97: =IF(A97="","", "DARINKA UREÑA CASILLAS") -> DARINKA UREÑA CASILLAS | Q97: =IF(D97="","",VLOOKUP(MONTH(D97),Listas!$C$2:$D$14,2,0)) -> Marzo | R97: =IF(D97="","",YEAR(D97)) -> 2021 | S97: =IF(D97="","",(DAY(D97))) -> 23 | T97: =IF(D97="","",S97-$W$1) -> 23 | U97: =IF(D97="","",(MONTH(D97))) -> 3 | V97: =IF(I97="","",(DAY(I97))) -> 27 | W97: =IF(I97="","",V97-$W$1) -> 27 | X97: =IF(I97="","",(MONTH(I97))) -> 7 | Y97: =IF(D97="","",(MONTH(D97))) -> 3 | Z97: =IFERROR(IF(I97="","", DATEDIF(I97, TODAY(), "Y")),0) -> 3 | AA97: =IF(Z97="","", IFS(Z97 >= 61, "61+ años", Z97 >= 51, "51-60 años", Z97 >= 40, "40-50 años", Z97 >= 20, "20-39 años", TRUE, "-20 años")) -> -20 años
A98: LUZ JIMENA APARICIO GARCIA | B98: M | C98: Activo | D98: 44913 | E98: GM0000586501 | F98: 16892.77 | G98: MXN | H98: Anual | I98: 45039 | K98: TC | L98: Gastos Médicos | M98: Integro | N98: jimeapariciogarcia@gmail.com | O98: 9842330600 | P98: =IF(A98="","", "DARINKA UREÑA CASILLAS") -> DARINKA UREÑA CASILLAS | Q98: =IF(D98="","",VLOOKUP(MONTH(D98),Listas!$C$2:$D$14,2,0)) -> Diciembre | R98: =IF(D98="","",YEAR(D98)) -> 2022 | S98: =IF(D98="","",(DAY(D98))) -> 18 | T98: =IF(D98="","",S98-$W$1) -> 18 | U98: =IF(D98="","",(MONTH(D98))) -> 12 | V98: =IF(I98="","",(DAY(I98))) -> 23 | W98: =IF(I98="","",V98-$W$1) -> 23 | X98: =IF(I98="","",(MONTH(I98))) -> 4 | Y98: =IF(D98="","",(MONTH(D98))) -> 12 | Z98: =IFERROR(IF(I98="","", DATEDIF(I98, TODAY(), "Y")),0) -> 3 | AA98: =IF(Z98="","", IFS(Z98 >= 61, "61+ años", Z98 >= 51, "51-60 años", Z98 >= 40, "40-50 años", Z98 >= 20, "20-39 años", TRUE, "-20 años")) -> -20 años
A99: MARA GABRIELA DUEÑAS SALGADO | B99: M | C99: Activo | D99: 44698 | E99: VI0002667040 | F99: =2550.33*7.33 -> 18693.919 | G99: UDIS | H99: Anual | I99: 45094 | K99: TC | L99: Vida | M99: Segubeca | N99: markador_23@hotmail.com | O99: 3331060698 | P99: =IF(A99="","", "DARINKA UREÑA CASILLAS") -> DARINKA UREÑA CASILLAS | Q99: =IF(D99="","",VLOOKUP(MONTH(D99),Listas!$C$2:$D$14,2,0)) -> Mayo | R99: =IF(D99="","",YEAR(D99)) -> 2022 | S99: =IF(D99="","",(DAY(D99))) -> 17 | T99: =IF(D99="","",S99-$W$1) -> 17 | U99: =IF(D99="","",(MONTH(D99))) -> 5 | V99: =IF(I99="","",(DAY(I99))) -> 17 | W99: =IF(I99="","",V99-$W$1) -> 17 | X99: =IF(I99="","",(MONTH(I99))) -> 6 | Y99: =IF(D99="","",(MONTH(D99))) -> 5 | Z99: =IFERROR(IF(I99="","", DATEDIF(I99, TODAY(), "Y")),0) -> 2 | AA99: =IF(Z99="","", IFS(Z99 >= 61, "61+ años", Z99 >= 51, "51-60 años", Z99 >= 40, "40-50 años", Z99 >= 20, "20-39 años", TRUE, "-20 años")) -> -20 años
A100: MARCO ANTONIO RAMOS REYNOSO | B100: H | C100: Activo | D100: 44259 | E100: VI0002588611 | F100: =1900.22*7.118 -> 13525.766 | G100: UDIS | H100: Anual | I100: 44660 | K100: TC | L100: Vida | M100: Orvi | N100: 01.ramosreynoso@gmail.com | O100: 3310244685 | P100: =IF(A100="","", "DARINKA UREÑA CASILLAS") -> DARINKA UREÑA CASILLAS | Q100: =IF(D100="","",VLOOKUP(MONTH(D100),Listas!$C$2:$D$14,2,0)) -> Marzo | R100: =IF(D100="","",YEAR(D100)) -> 2021 | S100: =IF(D100="","",(DAY(D100))) -> 4 | T100: =IF(D100="","",S100-$W$1) -> 4 | U100: =IF(D100="","",(MONTH(D100))) -> 3 | V100: =IF(I100="","",(DAY(I100))) -> 9 | W100: =IF(I100="","",V100-$W$1) -> 9 | X100: =IF(I100="","",(MONTH(I100))) -> 4 | Y100: =IF(D100="","",(MONTH(D100))) -> 3 | Z100: =IFERROR(IF(I100="","", DATEDIF(I100, TODAY(), "Y")),0) -> 4 | AA100: =IF(Z100="","", IFS(Z100 >= 61, "61+ años", Z100 >= 51, "51-60 años", Z100 >= 40, "40-50 años", Z100 >= 20, "20-39 años", TRUE, "-20 años")) -> -20 años
A101: MARIA AURORA RIOS GALVAN | B101: M | C101: Activo | D101: 44280 | E101: VI0002592088 | F101: =2*7.118*4574.84 -> 65127.422 | G101: UDIS | H101: Semestral | I101: 44708 | K101: TD | L101: Vida | M101: Orvi | N101: aleyois.cr@gmail.com | O101: 3316119244 | P101: =IF(A101="","", "DARINKA UREÑA CASILLAS") -> DARINKA UREÑA CASILLAS | Q101: =IF(D101="","",VLOOKUP(MONTH(D101),Listas!$C$2:$D$14,2,0)) -> Marzo | R101: =IF(D101="","",YEAR(D101)) -> 2021 | S101: =IF(D101="","",(DAY(D101))) -> 25 | T101: =IF(D101="","",S101-$W$1) -> 25 | U101: =IF(D101="","",(MONTH(D101))) -> 3 | V101: =IF(I101="","",(DAY(I101))) -> 27 | W101: =IF(I101="","",V101-$W$1) -> 27 | X101: =IF(I101="","",(MONTH(I101))) -> 5 | Y101: =IF(D101="","",(MONTH(D101))) -> 3 | Z101: =IFERROR(IF(I101="","", DATEDIF(I101, TODAY(), "Y")),0) -> 3 | AA101: =IF(Z101="","", IFS(Z101 >= 61, "61+ años", Z101 >= 51, "51-60 años", Z101 >= 40, "40-50 años", Z101 >= 20, "20-39 años", TRUE, "-20 años")) -> -20 años
A102: MARIA FLORENTINA CONTRERAS SANTILLAN | B102: M | C102: Activo | D102: 44433 | E102: VI0002620401 | F102: =2*2254.11*7.118 -> 32089.51 | G102: UDIS | H102: Semestral | I102: 44886 | K102: TC | L102: Vida | M102: Orvi | N102: florentina219011@gmail.com | O102: 3313983302 | P102: =IF(A102="","", "DARINKA UREÑA CASILLAS") -> DARINKA UREÑA CASILLAS | Q102: =IF(D102="","",VLOOKUP(MONTH(D102),Listas!$C$2:$D$14,2,0)) -> Agosto | R102: =IF(D102="","",YEAR(D102)) -> 2021 | S102: =IF(D102="","",(DAY(D102))) -> 25 | T102: =IF(D102="","",S102-$W$1) -> 25 | U102: =IF(D102="","",(MONTH(D102))) -> 8 | V102: =IF(I102="","",(DAY(I102))) -> 21 | W102: =IF(I102="","",V102-$W$1) -> 21 | X102: =IF(I102="","",(MONTH(I102))) -> 11 | Y102: =IF(D102="","",(MONTH(D102))) -> 8 | Z102: =IFERROR(IF(I102="","", DATEDIF(I102, TODAY(), "Y")),0) -> 3 | AA102: =IF(Z102="","", IFS(Z102 >= 61, "61+ años", Z102 >= 51, "51-60 años", Z102 >= 40, "40-50 años", Z102 >= 20, "20-39 años", TRUE, "-20 años")) -> -20 años
...

Sheet Asegurados
A5: Cliente | B5: Número de póliza | C5: Nombre Asegurado | D5: Parentesco | E5: Cumpleaños | F5: Mes Cumpleaños
B6: =IF(A6="","",VLOOKUP(A6,'BD Asesor'!$A$8:$E$1998,5,0)) | F6: =IF(E6="","",(MONTH(E6)))
B7: =IF(A7="","",VLOOKUP(A7,'BD Asesor'!$A$8:$E$1998,5,0)) | F7: =IF(E7="","",(MONTH(E7)))
B8: =IF(A8="","",VLOOKUP(A8,'BD Asesor'!$A$8:$E$1998,5,0)) | F8: =IF(E8="","",(MONTH(E8)))
B9: =IF(A9="","",VLOOKUP(A9,'BD Asesor'!$A$8:$E$1998,5,0)) | F9: =IF(E9="","",(MONTH(E9)))
B10: =IF(A10="","",VLOOKUP(A10,'BD Asesor'!$A$8:$E$1998,5,0)) | F10: =IF(E10="","",(MONTH(E10)))
B11: =IF(A11="","",VLOOKUP(A11,'BD Asesor'!$A$8:$E$1998,5,0)) | F11: =IF(E11="","",(MONTH(E11)))
B12: =IF(A12="","",VLOOKUP(A12,'BD Asesor'!$A$8:$E$1998,5,0)) | F12: =IF(E12="","",(MONTH(E12)))
B13: =IF(A13="","",VLOOKUP(A13,'BD Asesor'!$A$8:$E$1998,5,0)) | F13: =IF(E13="","",(MONTH(E13)))
B14: =IF(A14="","",VLOOKUP(A14,'BD Asesor'!$A$8:$E$1998,5,0)) | F14: =IF(E14="","",(MONTH(E14)))
B15: =IF(A15="","",VLOOKUP(A15,'BD Asesor'!$A$8:$E$1998,5,0)) | F15: =IF(E15="","",(MONTH(E15)))
B16: =IF(A16="","",VLOOKUP(A16,'BD Asesor'!$A$8:$E$1998,5,0)) | F16: =IF(E16="","",(MONTH(E16)))
B17: =IF(A17="","",VLOOKUP(A17,'BD Asesor'!$A$8:$E$1998,5,0)) | F17: =IF(E17="","",(MONTH(E17)))
... B1000: =IF(A1000="","",VLOOKUP(A1000,'BD Asesor'!$A$8:$E$1998,5,0)) | F1000: =IF(E1000="","",(MONTH(E1000)))

Sheet Prospectos
C4: 15 dias antes
C5: Hoy | G5: Tabla de Status | L5: Tabla de Fuente | P5: Tabla de Referenciados | S5: Tabla de Grupo de Referidos
C6: Vencido
A7: Prospecto | B7: Fuente | C7: Siguiente Contacto | D7: Referenciado por | E7: Diferencia de dia | F7: TELEFONO | G7: STATUS | H7: Status | I7: Prospecto | J7: Porcentaje | L7: Fuente | M7: Prospecto | N7: Porcentaje
A8: AMAURI | B8: Referido | C8: 44595 | D8: DR. BARRAGAN | E8: =IF(C8 ="","",C8-Listas!$B$2) -> -1566 | F8: 3313014779 | G8: Cita cierre | H8: Cerrado | I8: =COUNTIF($A$7:$D$1000,H8) -> 0 | J8: =I8/$I$12 -> #DIV/0! | L8: Mercado cálido | M8: =COUNTIF($A$7:$D$1000,L8) -> 0 | N8: =M8/$I$12 -> #DIV/0!
A9: DR. JIMENEZ | B9: Referido | C9: 44601 | D9: DR. BARRAGAN | E9: =IF(C9 ="","",C9-Listas!$B$2) -> -1560 | F9: 3336260468 | G9: Cita cierre | H9: Cita de cierre | I9: =COUNTIF($A$7:$D$1000,H9) -> 0 | J9: =I9/$I$12 -> #DIV/0! | L9: Redes sociales | M9: =COUNTIF($A$7:$D$1000,L9) -> 0 | N9: =M9/$I$12 -> #DIV/0!
A10: DR.CARDE | B10: Referido | C10: 44600 | D10: DR. BARRAGAN | E10: =IF(C10 ="","",C10-Listas!$B$2) -> -1561 | F10: 3316727678 | G10: CITA INICIAL | H10: Cita inicial | I10: =COUNTIF($A$7:$D$1000,H10) -> 0 | J10: =I10/$I$12 -> #DIV/0! | L10: Referido | M10: =COUNTIF($A$7:$D$1000,L10) -> 327 | N10: =M10/$I$12 -> #DIV/0!
A11: DR. ISLAS | B11: Referido | C11: X | D11: DR. BARRAGAN | E11: =IF(C11 ="","",C11-Listas!$B$2) -> #VALUE! | F11: 3310440720 | G11: LLAMAR | H11: Contactado | I11: =COUNTIF($A$7:$D$1000,H11) -> 0 | J11: =I11/$I$12 -> #DIV/0! | L11: Otro | M11: =COUNTIF($A$7:$D$1000,L11) -> 0 | N11: =M11/$I$12 -> #DIV/0!
A12: DR. NAVA | B12: Referido | C12: X | D12: DR. BARRAGAN | E12: =IF(C12 ="","",C12-Listas!$B$2) -> #VALUE! | F12: 3313038073 | G12: X | H12: Total | I12: =SUM(I8:I11) -> 0 | J12: =SUM(J8:J11) -> #DIV/0! | L12: Total | M12: =SUM(M8:M11) -> 327 | N12: =SUM(N8:N11) -> #DIV/0!
A13: LUIS FERNANDO | B13: Referido | C13: X | D13: CLAUDIO MARTIN | E13: =IF(C13 ="","",C13-Listas!$B$2) -> #VALUE! | F13: 3311690262 | G13: 19 DE MAYO
A14: FRANCISCO | B14: Referido | C14: PLAN ORVI | D14: CLAUDIO MARTIN | E14: =IF(C14 ="","",C14-Listas!$B$2) -> #VALUE! | F14: 3331675304 | G14: CERRADO
A15: JOSE ANTONIO | B15: Referido | C15: YA TIENE PLANES | D15: CLAUDIO MARTIN | E15: =IF(C15 ="","",C15-Listas!$B$2) -> #VALUE! | F15: 3313591320 | G15: 19 DE MAYO
A16: MAELY SASSO | B16: Referido | C16: X | D16: CLAUDIO MARTIN | E16: =IF(C16 ="","",C16-Listas!$B$2) -> #VALUE! | F16: 3314257494 | G16: 25 DE ABRIL
A17: JUAN PABLO | B17: Referido | C17: X | D17: CLAUDIO MARTIN | E17: =IF(C17 ="","",C17-Listas!$B$2) -> #VALUE! | F17: 3311868613 | G17: X
A18: MIGUEL TABLON | B18: Referido | C18: X | D18: CLAUDIO MARTIN | E18: =IF(C18 ="","",C18-Listas!$B$2) -> #VALUE! | F18: 3311768094 | G18: X
A19: ADAN | B19: Referido | C19: X | D19: CARLA MARTINEZ | E19: =IF(C19 ="","",C19-Listas!$B$2) -> #VALUE! | F19: 3312693025 | G19: 01 DE ABRIL 2025
A20: ALANIS | B20: Referido | C20: X | D20: CARLA MARTINEZ | E20: =IF(C20 ="","",C20-Listas!$B$2) -> #VALUE! | F20: 3311769244 | G20: 2 DE ENERO 2025
A21: ALE MEZA | B21: Referido | C21: X | D21: CARLA MARTINEZ | E21: =IF(C21 ="","",C21-Listas!$B$2) -> #VALUE! | F21: 3334560402 | G21: 12 DE FEBRERO 2025
A22: ALEX | B22: Referido | C22: X | D22: CARLA MARTINEZ | E22: =IF(C22 ="","",C22-Listas!$B$2) -> #VALUE! | F22: 3339548158 | G22: 5 DE FEBRERO 2025
A23: ALEX GMM | B23: Referido | C23: X | D23: CARLA MARTINEZ | E23: =IF(C23 ="","",C23-Listas!$B$2) -> #VALUE! | F23: 3319165772 | G23: 01 DE ABRIL 2025
A24: ALICIA | B24: Referido | C24: YA TIENE PLANES | D24: CARLA MARTINEZ | E24: =IF(C24 ="","",C24-Listas!$B$2) -> #VALUE! | F24: 3311105038 | G24: 2 DE ENERO 2025
... A26: ANA | B26: Referido | C26: X | D26: CARLA MARTINEZ | E26: =IF(C26 ="","",C26-Listas!$B$2) -> #VALUE! | F26: 3317879808 | G26: 14 DE ENERO 2025
A27: ANGIE | B27: Referido | C27: NO CONTESTA | D27: CARLA MARTINEZ | E27: =IF(C27 ="","",C27-Listas!$B$2) -> #VALUE! | F27: X | G27: 2 DE ENERO 2025
A28: X | B28: Referido | C28: PREGUNTAR NOMBRE | D28: CARLA MARTINEZ | E28: =IF(C28 ="","",C28-Listas!$B$2) -> #VALUE! | F28: 3310384826 | G28: 2 DE ENERO 2025
A29: BETO ROMO | B29: Referido | C29: X | D29: CARLA MARTINEZ | E29: =IF(C29 ="","",C29-Listas!$B$2) -> #VALUE! | F29: 33 1822 9636 | G29: 12 DE FEBRERO 2025
A30: CESAR | B30: Referido | C30: NO LE INTERESA | D30: CARLA MARTINEZ | E30: =IF(C30 ="","",C30-Listas!$B$2) -> #VALUE! | F30: 33 1286 5078 | G30: 2 DE ENERO 2025
A31: CHARLIE | B31: Referido | C31: X | D31: CARLA MARTINEZ | E31: =IF(C31 ="","",C31-Listas!$B$2) -> #VALUE! | F31: 664 335 4558 | G31: 5 DE FEBERO 2025
A32: JOSE | B32: Referido | C32: X | D32: CARLA MARTINEZ | E32: =IF(C32 ="","",C32-Listas!$B$2) -> #VALUE! | F32: 33 1431 7950 | G32: 2 DE ENERO 2025
A33: CHAVA CHIVAS | B33: Referido | C33: X | D33: CARLA MARTINEZ | E33: =IF(C33 ="","",C33-Listas!$B$2) -> #VALUE! | F33: 33 3839 8680 | G33: 01 DE ABRIL 2025
A34: CRIS BRAMBILA | B34: Referido | C34: YA TIENE PPR Y VARIOS PLANES | D34: CARLA MARTINEZ | E34: =IF(C34 ="","",C34-Listas!$B$2) -> #VALUE! | F34: 33 3167 5044 | G34: 2 DE ENERO 2025
A35: DAVID ALEX | B35: Referido | C35: X | D35: CARLA MARTINEZ | E35: =IF(C35 ="","",C35-Listas!$B$2) -> #VALUE! | F35: 33 1573 9184 | G35: 01 DE ABRIL 2025
A36: DENTISTA VERO | B36: Referido | C36: x | D36: CARLA MARTINEZ | E36: =IF(C36 ="","",C36-Listas!$B$2) -> #VALUE! | F36: 33 3508 6396 | G36: 01 DE ABRIL 2025
A37: DIANA | B37: Referido | C37: X | D37: CARLA MARTINEZ | E37: =IF(C37 ="","",C37-Listas!$B$2) -> #VALUE! | F37: 33 1822 5060 | G37: 01 DE ABRIL 2025
A38: DIANA OCAMPO | B38: Referido | C38: JUSTO CONTRATO GMM | D38: CARLA MARTINEZ | E38: =IF(C38 ="","",C38-Listas!$B$2) -> #VALUE! | F38: 33 1255 7032 | G38: 01 DE ABRIL 2025
A39: DIEGO CIRQUE | B39: Referido | C39: X | D39: CARLA MARTINEZ | E39: =IF(C39 ="","",C39-Listas!$B$2) -> #VALUE! | F39: 33 1976 5481 | G39: 02 DE ABRIL 2025
A40: EDGAR ALTEA | B40: Referido | C40: X | D40: CARLA MARTINEZ | E40: =IF(C40 ="","",C40-Listas!$B$2) -> #VALUE! | F40: 33 1893 0520 | G40: 02 DE ABRIL 2025
... A54: KAROL PEREZ | B54: Referido | C54: YA TIENE PLANES EN MONTERREY | D54: CARLA MARTINEZ | E54: =IF(C54 ="","",C54-Listas!$B$2) -> #VALUE! | F54: 33 1445 5799 | G54: 14 DE ABRIL 2025
A55: KAROL VARGAS | B55: Referido | C55: X | D55: CARLA MARTINEZ | E55: =IF(C55 ="","",C55-Listas!$B$2) -> #VALUE! | F55: 3314312352 | G55: 14 DE ABRIL 2025
A56: KEISSY RUIZ | B56: Referido | C56: X | D56: CARLA MARTINEZ | E56: =IF(C56 ="","",C56-Listas!$B$2) -> #VALUE! | F56: 33 3749 2139 | G56: 16 DE ABRIL 2025
A57: KEVIN CONEJO | B57: Referido | C57: BUSCAR EN AGOSTO 2025 | D57: CARLA MARTINEZ | E57: =IF(C57 ="","",C57-Listas!$B$2) -> #VALUE! | F57: 33 1449 7109 | G57: 02 DE MAYO 2025
A58: KRIS | B58: Referido | C58: YA TIENE ASESOR | D58: CARLA MARTINEZ | E58: =IF(C58 ="","",C58-Listas!$B$2) -> #VALUE! | F58: 33 3390 0438 | G58: 16 DE ABRIL 2025
A59: LAU LOZANO | B59: Referido | C59: REFERIDOS NADA MAS | D59: CARLA MARTINEZ | E59: =IF(C59 ="","",C59-Listas!$B$2) -> #VALUE! | F59: 33 1219 6168 | G59: 16 DE ABRIL 2025
A60: LUISA RAMOS | B60: Referido | C60: X | D60: CARLA MARTINEZ | E60: =IF(C60 ="","",C60-Listas!$B$2) -> #VALUE! | F60: 33 1534 3108 | G60: 06 DE MAYO 2025
A61: LUISA ROMO | B61: Referido | C61: X | D61: CARLA MARTINEZ | E61: =IF(C61 ="","",C61-Listas!$B$2) -> #VALUE! | F61: 33 1670 5429 | G61: 06 DE MAYO 2025
A62: LUPITA GOMEZ | B62: Referido | C62: YA TIENE METFLIFE | D62: CARLA MARTINEZ | E62: =IF(C62 ="","",C62-Listas!$B$2) -> #VALUE! | F62: 33 1356 3320 | G62: 06 DE MAYO 2025
A63: MAFER DE LA TORRE | B63: Referido | C63: X | D63: CARLA MARTINEZ | E63: =IF(C63 ="","",C63-Listas!$B$2) -> #VALUE! | F63: 33 1804 3849 | G63: 12 DE MAYO 2025
A64: MAFER MORA | B64: Referido | C64: MAMA ASESORA X | D64: CARLA MARTINEZ | E64: =IF(C64 ="","",C64-Listas!$B$2) -> #VALUE! | F64: 33 1488 3859 | G64: 12 DE MAYO 2025
A65: MAFER VEGA | B65: Referido | C65: YA TIENE ASESOR | D65: CARLA MARTINEZ | E65: =IF(C65 ="","",C65-Listas!$B$2) -> #VALUE! | F65: 33 1691 5204 | G65: 13 DE NOVIEMBRE 24
A66: MARIANA | B66: Referido | C66: X | D66: CARLA MARTINEZ | E66: =IF(C66 ="","",C66-Listas!$B$2) -> #VALUE! | F66: 33 1518 9312 | G66: 06 DE MAYO 2025
A67: MARIANA CUEME | B67: Referido | C67: X | D67: CARLA MARTINEZ | E67: =IF(C67 ="","",C67-Listas!$B$2) -> #VALUE! | F67: 33 3661 2991 | G67: 06 DE MAYO 2025
... A84: ZUPY ZUCAMP | B84: Referido | C84: X | D84: CARLA MARTINEZ | E84: =IF(C84 ="","",C84-Listas!$B$2) -> #VALUE! | F84: 33 3569 3413 | G84: 12 DE MAYO 2025
A85: EVER | B85: Referido | C85: X | D85: GERMAN URIBE | E85: =IF(C85 ="","",C85-Listas!$B$2) -> #VALUE! | F85: 4433371127 | G85: 13 DE MAYO 2025
A86: ALEJANDRA ESQUIVEL | B86: Referido | C86: ES ASESORA DE SEGUROS | D86: JOYCE URIBE | E86: =IF(C86 ="","",C86-Listas!$B$2) -> #VALUE! | F86: 7531317473 | G86: 02 DE JUNIO 2025
A87: ALEJANDRA GIL | B87: Referido | C87: X | D87: JOYCE URIBE | E87: =IF(C87 ="","",C87-Listas!$B$2) -> #VALUE! | F87: 4434574501 | G87: 02 DE JUNIO 2025
A88: SEBASTIAN ALEGRIA | B88: Referido | C88: NO LE INTERESA | D88: PRIMO | E88: =IF(C88 ="","",C88-Listas!$B$2) -> #VALUE! | F88: 3931173449 | G88: 03 DE JUNIO 2025
A89: HOLBEING ALFARO GALINDEZ | B89: Referido | C89: BUZON DIRECTO | D89: TANIA URIBE | E89: =IF(C89 ="","",C89-Listas!$B$2) -> #VALUE! | F89: 4432210610 | G89: 03 DE JUNIO 2025
A90: ALMA | B90: Referido | C90: X | D90: JOYCE URIBE | E90: =IF(C90 ="","",C90-Listas!$B$2) -> #VALUE! | F90: 4432853725 | G90: 04 DE JUNIO 2025
A91: CRISTIAN ALVAREZ | B91: Referido | C91: X | D91: JOYCE URIBE | E91: =IF(C91 ="","",C91-Listas!$B$2) -> #VALUE! | F91: 4431665560 | G91: 03 DE JUNIO 2025
A92: AMPARO | B92: Referido | C92: X | D92: JOYCE URIBE | E92: =IF(C92 ="","",C92-Listas!$B$2) -> #VALUE! | F92: 4431361752 | G92: 03 DE JUNIO 2025
A93: MONICA ANDRES | B93: Referido | C93: BUZON DIRECTO | D93: TANIA URIBE | E93: =IF(C93 ="","",C93-Listas!$B$2) -> #VALUE! | F93: 5517669491 | G93: 03 DE JUNIO 2025
A94: CESAR VILLEGAS | B94: Referido | C94: X | D94: JOYCE URIBE | E94: =IF(C94 ="","",C94-Listas!$B$2) -> #VALUE! | F94: 4432812608 | G94: 04 DE JUNIO 2025
A95: JAIME | B95: Referido | C95: YA TIENE PLANES | D95: JOYCE URIBE | E95: =IF(C95 ="","",C95-Listas!$B$2) -> #VALUE! | F95: 4433565044 | G95: 03 DE JUNIO 2025
A96: ADRIANA | B96: Referido | C96: BUZON DIRECTO | D96: JOYCE URIBE | E96: =IF(C96 ="","",C96-Listas!$B$2) -> #VALUE! | F96: 4437223363 | G96: 04 DE JUNIO 2025
... A111: MIGUEL ANGEL FABELA | B111: Referido | C111: X | D111: JOYCE URIBE | E111: =IF(C111 ="","",C111-Listas!$B$2) -> #VALUE! | F111: 4431437268 | G111: 28 DE JULIO 2025
A112: EDUARDO GONZALEZ | B112: Referido | C112: X | D112: TANIA URIBE | E112: =IF(C112 ="","",C112-Listas!$B$2) -> #VALUE! | F112: 9999055449 / 4431091895
A113: HUMBERTO GORDILLO | B113: Referido | C113: ULTIMO MSJ | D113: TANIA URIBE | E113: =IF(C113 ="","",C113-Listas!$B$2) -> #VALUE! | F113: 4433301292 | G113: 28 DE JULIO 2025
A114: ALEJANDRO CORTES | B114: Referido | C114: ULTIMO MSJ | D114: TANIA URIBE | E114: =IF(C114 ="","",C114-Listas!$B$2) -> #VALUE! | F114: 4433781091 | G114: 28 DE JULIO 2025
A115: ARTURO CHAVEZ ZAMORA | B115: Referido | C115: ULTIMO MSJ | D115: TANIA URIBE | E115: =IF(C115 ="","",C115-Listas!$B$2) -> #VALUE! | F115: 4433384968 | G115: 28 DE JULIO 2025
A116: CARLA PALOU | B116: Referido | C116: YA TIENE PLANES PERO GUARDAR | D116: TANIA URIBE | E116: =IF(C116 ="","",C116-Listas!$B$2) -> #VALUE! | F116: 2224457519 | G116: 28 DE JULIO 2025
A117: CARLOS JUAREZ | B117: Referido | C117: X | D117: TANIA URIBE | E117: =IF(C117 ="","",C117-Listas!$B$2) -> #VALUE! | F117: 5514518682 | G117: 28 DE JULIO 2025
A118: DAVID LEON | B118: Referido | C118: YA TIENE TODO | D118: TANIA URIBE | E118: =IF(C118 ="","",C118-Listas!$B$2) -> #VALUE! | F118: 4432092786 | G118: 28 DE JULIO 2025
A119: EDGAR TARSICIO | B119: Referido | C119: X | D119: TANIA URIBE | E119: =IF(C119 ="","",C119-Listas!$B$2) -> #VALUE! | F119: 4431550860 | G119: 28 DE JULIO 2025
A120: EDITH GONZALEZ | B120: Referido | C120: YA TIENE TODO EN GNP | D120: TANIA URIBE | E120: =IF(C120 ="","",C120-Listas!$B$2) -> #VALUE! | F120: 5566962168 | G120: 28 DE JULIO 2025
A121: FERNANDO PONCE DE LEON | B121: Referido | C121: X | D121: TANIA URIBE | E121: =IF(C121 ="","",C121-Listas!$B$2) -> #VALUE! | F121: 4432218094 | G121: 28 DE JULIO 2025
A122: GEORGINA VALDEZ | B122: Referido | C122: NO INTERESADO | D122: TANIA URIBE | E122: =IF(C122 ="","",C122-Listas!$B$2) -> #VALUE! | F122: 5551061793 | G122: 28 DE JULIO 2025
A123: GUILLERMO BARBA | B123: Referido | D123: TANIA URIBE | E123: =IF(C123 ="","",C123-Listas!$B$2) | F123: 4431600083 | G123: 28 DE JULIO 2025
A124: GUILLERMO ZAVALA | B124: Referido | D124: TANIA URIBE | E124: =IF(C124 ="","",C124-Listas!$B$2) | F124: 4434101654
A125: IVAN CASTRO | B125: Referido | D125: TANIA URIBE | E125: =IF(C125 ="","",C125-Listas!$B$2) | F125: 5529479697
A126: IVAN VERDIN | B126: Referido | D126: TANIA URIBE | E126: =IF(C126 ="","",C126-Listas!$B$2) | F126: 4433950141
A127: JAIME CALDERON | B127: Referido | D127: TANIA URIBE | E127: =IF(C127 ="","",C127-Listas!$B$2) | F127: 4433796974
A128: JORGE VAZQUEZ | B128: Referido | D128: TANIA URIBE | E128: =IF(C128 ="","",C128-Listas!$B$2) | F128: 4433181411
A129: JOSE QUINTERO | B129: Referido | D129: TANIA URIBE | E129: =IF(C129 ="","",C129-Listas!$B$2) | F129: 4433183503
A130: JOSE PADILLA | B130: Referido | D130: TANIA URIBE | E130: =IF(C130 ="","",C130-Listas!$B$2) | F130: 4433770757
A131: JOSUE ESCUTIA | B131: Referido | D131: TANIA URIBE | E131: =IF(C131 ="","",C131-Listas!$B$2) | F131: 4434403313
A132: JUAN PABLO TOLEDO | B132: Referido | D132: TANIA URIBE | E132: =IF(C132 ="","",C132-Listas!$B$2) | F132: 4432736774
A133: JUAN TINAJERO | B133: Referido | D133: TANIA URIBE | E133: =IF(C133 ="","",C133-Listas!$B$2) | F133: 4431551180
A134: LENIN | B134: Referido | D134: TANIA URIBE | E134: =IF(C134 ="","",C134-Listas!$B$2) | F134: 4431645018
A135: LEONARDO GARCIA | B135: Referido | D135: TANIA URIBE | E135: =IF(C135 ="","",C135-Listas!$B$2) | F135: 4433690339
... A150: EDUARDO QUINTANA | B150: Referido | D150: TANIA URIBE | E150: =IF(C150 ="","",C150-Listas!$B$2) | F150: 4431551917
A151: OSCAR HUGO GONZALEZ | B151: Referido | C151: X | D151: DIGNA | E151: =IF(C151 ="","",C151-Listas!$B$2) -> #VALUE! | F151: 3316231578 | G151: 04 DE AGOSTO 2025
A152: RAUL ANGELES | B152: Referido | C152: X | D152: DIGNA | E152: =IF(C152 ="","",C152-Listas!$B$2) -> #VALUE! | F152: 3331400515 | G152: 28 DE JULIO 2025
A153: SAUL QUEVEDO | B153: Referido | C153: YA TIENE PLAN EN SEGUROS | D153: DIGNA | E153: =IF(C153 ="","",C153-Listas!$B$2) -> #VALUE! | F153: 3314393267 | G153: 16 DE JULIO 24
A154: ALEJANDRO GASPAR | B154: Referido | C154: X | D154: DIGNA | E154: =IF(C154 ="","",C154-Listas!$B$2) -> #VALUE! | F154: 3313859028 | G154: 16 DE JULIO 24
A155: GABRIELA FRIAS | B155: Referido | C155: YA TIENE PLAN EN SEGUROS | D155: DIGNA | E155: =IF(C155 ="","",C155-Listas!$B$2) -> #VALUE! | F155: 3323852082 | G155: 16 DE JULIO 24
A156: JOSE RAMON BECERA ZENDEJAS | B156: Referido | C156: X | D156: DIGNA | E156: =IF(C156 ="","",C156-Listas!$B$2) -> #VALUE! | F156: 33142767770 | G156: 16 DE JULIO 24
A157: ADRIANA ZERMEÑO ZAMORA | B157: Referido | C157: X | D157: DIGNA | E157: =IF(C157 ="","",C157-Listas!$B$2) -> #VALUE! | F157: 3312890546 | G157: 17 DE JULIO 24
A158: ALEJANDRA CHAVEZ | B158: Referido | C158: YA TIENE PLAN EN SEGUROS | D158: DIGNA | E158: =IF(C158 ="","",C158-Listas!$B$2) -> #VALUE! | F158: 3312257970 | G158: 17 DE JULIO 24
A159: ALEJANDRO ALFARO | B159: Referido | C159: BUZON DIRECTO | D159: DIGNA | E159: =IF(C159 ="","",C159-Listas!$B$2) -> #VALUE! | F159: 3338067309 | G159: 28 DE JULIO 2025
A160: ALMA DELIA VELAZQUEZ ALVAREZ | B160: Referido | C160: X | D160: DIGNA | E160: =IF(C160 ="","",C160-Listas!$B$2) -> #VALUE! | F160: 3325785141 | G160: 04 DE AGOSTO 2025
A161: ANA CRISTINA MERCADO FERNANDEZ | B161: Referido | C161: YA TIENE PLAN EN SEGUROS | D161: DIGNA | E161: =IF(C161 ="","",C161-Listas!$B$2) -> #VALUE! | F161: 3338397801 | G161: 17 DE JULIO 24
...

Sheet Análisis de Info Histórico
C3: Análisis de Información Histórico
CH8: Tabla de Número de pólizas por Año
B9: Promedio de Prima anual | G9: Tabla de Número de pólizas por año | P9: Hombre vs Mujer | U9: Promedio de Prima anual Hombre vs Mujer | AC9: Tabla de Número de pólizas por año Hombre vs Mujer | AK9: Bloque de edades | AP9: Promedio de Prima anual por edades | BA9: Tabla de Número de pólizas por año por edades | BN9: Promedio de Prima anual Vida | BS9: Tabla de Número de pólizas de Vida por año | BX9: Promedio de Prima anual Gastos Médicos | CC9: Tabla de Número de pólizas de Gastos Médicos por año | CO9: Tabla de Modo de cobro | CS9: Tabla de Tipo de moneda | CW9: Tabla de Forma de pago
CH11: Mes | CI11: Número de polizas | CO11: Modo de Cobro | CP11: Cantidad de pagos | CQ11: Porcentaje | CS11: Tipo de moneda | CT11: Cantidad de pagos | CU11: Porcentaje | CW11: Forma de pago | CX11: Cantidad de pagos | CY11: Porcentaje
CH12: 2018 | CI12: =COUNTIFS('BD Asesor'!$R:$R,CH12) -> 3 | CO12: TC | CP12: =COUNTIF('BD Asesor'!$A:$L,CO12) -> 146 | CQ12: =CP12/$CP$14 -> 0.66666667 | CS12: MXN | CT12: =COUNTIF('BD Asesor'!$A:$L,CS12) -> 84 | CU12: =CT12/$CT$15 -> 0.32307692 | CW12: Mensual | CX12: =COUNTIF('BD Asesor'!$A:$L,CW12) -> 61 | CY12: =CX12/$CX$16 -> 0.23282443
CH13: 2019 | CI13: =COUNTIFS('BD Asesor'!$R:$R,CH13) -> 1 | CO13: TD | CP13: =COUNTIF('BD Asesor'!$A:$L,CO13) -> 73 | CQ13: =CP13/$CP$14 -> 0.33333333 | CS13: USD | CT13: =COUNTIF('BD Asesor'!$A:$L,CS13) -> 3 | CU13: =CT13/$CT$15 -> 0.011538462 | CW13: Trimestral | CX13: =COUNTIF('BD Asesor'!$A:$L,CW13) -> 19 | CY13: =CX13/$CX$16 -> 0.072519084
CH14: 2021 | CI14: =COUNTIFS('BD Asesor'!$R:$R,CH14) -> 45 | CO14: Total | CP14: =SUM(CP12:CP13) -> 219 | CS14: UDIS | CT14: =COUNTIF('BD Asesor'!$A:$L,CS14) -> 173 | CU14: =CT14/$CT$15 -> 0.66538462 | CW14: Semestral | CX14: =COUNTIF('BD Asesor'!$A:$L,CW14) -> 44 | CY14: =CX14/$CX$16 -> 0.16793893
CH15: 2022 | CI15: =COUNTIFS('BD Asesor'!$R:$R,CH15) -> 44 | CS15: Total | CT15: =SUM(CT12:CT14) -> 260 | CW15: Anual | CX15: =COUNTIF('BD Asesor'!$A:$L,CW15) -> 138 | CY15: =CX15/$CX$16 -> 0.52671756
CH16: 2023 | CI16: =COUNTIFS('BD Asesor'!$R:$R,CH16) -> 44 | CW16: Total | CX16: =SUM(CX12:CX15) -> 262
CH17: 2024 | CI17: =COUNTIFS('BD Asesor'!$R:$R,CH17) -> 43
CH18: 2025 | CI18: =COUNTIFS('BD Asesor'!$R:$R,CH18) -> 32 | CO18: Tabla de Tipo de plan | CS18: Tabla de Estado de Pólizas
CH19: 2026 | CI19: =COUNTIFS('BD Asesor'!$R:$R,CH19) -> 11 | CO19: Tipo de Plan | CP19: Cantidad de Tipo de plan | CQ19: Porcentaje | CS19: Estado | CT19: Cantidad de pagos | CU19: Porcentaje
CH20: 2027 | CI20: =COUNTIFS('BD Asesor'!$R:$R,CH20) -> 0 | CO20: Vida | CP20: =COUNTIF('BD Asesor'!$A:$L,CO20) -> 176 | CQ20: =CP20/$CP$22 -> 0.6743295 | CS20: Activo | CT20: =COUNTIF('BD Asesor'!$A:$L,CS20) -> 262 | CU20: =CT20/$CT$22 -> 1
CH21: 2028 | CI21: =COUNTIFS('BD Asesor'!$R:$R,CH21) -> 0 | CO21: Gastos Médicos | CP21: =COUNTIF('BD Asesor'!$A$7:$L$1008,CO21) -> 85 | CQ21: =CP21/$CP$22 -> 0.3256705 | CS21: Inactivo | CT21: =COUNTIF('BD Asesor'!$A:$L,CS21) -> 0 | CU21: =CT21/$CT$22 -> 0
CH22: 2029 | CI22: =COUNTIFS('BD Asesor'!$R:$R,CH22) -> 0 | CO22: Total | CP22: =SUM(CP20:CP21) -> 261 | CS22: Total | CT22: =SUM(CT20:CT21) -> 262
CH23: 2030 | CI23: =COUNTIFS('BD Asesor'!$R:$R,CH23) -> 0
CH24: Total | CI24: =SUM(CI12:CI23) -> 223

Sheet Análisis de Info Anual
C3: Análisis de Información Histórico
D5: Año
D6: 2023
CF8: Tabla de Número de pólizas por mes
B9: Promedio de Prima | G9: Tabla de Número de pólizas | P9: Hombre vs Mujer | U9: Promedio de Prima anual Hombre vs Mujer | AC9: Tabla de Número de pólizas por año Hombre vs Mujer | AK9: Bloque de edades | AP9: Promedio de Prima anual por edades | BA9: Tabla de Número de pólizas por año por edades | BL9: Promedio de Prima anual Vida | BQ9: Tabla de Número de pólizas de Vida por año | BV9: Promedio de Prima anual Gastos Médicos | CA9: Tabla de Número de pólizas de Gastos Médicos por año | CM9: Tabla de Modo de cobro | CQ9: Tabla de Tipo de moneda | CU9: Tabla de Forma de pago
CF11: Mes | CG11: Número de polizas | CM11: Modo de Cobro | CN11: Cantidad de pagos | CO11: Porcentaje | CQ11: Tipo de moneda | CR11: Cantidad de pagos | CS11: Porcentaje | CU11: Forma de pago | CV11: Cantidad de pagos | CW11: Porcentaje
CF12: Enero | CG12: =COUNTIFS('BD Asesor'!$Q:$Q,CF12,'BD Asesor'!$R:$R,$D$6) -> 2 | CM12: TC | CN12: =COUNTIFS('BD Asesor'!$K:$K,CM12,'BD Asesor'!$R:$R,$D$6) -> 27 | CO12: =IFERROR(CN12/$CN$14,"0.00%") -> 0.81818182 | CQ12: MXN | CR12: =COUNTIFS('BD Asesor'!$G:$G,CM12,'BD Asesor'!$R:$R,$D$6) -> 0 | CS12: =IFERROR(CN12/$CR$15,"0.00%") -> 0.00% | CU12: Mensual | CV12: =COUNTIFS('BD Asesor'!$H:$H,CU12,'BD Asesor'!$R:$R,$D$6) -> 3 | CW12: =IFERROR(CN12/$CV$16,"0.00%") -> 0.61363636
CF13: Febrero | CG13: =COUNTIFS('BD Asesor'!$Q:$Q,CF13,'BD Asesor'!$R:$R,$D$6) -> 5 | CM13: TD | CN13: =COUNTIFS('BD Asesor'!$K:$K,CM13,'BD Asesor'!$R:$R,$D$6) -> 6 | CO13: =IFERROR(CN13/$CN$14,"0.00%") -> 0.18181818 | CQ13: USD | CR13: =COUNTIFS('BD Asesor'!$G:$G,CM13,'BD Asesor'!$R:$R,$D$6) -> 0 | CS13: =IFERROR(CN13/$CR$15,"0.00%") -> 0.00% | CU13: Trimestral | CV13: =COUNTIFS('BD Asesor'!$H:$H,CU13,'BD Asesor'!$R:$R,$D$6) -> 3 | CW13: =CV13/$CV$16 -> 0.068181818
CF14: Marzo | CG14: =COUNTIFS('BD Asesor'!$Q:$Q,CF14,'BD Asesor'!$R:$R,$D$6) -> 2 | CM14: Total | CN14: =SUM(CN12:CN13) -> 33 | CQ14: UDIS | CR14: =COUNTIFS('BD Asesor'!$G:$G,CM14,'BD Asesor'!$R:$R,$D$6) -> 0 | CS14: =IFERROR(CN14/$CR$15,"0.00%") -> 0.00% | CU14: Semestral | CV14: =COUNTIFS('BD Asesor'!$H:$H,CU14,'BD Asesor'!$R:$R,$D$6) -> 5 | CW14: =CV14/$CV$16 -> 0.11363636
CF15: Abril | CG15: =COUNTIFS('BD Asesor'!$Q:$Q,CF15,'BD Asesor'!$R:$R,$D$6) -> 5 | CQ15: Total | CR15: =SUM(CR12:CR14) -> 0 | CU15: Anual | CV15: =COUNTIFS('BD Asesor'!$H:$H,CU15,'BD Asesor'!$R:$R,$D$6) -> 33 | CW15: =CV15/$CV$16 -> 0.75
CF16: Mayo | CG16: =COUNTIFS('BD Asesor'!$Q:$Q,CF16,'BD Asesor'!$R:$R,$D$6) -> 3 | CU16: Total | CV16: =SUM(CV12:CV15) -> 44
CF17: Junio | CG17: =COUNTIFS('BD Asesor'!$Q:$Q,CF17,'BD Asesor'!$R:$R,$D$6) -> 2
CF18: Julio | CG18: =COUNTIFS('BD Asesor'!$Q:$Q,CF18,'BD Asesor'!$R:$R,$D$6) -> 4 | CM18: Tabla de Tipo de plan | CQ18: Tabla de Estado de Pólizas
CF19: Agosto | CG19: =COUNTIFS('BD Asesor'!$Q:$Q,CF19,'BD Asesor'!$R:$R,$D$6) -> 6 | CM19: Tipo de Plan | CN19: Cantidad de Tipo de plan | CO19: Porcentaje | CQ19: Estado | CR19: Cantidad de pagos | CS19: Porcentaje
CF20: Septiembre | CG20: =COUNTIFS('BD Asesor'!$Q:$Q,CF20,'BD Asesor'!$R:$R,$D$6) -> 3 | CM20: Vida | CN20: =COUNTIFS('BD Asesor'!$L:$L,CM20,'BD Asesor'!$R:$R,$D$6) -> 20 | CO20: =CN20/$CN$22 -> 0.46511628 | CQ20: Activo | CR20: =COUNTIFS('BD Asesor'!$C:$C,CQ20,'BD Asesor'!$R:$R,$D$6) -> 44 | CS20: =IFERROR(CN12/$CR$22,"0.00%") -> 0.61363636
CF21: Octubre | CG21: =COUNTIFS('BD Asesor'!$Q:$Q,CF21,'BD Asesor'!$R:$R,$D$6) -> 2 | CM21: Gastos Médicos | CN21: =COUNTIFS('BD Asesor'!$L:$L,CM21,'BD Asesor'!$R:$R,$D$6) -> 23 | CO21: =CN21/$CN$22 -> 0.53488372 | CQ21: Inactivo | CR21: =COUNTIFS('BD Asesor'!$C:$C,CQ21,'BD Asesor'!$R:$R,$D$6) -> 0 | CS21: =IFERROR(CN13/$CR$22,"0.00%") -> 0.13636364
CF22: Noviembre | CG22: =COUNTIFS('BD Asesor'!$Q:$Q,CF22,'BD Asesor'!$R:$R,$D$6) -> 7 | CM22: Total | CN22: =SUM(CN20:CN21) -> 43 | CQ22: Total | CR22: =SUM(CR20:CR21) -> 44
CF23: Diciembre | CG23: =COUNTIFS('BD Asesor'!$Q:$Q,CF23,'BD Asesor'!$R:$R,$D$6) -> 3
CF24: Total | CG24: =SUM(CG12:CG23) -> 44

Sheet Listas
A2: Hoy | B2: =TODAY() -> 46161 | C2: 1 | D2: Enero | F2: Vida | G2: Gastos Médicos
A3: =DAY(B2) -> 19 | B3: =MONTH(B2) -> 5 | C3: 2 | D3: Febrero
C4: 3 | D4: Marzo | F4: Orvi | G4: Pleno | I4: =IFERROR(__xludf.DUMMYFUNCTION("FILTER('BD Asesor'!A8:A1998,'BD Asesor'!C8:C1998=""Activo"")"),"ABRAHAM GALICIA MANCERA") -> ABRAHAM GALICIA MANCERA
C5: 4 | D5: Abril | F5: Dotal | G5: Integro | I5: =IFERROR(__xludf.DUMMYFUNCTION("""COMPUTED_VALUE"""),"ABRAHAM GALICIA MANCERA") -> ABRAHAM GALICIA MANCERA
C6: 5 | D6: Mayo | F6: Vida mujer | G6: Practico | I6: =IFERROR(__xludf.DUMMYFUNCTION("""COMPUTED_VALUE"""),"ADRIAN ALEJANDRO RAMIREZ MORALES") -> ADRIAN ALEJANDRO RAMIREZ MORALES
B7: 2018 | C7: 6 | D7: Junio | F7: Imagina ser | G7: Flex A | I7: =IFERROR(__xludf.DUMMYFUNCTION("""COMPUTED_VALUE"""),"ADRIAN ALEJANDRO RAMIREZ MORALES") -> ADRIAN ALEJANDRO RAMIREZ MORALES
B8: 2019 | C8: 7 | D8: Julio | F8: Nuevo planitud | G8: Flex B | I8: =IFERROR(__xludf.DUMMYFUNCTION("""COMPUTED_VALUE"""),"AIDA GRACIELA FLORES BARBA") -> AIDA GRACIELA FLORES BARBA
B9: 2020 | C9: 8 | D9: Agosto | F9: Segubeca | I9: =IFERROR(__xludf.DUMMYFUNCTION("""COMPUTED_VALUE"""),"ALEJANDRA DEL CARMEN UREÑA CASILLAS") -> ALEJANDRA DEL CARMEN UREÑA CASILLAS
B10: 2021 | C10: 9 | D10: Septiembre | F10: Mio | I10: =IFERROR(__xludf.DUMMYFUNCTION("""COMPUTED_VALUE"""),"ALEJANDRA DEL CARMEN UREÑA CASILLAS") -> ALEJANDRA DEL CARMEN UREÑA CASILLAS
B11: 2022 | C11: 10 | D11: Octubre | I11: =IFERROR(__xludf.DUMMYFUNCTION("""COMPUTED_VALUE"""),"ALEJANDRA DEL CARMEN UREÑA CASILLAS") -> ALEJANDRA DEL CARMEN UREÑA CASILLAS
B12: 2023 | C12: 11 | D12: Noviembre | I12: =IFERROR(__xludf.DUMMYFUNCTION("""COMPUTED_VALUE"""),"ALEJANDRO ARTURO LOMELI OROZCO") -> ALEJANDRO ARTURO LOMELI OROZCO
B13: 2024 | C13: 12 | D13: Diciembre | I13: =IFERROR(__xludf.DUMMYFUNCTION("""COMPUTED_VALUE"""),"ALEJANDRO MORENO TRUJILLO") -> ALEJANDRO MORENO TRUJILLO
B14: 2025 | I14: =IFERROR(__xludf.DUMMYFUNCTION("""COMPUTED_VALUE"""),"ALEJANDRO MORENO TRUJILLO") -> ALEJANDRO MORENO TRUJILLO
B15: 2026 | I15: =IFERROR(__xludf.DUMMYFUNCTION("""COMPUTED_VALUE"""),"ALEJANDRO SOTO ELIZALDE") -> ALEJANDRO SOTO ELIZALDE
I16: =IFERROR(__xludf.DUMMYFUNCTION("""COMPUTED_VALUE"""),"ALEJANDRO VAZQUEZ RODRIGUEZ") -> ALEJANDRO VAZQUEZ RODRIGUEZ
I17: =IFERROR(__xludf.DUMMYFUNCTION("""COMPUTED_VALUE"""),"ALEXA GISELLE INFANTE JAIME") -> ALEXA GISELLE INFANTE JAIME
I18: =IFERROR(__xludf.DUMMYFUNCTION("""COMPUTED_VALUE"""),"ANA KAREN MUÑIZ CHAVEZ") -> ANA KAREN MUÑIZ CHAVEZ
I19: =IFERROR(__xludf.DUMMYFUNCTION("""COMPUTED_VALUE"""),"ANA PAULA GONZALEZ LUNA NIÑO") -> ANA PAULA GONZALEZ LUNA NIÑO
I20: =IFERROR(__xludf.DUMMYFUNCTION("""COMPUTED_VALUE"""),"ANDREA HERNANDEZ MERCADO") -> ANDREA HERNANDEZ MERCADO
I21: =IFERROR(__xludf.DUMMYFUNCTION("""COMPUTED_VALUE"""),"ANGELICA ALEJANDRA SANCHEZ DURAN") -> ANGELICA ALEJANDRA SANCHEZ DURAN
I22: =IFERROR(__xludf.DUMMYFUNCTION("""COMPUTED_VALUE"""),"ARNOLD SANCHEZ SANCHEZ") -> ARNOLD SANCHEZ SANCHEZ
I23: =IFERROR(__xludf.DUMMYFUNCTION("""COMPUTED_VALUE"""),"BERNARDO GARCIA GOMEZ") -> BERNARDO GARCIA GOMEZ
I24: =IFERROR(__xludf.DUMMYFUNCTION("""COMPUTED_VALUE"""),"BERNARDO GARCIA GOMEZ") -> BERNARDO GARCIA GOMEZ
I25: =IFERROR(__xludf.DUMMYFUNCTION("""COMPUTED_VALUE"""),"BETH SUA MONTEJANO CARMONA") -> BETH SUA MONTEJANO CARMONA
I26: =IFERROR(__xludf.DUMMYFUNCTION("""COMPUTED_VALUE"""),"BLANCA CAROLINA MAGAÑA CASTELLON") -> BLANCA CAROLINA MAGAÑA CASTELLON
I27: =IFERROR(__xludf.DUMMYFUNCTION("""COMPUTED_VALUE"""),"CARLA ANDREA MARTINEZ LAGOS") -> CARLA ANDREA MARTINEZ LAGOS
I28: =IFERROR(__xludf.DUMMYFUNCTION("""COMPUTED_VALUE"""),"CARLOS ALBERTO MORALES NOGUEDA") -> CARLOS ALBERTO MORALES NOGUEDA
I29: =IFERROR(__xludf.DUMMYFUNCTION("""COMPUTED_VALUE"""),"CARLOS CASTRO PALAZUELOS") -> CARLOS CASTRO PALAZUELOS
I30: =IFERROR(__xludf.DUMMYFUNCTION("""COMPUTED_VALUE"""),"CARLOS DAVID AVILA URRUCHUA") -> CARLOS DAVID AVILA URRUCHUA
I31: =IFERROR(__xludf.DUMMYFUNCTION("""COMPUTED_VALUE"""),"CARLOS HUMBERTO VILLANUEVA CARMONA") -> CARLOS HUMBERTO VILLANUEVA CARMONA
I32: =IFERROR(__xludf.DUMMYFUNCTION("""COMPUTED_VALUE"""),"CARLOS VERDUZO FAVELA") -> CARLOS VERDUZO FAVELA
I33: =IFERROR(__xludf.DUMMYFUNCTION("""COMPUTED_VALUE"""),"CARLOS XAVIER BARBA LOPEZ") -> CARLOS XAVIER BARBA LOPEZ
I34: =IFERROR(__xludf.DUMMYFUNCTION("""COMPUTED_VALUE"""),"CECILIA ARCEO CERVANTES") -> CECILIA ARCEO CERVANTES
I35: =IFERROR(__xludf.DUMMYFUNCTION("""COMPUTED_VALUE"""),"CESAR ISRRAEL HERNANDEZ SANCHEZ") -> CESAR ISRRAEL HERNANDEZ SANCHEZ
I36: =IFERROR(__xludf.DUMMYFUNCTION("""COMPUTED_VALUE"""),"CESAR ISRRAEL HERNANDEZ SANCHEZ") -> CESAR ISRRAEL HERNANDEZ SANCHEZ
I37: =IFERROR(__xludf.DUMMYFUNCTION("""COMPUTED_VALUE"""),"CINTHIA NOEMI JASSO TORRES") -> CINTHIA NOEMI JASSO TORRES
I38: =IFERROR(__xludf.DUMMYFUNCTION("""COMPUTED_VALUE"""),"CLAUDIO ALBERTO MARTIN LOPEZ") -> CLAUDIO ALBERTO MARTIN LOPEZ
I39: =IFERROR(__xludf.DUMMYFUNCTION("""COMPUTED_VALUE"""),"CRISTINA GUADALUPE ALVAREZ HERNANDEZ") -> CRISTINA GUADALUPE ALVAREZ HERNANDEZ
I40: =IFERROR(__xludf.DUMMYFUNCTION("""COMPUTED_VALUE"""),"CRISTINA LETICIA RODRIGUEZ DE LA TORRE") -> CRISTINA LETICIA RODRIGUEZ DE LA TORRE
I41: =IFERROR(__xludf.DUMMYFUNCTION("""COMPUTED_VALUE"""),"CYNTHIA ELIZABETH MORALES ORTEGA") -> CYNTHIA ELIZABETH MORALES ORTEGA
I42: =IFERROR(__xludf.DUMMYFUNCTION("""COMPUTED_VALUE"""),"CYNTHIA ELIZABETH MORALES ORTEGA") -> CYNTHIA ELIZABETH MORALES ORTEGA
I43: =IFERROR(__xludf.DUMMYFUNCTION("""COMPUTED_VALUE"""),"CYNTHIA ELIZABETH MORALES ORTEGA") -> CYNTHIA ELIZABETH MORALES ORTEGA
I44: =IFERROR(__xludf.DUMMYFUNCTION("""COMPUTED_VALUE"""),"DANIELA CABRAL ROMO") -> DANIELA CABRAL ROMO
I45: =IFERROR(__xludf.DUMMYFUNCTION("""COMPUTED_VALUE"""),"DANIELA GUADALUPE PEREGRINA GONZALEZ") -> DANIELA GUADALUPE PEREGRINA GONZALEZ
I46: =IFERROR(__xludf.DUMMYFUNCTION("""COMPUTED_VALUE"""),"DANIELA GUADALUPE PEREGRINA GONZALEZ") -> DANIELA GUADALUPE PEREGRINA GONZALEZ
I47: =IFERROR(__xludf.DUMMYFUNCTION("""COMPUTED_VALUE"""),"DANIELA NIETO MORAN") -> DANIELA NIETO MORAN
I48: =IFERROR(__xludf.DUMMYFUNCTION("""COMPUTED_VALUE"""),"DARINKA UREÑA CASILLAS") -> DARINKA UREÑA CASILLAS
I49: =IFERROR(__xludf.DUMMYFUNCTION("""COMPUTED_VALUE"""),"DARINKA UREÑA CASILLAS") -> DARINKA UREÑA CASILLAS
I50: =IFERROR(__xludf.DUMMYFUNCTION("""COMPUTED_VALUE"""),"DAVID MORENO NERI") -> DAVID MORENO NERI
I51: =IFERROR(__xludf.DUMMYFUNCTION("""COMPUTED_VALUE"""),"DAVID MORENO NERI") -> DAVID MORENO NERI
I52: =IFERROR(__xludf.DUMMYFUNCTION("""COMPUTED_VALUE"""),"DENISSE CARDENAS GONZALEZ") -> DENISSE CARDENAS GONZALEZ
I53: =IFERROR(__xludf.DUMMYFUNCTION("""COMPUTED_VALUE"""),"DIEGO IVAN AGUAYO RAMIREZ") -> DIEGO IVAN AGUAYO RAMIREZ
I54: =IFERROR(__xludf.DUMMYFUNCTION("""COMPUTED_VALUE"""),"DIEGO LEONARDO UREÑA GUARNEROS") -> DIEGO LEONARDO UREÑA GUARNEROS
I55: =IFERROR(__xludf.DUMMYFUNCTION("""COMPUTED_VALUE"""),"DIGNA MARIA BAÑUELOS ZAMORA") -> DIGNA MARIA BAÑUELOS ZAMORA
I56: =IFERROR(__xludf.DUMMYFUNCTION("""COMPUTED_VALUE"""),"EDER EMMANUEL ALCALA GUTIERREZ") -> EDER EMMANUEL ALCALA GUTIERREZ
I57: =IFERROR(__xludf.DUMMYFUNCTION("""COMPUTED_VALUE"""),"EDGAR SANCHEZ GONZALEZ") -> EDGAR SANCHEZ GONZALEZ
I58: =IFERROR(__xludf.DUMMYFUNCTION("""COMPUTED_VALUE"""),"EDUARDO ERNESTO VALLES JARILLO") -> EDUARDO ERNESTO VALLES JARILLO
I59: =IFERROR(__xludf.DUMMYFUNCTION("""COMPUTED_VALUE"""),"EDUARDO RAMIRO TORRES ALVAREZ") -> EDUARDO RAMIRO TORRES ALVAREZ
I60: =IFERROR(__xludf.DUMMYFUNCTION("""COMPUTED_VALUE"""),"EMMANUEL CONTRERAS RIOS") -> EMMANUEL CONTRERAS RIOS
I61: =IFERROR(__xludf.DUMMYFUNCTION("""COMPUTED_VALUE"""),"EMMANUEL ORTEGA GUTIERREZ") -> EMMANUEL ORTEGA GUTIERREZ
I62: =IFERROR(__xludf.DUMMYFUNCTION("""COMPUTED_VALUE"""),"ESTEFANI ALEYOIS CONTRERAS RIOS") -> ESTEFANI ALEYOIS CONTRERAS RIOS
I63: =IFERROR(__xludf.DUMMYFUNCTION("""COMPUTED_VALUE"""),"ESTEFANI ALEYOIS CONTRERAS RIOS") -> ESTEFANI ALEYOIS CONTRERAS RIOS
I64: =IFERROR(__xludf.DUMMYFUNCTION("""COMPUTED_VALUE"""),"FELICITAS CASILLAS GALINDO") -> FELICITAS CASILLAS GALINDO
I65: =IFERROR(__xludf.DUMMYFUNCTION("""COMPUTED_VALUE"""),"FLORENCIA LILIANA CORONA GARNICA") -> FLORENCIA LILIANA CORONA GARNICA
I66: =IFERROR(__xludf.DUMMYFUNCTION("""COMPUTED_VALUE"""),"FRANCISCO JAVIER VALENCIA PRADO") -> FRANCISCO JAVIER VALENCIA PRADO
I67: =IFERROR(__xludf.DUMMYFUNCTION("""COMPUTED_VALUE"""),"FRANCISCO JAVIER VALENCIA PRADO") -> FRANCISCO JAVIER VALENCIA PRADO
I68: =IFERROR(__xludf.DUMMYFUNCTION("""COMPUTED_VALUE"""),"FRANCISCO JAVIER VALENCIA PRADO") -> FRANCISCO JAVIER VALENCIA PRADO
I69: =IFERROR(__xludf.DUMMYFUNCTION("""COMPUTED_VALUE"""),"FRANCISCO JOSE MARTIN LOPEZ") -> FRANCISCO JOSE MARTIN LOPEZ
I70: =IFERROR(__xludf.DUMMYFUNCTION("""COMPUTED_VALUE"""),"GLENDA GISELA CASIANO VEGA") -> GLENDA GISELA CASIANO VEGA
I71: =IFERROR(__xludf.DUMMYFUNCTION("""COMPUTED_VALUE"""),"GUSTAVO GUTIERREZ PLASCENCIA") -> GUSTAVO GUTIERREZ PLASCENCIA
I72: =IFERROR(__xludf.DUMMYFUNCTION("""COMPUTED_VALUE"""),"HEBER RAMIREZ LUNA") -> HEBER RAMIREZ LUNA
I73: =IFERROR(__xludf.DUMMYFUNCTION("""COMPUTED_VALUE"""),"IZCHEL IRAIS GONZALEZ DIAZ") -> IZCHEL IRAIS GONZALEZ DIAZ
I74: =IFERROR(__xludf.DUMMYFUNCTION("""COMPUTED_VALUE"""),"JAVIER ALEJANDRO OCHOA FLORES") -> JAVIER ALEJANDRO OCHOA FLORES
I75: =IFERROR(__xludf.DUMMYFUNCTION("""COMPUTED_VALUE"""),"JAVIER RAMOS BARAJAS") -> JAVIER RAMOS BARAJAS
I76: =IFERROR(__xludf.DUMMYFUNCTION("""COMPUTED_VALUE"""),"JAZMIN ALICIA ROMERO JOHNSON") -> JAZMIN ALICIA ROMERO JOHNSON
I77: =IFERROR(__xludf.DUMMYFUNCTION("""COMPUTED_VALUE"""),"JAZMIN ALICIA ROMERO JOHNSON") -> JAZMIN ALICIA ROMERO JOHNSON
I78: =IFERROR(__xludf.DUMMYFUNCTION("""COMPUTED_VALUE"""),"JAZMIN JUDITH HERNANDEZ AGUIRRE") -> JAZMIN JUDITH HERNANDEZ AGUIRRE
I79: =IFERROR(__xludf.DUMMYFUNCTION("""COMPUTED_VALUE"""),"JENIFER RIVERA LIRA") -> JENIFER RIVERA LIRA
I80: =IFERROR(__xludf.DUMMYFUNCTION("""COMPUTED_VALUE"""),"JENNIFER GODINEZ CASILLAS") -> JENNIFER GODINEZ CASILLAS
I81: =IFERROR(__xludf.DUMMYFUNCTION("""COMPUTED_VALUE"""),"JESUS ADRIAN AVILA CABRAL") -> JESUS ADRIAN AVILA CABRAL
I82: =IFERROR(__xludf.DUMMYFUNCTION("""COMPUTED_VALUE"""),"JORGE FRANCISCO AREVALO CONTRERAS") -> JORGE FRANCISCO AREVALO CONTRERAS
I83: =IFERROR(__xludf.DUMMYFUNCTION("""COMPUTED_VALUE"""),"JORGE FRANCISCO AREVALO CONTRERAS") -> JORGE FRANCISCO AREVALO CONTRERAS
I84: =IFERROR(__xludf.DUMMYFUNCTION("""COMPUTED_VALUE"""),"JOSE DANIEL FLORES ARELLANO") -> JOSE DANIEL FLORES ARELLANO
I85: =IFERROR(__xludf.DUMMYFUNCTION("""COMPUTED_VALUE"""),"JOSE FRANCISCO SEDA CEJA") -> JOSE FRANCISCO SEDA CEJA
I86: =IFERROR(__xludf.DUMMYFUNCTION("""COMPUTED_VALUE"""),"JOSEFINA GALVEZ") -> JOSEFINA GALVEZ
I87: =IFERROR(__xludf.DUMMYFUNCTION("""COMPUTED_VALUE"""),"JUAN ANTONIO VELAZQUEZ ALVAREZ") -> JUAN ANTONIO VELAZQUEZ ALVAREZ
I88: =IFERROR(__xludf.DUMMYFUNCTION("""COMPUTED_VALUE"""),"JUAN CARLOS CONTRERAS VAZQUEZ") -> JUAN CARLOS CONTRERAS VAZQUEZ
I89: =IFERROR(__xludf.DUMMYFUNCTION("""COMPUTED_VALUE"""),"KAREN DENISSE SEDA MUÑOZ") -> KAREN DENISSE SEDA MUÑOZ
I90: =IFERROR(__xludf.DUMMYFUNCTION("""COMPUTED_VALUE"""),"KAREN ENRIQUEZ LEDEZMA") -> KAREN ENRIQUEZ LEDEZMA
I91: =IFERROR(__xludf.DUMMYFUNCTION("""COMPUTED_VALUE"""),"KEVIN IVAN MARCHENA DUEÑAS") -> KEVIN IVAN MARCHENA DUEÑAS
I92: =IFERROR(__xludf.DUMMYFUNCTION("""COMPUTED_VALUE"""),"KIMBERLY MONTSERRAT SEDA MUÑOZ") -> KIMBERLY MONTSERRAT SEDA MUÑOZ
I93: =IFERROR(__xludf.DUMMYFUNCTION("""COMPUTED_VALUE"""),"LUCIA ORTEGA RAMIREZ") -> LUCIA ORTEGA RAMIREZ
I94: =IFERROR(__xludf.DUMMYFUNCTION("""COMPUTED_VALUE"""),"LUZ JIMENA APARICIO GARCIA") -> LUZ JIMENA APARICIO GARCIA
I95: =IFERROR(__xludf.DUMMYFUNCTION("""COMPUTED_VALUE"""),"MARA GABRIELA DUEÑAS SALGADO") -> MARA GABRIELA DUEÑAS SALGADO
I96: =IFERROR(__xludf.DUMMYFUNCTION("""COMPUTED_VALUE"""),"MARCO ANTONIO RAMOS REYNOSO") -> MARCO ANTONIO RAMOS REYNOSO
I97: =IFERROR(__xludf.DUMMYFUNCTION("""COMPUTED_VALUE"""),"MARIA AURORA RIOS GALVAN") -> MARIA AURORA RIOS GALVAN
I98: =IFERROR(__xludf.DUMMYFUNCTION("""COMPUTED_VALUE"""),"MARIA FLORENTINA CONTRERAS SANTILLAN") -> MARIA FLORENTINA CONTRERAS SANTILLAN
I99: =IFERROR(__xludf.DUMMYFUNCTION("""COMPUTED_VALUE"""),"MARIA GUADALUPE CRISTINA CASTELLON DUEÑAS") -> MARIA GUADALUPE CRISTINA CASTELLON DUEÑAS
I100: =IFERROR(__xludf.DUMMYFUNCTION("""COMPUTED_VALUE"""),"MARIO ALEJANDRO VALDIVIESO BERNAL") -> MARIO ALEJANDRO VALDIVIESO BERNAL
I101: =IFERROR(__xludf.DUMMYFUNCTION("""COMPUTED_VALUE"""),"MAYRA ALEJANDRA BALDERAS FONSECA") -> MAYRA ALEJANDRA BALDERAS FONSECA
...

Sheet Mina de Oro
A2: Mes: | B2: Junio
C5: Cliente | D5: Sexo | E5: Estado | F5: Emisión | G5: Número de póliza | H5: Prima anual | I5: Tipo de plan | J5: Nombre del plan
C6: =IFERROR(__xludf.DUMMYFUNCTION("FILTER('BD Asesor'!A8:F1000,'BD Asesor'!Q8:Q1000=B2,'BD Asesor'!C8:C1000=""Activo"")"),"ALEJANDRA DEL CARMEN UREÑA CASILLAS") -> ALEJANDRA DEL CARMEN UREÑA CASILLAS | D6: =IFERROR(__xludf.DUMMYFUNCTION("""COMPUTED_VALUE"""),"M") -> M | E6: =IFERROR(__xludf.DUMMYFUNCTION("""COMPUTED_VALUE"""),"Activo") -> Activo | F6: =IFERROR(__xludf.DUMMYFUNCTION("""COMPUTED_VALUE"""),44008.0) -> 44008 | G6: =IFERROR(__xludf.DUMMYFUNCTION("""COMPUTED_VALUE"""),"GM0000478411") -> GM0000478411 | H6: =IFERROR(__xludf.DUMMYFUNCTION("""COMPUTED_VALUE"""),10660.33) -> 10660.33 | I6: =IFERROR(__xludf.DUMMYFUNCTION("FILTER('BD Asesor'!L8:M1000,'BD Asesor'!Q8:Q1000=B2,'BD Asesor'!C8:C1000=""Activo"")"),"Gastos Médicos ") -> Gastos Médicos | J6: =IFERROR(__xludf.DUMMYFUNCTION("""COMPUTED_VALUE"""),"Integro") -> Integro
C7: =IFERROR(__xludf.DUMMYFUNCTION("""COMPUTED_VALUE"""),"CESAR ISRRAEL HERNANDEZ SANCHEZ") -> CESAR ISRRAEL HERNANDEZ SANCHEZ | D7: =IFERROR(__xludf.DUMMYFUNCTION("""COMPUTED_VALUE"""),"H") -> H | E7: =IFERROR(__xludf.DUMMYFUNCTION("""COMPUTED_VALUE"""),"Activo") -> Activo | F7: =IFERROR(__xludf.DUMMYFUNCTION("""COMPUTED_VALUE"""),44728.0) -> 44728 | G7: =IFERROR(__xludf.DUMMYFUNCTION("""COMPUTED_VALUE"""),"VI0002672529") -> VI0002672529 | H7: =IFERROR(__xludf.DUMMYFUNCTION("""COMPUTED_VALUE"""),94684.68359999999) -> 94684.684 | I7: =IFERROR(__xludf.DUMMYFUNCTION("""COMPUTED_VALUE"""),"Vida") -> Vida | J7: =IFERROR(__xludf.DUMMYFUNCTION("""COMPUTED_VALUE"""),"Orvi") -> Orvi
C8: =IFERROR(__xludf.DUMMYFUNCTION("""COMPUTED_VALUE"""),"FRANCISCO JAVIER VALENCIA PRADO") -> FRANCISCO JAVIER VALENCIA PRADO | D8: =IFERROR(__xludf.DUMMYFUNCTION("""COMPUTED_VALUE"""),"H") -> H | E8: =IFERROR(__xludf.DUMMYFUNCTION("""COMPUTED_VALUE"""),"Activo") -> Activo | F8: =IFERROR(__xludf.DUMMYFUNCTION("""COMPUTED_VALUE"""),44012.0) -> 44012 | G8: =IFERROR(__xludf.DUMMYFUNCTION("""COMPUTED_VALUE"""),"GM0000479419") -> GM0000479419 | H8: =IFERROR(__xludf.DUMMYFUNCTION("""COMPUTED_VALUE"""),16188.72) -> 16188.72 | I8: =IFERROR(__xludf.DUMMYFUNCTION("""COMPUTED_VALUE"""),"Gastos Médicos ") -> Gastos Médicos | J8: =IFERROR(__xludf.DUMMYFUNCTION("""COMPUTED_VALUE"""),"Integro") -> Integro
C9: =IFERROR(__xludf.DUMMYFUNCTION("""COMPUTED_VALUE"""),"GUSTAVO GUTIERREZ PLASCENCIA") -> GUSTAVO GUTIERREZ PLASCENCIA | D9: =IFERROR(__xludf.DUMMYFUNCTION("""COMPUTED_VALUE"""),"H") -> H | E9: =IFERROR(__xludf.DUMMYFUNCTION("""COMPUTED_VALUE"""),"Activo") -> Activo | F9: =IFERROR(__xludf.DUMMYFUNCTION("""COMPUTED_VALUE"""),44362.0) -> 44362 | G9: =IFERROR(__xludf.DUMMYFUNCTION("""COMPUTED_VALUE"""),"VI0002607534") -> VI0002607534 | H9: =IFERROR(__xludf.DUMMYFUNCTION("""COMPUTED_VALUE"""),23822.451220000003) -> 23822.451 | I9: =IFERROR(__xludf.DUMMYFUNCTION("""COMPUTED_VALUE"""),"Vida") -> Vida | J9: =IFERROR(__xludf.DUMMYFUNCTION("""COMPUTED_VALUE"""),"Orvi") -> Orvi
C10: =IFERROR(__xludf.DUMMYFUNCTION("""COMPUTED_VALUE"""),"IZCHEL IRAIS GONZALEZ DIAZ") -> IZCHEL IRAIS GONZALEZ DIAZ | D10: =IFERROR(__xludf.DUMMYFUNCTION("""COMPUTED_VALUE"""),"M") -> M | E10: =IFERROR(__xludf.DUMMYFUNCTION("""COMPUTED_VALUE"""),"Activo") -> Activo | F10: =IFERROR(__xludf.DUMMYFUNCTION("""COMPUTED_VALUE"""),44366.0) -> 44366 | G10: =IFERROR(__xludf.DUMMYFUNCTION("""COMPUTED_VALUE"""),"VI0002608269") -> VI0002608269 | H10: =IFERROR(__xludf.DUMMYFUNCTION("""COMPUTED_VALUE"""),17576.90448) -> 17576.904 | I10: =IFERROR(__xludf.DUMMYFUNCTION("""COMPUTED_VALUE"""),"Vida") -> Vida | J10: =IFERROR(__xludf.DUMMYFUNCTION("""COMPUTED_VALUE"""),"Orvi") -> Orvi
C11: =IFERROR(__xludf.DUMMYFUNCTION("""COMPUTED_VALUE"""),"JAZMIN JUDITH HERNANDEZ AGUIRRE") -> JAZMIN JUDITH HERNANDEZ AGUIRRE | D11: =IFERROR(__xludf.DUMMYFUNCTION("""COMPUTED_VALUE"""),"M") -> M | E11: =IFERROR(__xludf.DUMMYFUNCTION("""COMPUTED_VALUE"""),"Activo") -> Activo | F11: =IFERROR(__xludf.DUMMYFUNCTION("""COMPUTED_VALUE"""),44740.0) -> 44740 | G11: =IFERROR(__xludf.DUMMYFUNCTION("""COMPUTED_VALUE"""),"VI0002675317") -> VI0002675317 | H11: =IFERROR(__xludf.DUMMYFUNCTION("""COMPUTED_VALUE"""),16748.0079) -> 16748.008 | I11: =IFERROR(__xludf.DUMMYFUNCTION("""COMPUTED_VALUE"""),"Vida") -> Vida | J11: =IFERROR(__xludf.DUMMYFUNCTION("""COMPUTED_VALUE"""),"Segubeca") -> Segubeca
C12: =IFERROR(__xludf.DUMMYFUNCTION("""COMPUTED_VALUE"""),"OSCAR ARTURO CORREA SOTO") -> OSCAR ARTURO CORREA SOTO | D12: =IFERROR(__xludf.DUMMYFUNCTION("""COMPUTED_VALUE"""),"H") -> H | E12: =IFERROR(__xludf.DUMMYFUNCTION("""COMPUTED_VALUE"""),"Activo") -> Activo | F12: =IFERROR(__xludf.DUMMYFUNCTION("""COMPUTED_VALUE"""),44372.0) -> 44372 | G12: =IFERROR(__xludf.DUMMYFUNCTION("""COMPUTED_VALUE"""),"VI0002610198") -> VI0002610198 | H12: =IFERROR(__xludf.DUMMYFUNCTION("""COMPUTED_VALUE"""),38433.71218) -> 38433.712 | I12: =IFERROR(__xludf.DUMMYFUNCTION("""COMPUTED_VALUE"""),"Vida") -> Vida | J12: =IFERROR(__xludf.DUMMYFUNCTION("""COMPUTED_VALUE"""),"Orvi") -> Orvi
C13: =IFERROR(__xludf.DUMMYFUNCTION("""COMPUTED_VALUE"""),"PAOLA RAMOS REYNOSO") -> PAOLA RAMOS REYNOSO | D13: =IFERROR(__xludf.DUMMYFUNCTION("""COMPUTED_VALUE"""),"M") -> M | E13: =IFERROR(__xludf.DUMMYFUNCTION("""COMPUTED_VALUE"""),"Activo") -> Activo | F13: =IFERROR(__xludf.DUMMYFUNCTION("""COMPUTED_VALUE"""),44357.0) -> 44357 | G13: =IFERROR(__xludf.DUMMYFUNCTION("""COMPUTED_VALUE"""),"VI0002606703") -> VI0002606703 | H13: =IFERROR(__xludf.DUMMYFUNCTION("""COMPUTED_VALUE"""),31557.93772) -> 31557.938 | I13: =IFERROR(__xludf.DUMMYFUNCTION("""COMPUTED_VALUE"""),"Vida") -> Vida | J13: =IFERROR(__xludf.DUMMYFUNCTION("""COMPUTED_VALUE"""),"Orvi") -> Orvi
C14: =IFERROR(__xludf.DUMMYFUNCTION("""COMPUTED_VALUE"""),"SUSANA RODRIGUEZ REYES") -> SUSANA RODRIGUEZ REYES | D14: =IFERROR(__xludf.DUMMYFUNCTION("""COMPUTED_VALUE"""),"M") -> M | E14: =IFERROR(__xludf.DUMMYFUNCTION("""COMPUTED_VALUE"""),"Activo") -> Activo | F14: =IFERROR(__xludf.DUMMYFUNCTION("""COMPUTED_VALUE"""),44740.0) -> 44740 | G14: =IFERROR(__xludf.DUMMYFUNCTION("""COMPUTED_VALUE"""),"VI0002675267") -> VI0002675267 | H14: =IFERROR(__xludf.DUMMYFUNCTION("""COMPUTED_VALUE"""),20042.694) -> 20042.694 | I14: =IFERROR(__xludf.DUMMYFUNCTION("""COMPUTED_VALUE"""),"Vida") -> Vida | J14: =IFERROR(__xludf.DUMMYFUNCTION("""COMPUTED_VALUE"""),"Segubeca") -> Segubeca
C15: =IFERROR(__xludf.DUMMYFUNCTION("""COMPUTED_VALUE"""),"TZEITEL PAMELA GUARDIAN AVELAR") -> TZEITEL PAMELA GUARDIAN AVELAR | D15: =IFERROR(__xludf.DUMMYFUNCTION("""COMPUTED_VALUE"""),"M") -> M | E15: =IFERROR(__xludf.DUMMYFUNCTION("""COMPUTED_VALUE"""),"Activo") -> Activo | F15: =IFERROR(__xludf.DUMMYFUNCTION("""COMPUTED_VALUE"""),44355.0) -> 44355 | G15: =IFERROR(__xludf.DUMMYFUNCTION("""COMPUTED_VALUE"""),"VI0002606377") -> VI0002606377 | H15: =IFERROR(__xludf.DUMMYFUNCTION("""COMPUTED_VALUE"""),35707.30464) -> 35707.305 | I15: =IFERROR(__xludf.DUMMYFUNCTION("""COMPUTED_VALUE"""),"Vida") -> Vida | J15: =IFERROR(__xludf.DUMMYFUNCTION("""COMPUTED_VALUE"""),"Orvi") -> Orvi
C16: =IFERROR(__xludf.DUMMYFUNCTION("""COMPUTED_VALUE"""),"KARLA GABRIELA GARIBAY MORAN") -> KARLA GABRIELA GARIBAY MORAN | D16: =IFERROR(__xludf.DUMMYFUNCTION("""COMPUTED_VALUE"""),"M") -> M | E16: =IFERROR(__xludf.DUMMYFUNCTION("""COMPUTED_VALUE"""),"Activo") -> Activo | F16: =IFERROR(__xludf.DUMMYFUNCTION("""COMPUTED_VALUE"""),45103.0) -> 45103 | G16: =IFERROR(__xludf.DUMMYFUNCTION("""COMPUTED_VALUE"""),"VI0002747846") -> VI0002747846 | H16: =IFERROR(__xludf.DUMMYFUNCTION("""COMPUTED_VALUE"""),20343.96) -> 20343.96 | I16: =IFERROR(__xludf.DUMMYFUNCTION("""COMPUTED_VALUE"""),"Vida") -> Vida | J16: =IFERROR(__xludf.DUMMYFUNCTION("""COMPUTED_VALUE"""),"Orvi") -> Orvi
C17: =IFERROR(__xludf.DUMMYFUNCTION("""COMPUTED_VALUE"""),"JOSE ANTONIO LINAGE GARZA") -> JOSE ANTONIO LINAGE GARZA | D17: =IFERROR(__xludf.DUMMYFUNCTION("""COMPUTED_VALUE"""),"H") -> H | E17: =IFERROR(__xludf.DUMMYFUNCTION("""COMPUTED_VALUE"""),"Activo") -> Activo | F17: =IFERROR(__xludf.DUMMYFUNCTION("""COMPUTED_VALUE"""),45105.0) -> 45105 | G17: =IFERROR(__xludf.DUMMYFUNCTION("""COMPUTED_VALUE"""),"VI0002748901") -> VI0002748901 | H17: =IFERROR(__xludf.DUMMYFUNCTION("""COMPUTED_VALUE"""),123987.396) -> 123987.4 | I17: =IFERROR(__xludf.DUMMYFUNCTION("""COMPUTED_VALUE"""),"Vida") -> Vida | J17: =IFERROR(__xludf.DUMMYFUNCTION("""COMPUTED_VALUE"""),"Orvi") -> Orvi
C18: =IFERROR(__xludf.DUMMYFUNCTION("""COMPUTED_VALUE"""),"MARIO HUMBERTO VILLANUEVA IBARRA") -> MARIO HUMBERTO VILLANUEVA IBARRA | D18: =IFERROR(__xludf.DUMMYFUNCTION("""COMPUTED_VALUE"""),"H") -> H | E18: =IFERROR(__xludf.DUMMYFUNCTION("""COMPUTED_VALUE"""),"Activo") -> Activo | F18: =IFERROR(__xludf.DUMMYFUNCTION("""COMPUTED_VALUE"""),45457.0) -> 45457 | G18: =IFERROR(__xludf.DUMMYFUNCTION("""COMPUTED_VALUE"""),"VI0002832905") -> VI0002832905 | H18: =IFERROR(__xludf.DUMMYFUNCTION("""COMPUTED_VALUE"""),67082.9112) -> 67082.911 | I18: =IFERROR(__xludf.DUMMYFUNCTION("""COMPUTED_VALUE"""),"Vida") -> Vida | J18: =IFERROR(__xludf.DUMMYFUNCTION("""COMPUTED_VALUE"""),"Orvi") -> Orvi
C19: =IFERROR(__xludf.DUMMYFUNCTION("""COMPUTED_VALUE"""),"JENNIFER DAYANA CHAVEZ GUTIERREZ") -> JENNIFER DAYANA CHAVEZ GUTIERREZ | D19: =IFERROR(__xludf.DUMMYFUNCTION("""COMPUTED_VALUE"""),"M") -> M | E19: =IFERROR(__xludf.DUMMYFUNCTION("""COMPUTED_VALUE"""),"Activo") -> Activo | F19: =IFERROR(__xludf.DUMMYFUNCTION("""COMPUTED_VALUE"""),45467.0) -> 45467 | G19: =IFERROR(__xludf.DUMMYFUNCTION("""COMPUTED_VALUE"""),"VI0002835245") -> VI0002835245 | H19: =IFERROR(__xludf.DUMMYFUNCTION("""COMPUTED_VALUE"""),20683.1515) -> 20683.151 | I19: =IFERROR(__xludf.DUMMYFUNCTION("""COMPUTED_VALUE"""),"Vida") -> Vida | J19: =IFERROR(__xludf.DUMMYFUNCTION("""COMPUTED_VALUE"""),"Segubeca") -> Segubeca
C20: =IFERROR(__xludf.DUMMYFUNCTION("""COMPUTED_VALUE"""),"BLANCA CAROLINA MAGAÑA CASTELLON") -> BLANCA CAROLINA MAGAÑA CASTELLON | D20: =IFERROR(__xludf.DUMMYFUNCTION("""COMPUTED_VALUE"""),"F") -> F | E20: =IFERROR(__xludf.DUMMYFUNCTION("""COMPUTED_VALUE"""),"Activo") -> Activo | F20: =IFERROR(__xludf.DUMMYFUNCTION("""COMPUTED_VALUE"""),43262.0) -> 43262 | G20: =IFERROR(__xludf.DUMMYFUNCTION("""COMPUTED_VALUE"""),"VI0002382839") -> VI0002382839 | H20: =IFERROR(__xludf.DUMMYFUNCTION("""COMPUTED_VALUE"""),73182.46199999998) -> 73182.462 | I20: =IFERROR(__xludf.DUMMYFUNCTION("""COMPUTED_VALUE"""),"Vida") -> Vida | J20: =IFERROR(__xludf.DUMMYFUNCTION("""COMPUTED_VALUE"""),"Segubeca") -> Segubeca
C21: =IFERROR(__xludf.DUMMYFUNCTION("""COMPUTED_VALUE"""),"ANGEL GONZALEZ MARTIN") -> ANGEL GONZALEZ MARTIN | D21: =IFERROR(__xludf.DUMMYFUNCTION("""COMPUTED_VALUE"""),"M") -> M | E21: =IFERROR(__xludf.DUMMYFUNCTION("""COMPUTED_VALUE"""),"Activo") -> Activo | F21: =IFERROR(__xludf.DUMMYFUNCTION("""COMPUTED_VALUE"""),45468.0) -> 45468 | G21: =IFERROR(__xludf.DUMMYFUNCTION("""COMPUTED_VALUE"""),"VI0002835520 ") -> VI0002835520 | I21: =IFERROR(__xludf.DUMMYFUNCTION("""COMPUTED_VALUE"""),"Vida") -> Vida | J21: =IFERROR(__xludf.DUMMYFUNCTION("""COMPUTED_VALUE"""),"Segubeca") -> Segubeca
C22: =IFERROR(__xludf.DUMMYFUNCTION("""COMPUTED_VALUE"""),"ADRIAN ALONSO CASTILLO GARCIA") -> ADRIAN ALONSO CASTILLO GARCIA | D22: =IFERROR(__xludf.DUMMYFUNCTION("""COMPUTED_VALUE"""),"M") -> M | E22: =IFERROR(__xludf.DUMMYFUNCTION("""COMPUTED_VALUE"""),"Activo") -> Activo | F22: =IFERROR(__xludf.DUMMYFUNCTION("""COMPUTED_VALUE"""),45819.0) -> 45819 | G22: =IFERROR(__xludf.DUMMYFUNCTION("""COMPUTED_VALUE"""),"VI0002918199") -> VI0002918199 | H22: =IFERROR(__xludf.DUMMYFUNCTION("""COMPUTED_VALUE"""),156513.4944) -> 156513.49 | I22: =IFERROR(__xludf.DUMMYFUNCTION("""COMPUTED_VALUE"""),"Vida") -> Vida | J22: =IFERROR(__xludf.DUMMYFUNCTION("""COMPUTED_VALUE"""),"Imagina ser") -> Imagina ser
C23: =IFERROR(__xludf.DUMMYFUNCTION("""COMPUTED_VALUE"""),"DIANA MONTSERRAT FLORES VERA ") -> DIANA MONTSERRAT FLORES VERA | D23: =IFERROR(__xludf.DUMMYFUNCTION("""COMPUTED_VALUE"""),"F") -> F | E23: =IFERROR(__xludf.DUMMYFUNCTION("""COMPUTED_VALUE"""),"Activo") -> Activo | F23: =IFERROR(__xludf.DUMMYFUNCTION("""COMPUTED_VALUE"""),45826.0) -> 45826 | G23: =IFERROR(__xludf.DUMMYFUNCTION("""COMPUTED_VALUE"""),"VI0002920158") -> VI0002920158 | H23: =IFERROR(__xludf.DUMMYFUNCTION("""COMPUTED_VALUE"""),28898.9072) -> 28898.907 | I23: =IFERROR(__xludf.DUMMYFUNCTION("""COMPUTED_VALUE"""),"Vida") -> Vida | J23: =IFERROR(__xludf.DUMMYFUNCTION("""COMPUTED_VALUE"""),"Imagina ser") -> Imagina ser

Sheet Cobranza
A2: Mes: | B2: Marzo
C5: Cliente | D5: Sexo | E5: Estado | F5: Emisión | G5: Número de póliza | H5: Prima anual | I5: Tipo de moneda | J5: Forma de pago | K5: Modo de Cobro | L5: Tipo de Plan | N5: Cliente | O5: Sexo | P5: Estado | Q5: Emisión | R5: Número de póliza | S5: Prima anual | T5: Tipo de moneda | U5: Forma de pago | V5: Modo de Cobro | W5: Tipo de Plan
C6: {=IF(OR( AND('BD Asesor'!H8="Mensual", MATCH($B$2, {"Enero", "Febrero", "Marzo", "Abril", "Mayo", "Junio", "Julio", "Agosto", "Septiembre", "Octubre", "Noviembre", "Diciembre"}, 0)>=1), AND('BD Asesor'!H8="Trimestral", MOD(MATCH($B$2, {"Enero", "Febrero", "Marzo", "Abril", "Mayo", "Junio", "Julio", "Agosto", "Septiembre", "Octubre", "Noviembre"}, 0)-MONTH('BD Asesor'!D8), 3)=0), AND('BD Asesor'!H8="Semestral", MOD(MATCH($B$2, {"Enero", "Febrero", "Marzo", "Abril", "Mayo", "Junio", "Julio", "Agosto", "Septiembre", "Octubre", "Noviembre"}, 0)-MONTH('BD Asesor'!D8), 6)=0), AND('BD Asesor'!H8="Anual", MONTH('BD Asesor'!D8)=MATCH($B$2, {"Enero", "Febrero", "Marzo", "Abril", "Mayo", "Junio", "Julio", "Agosto", "Septiembre", "Octubre", "Noviembre"}, 0)) ), 'BD Asesor'!A8, "")} -> ABRAHAM GALICIA MANCERA | D6: {=IF(OR( AND('BD Asesor'!H8="Mensual", MATCH($B$2, {"Enero", "Febrero", "Marzo", "Abril", "Mayo", "Junio", "Julio", "Agosto", "Septiembre", "Octubre", "Noviembre", "Diciembre"}, 0)>=1), AND('BD Asesor'!H8="Trimestral", MOD(MATCH($B$2, {"Enero", "Febrero", "Marzo", "Abril", "Mayo", "Junio", "Julio", "Agosto", "Septiembre", "Octubre", "Noviembre"}, 0)-MONTH('BD Asesor'!D8), 3)=0), AND('BD Asesor'!H8="Semestral", MOD(MATCH($B$2, {"Enero", "Febrero", "Marzo", "Abril", "Mayo", "Junio", "Julio", "Agosto", "Septiembre", "Octubre", "Noviembre"}, 0)-MONTH('BD Asesor'!D8), 6)=0), AND('BD Asesor'!H8="Anual", MONTH('BD Asesor'!D8)=MATCH($B$2, {"Enero", "Febrero", "Marzo", "Abril", "Mayo", "Junio", "Julio", "Agosto", "Septiembre", "Octubre", "Noviembre"}, 0)) ), 'BD Asesor'!B8, "")} -> H | E6: {=IF(OR( AND('BD Asesor'!H8="Mensual", MATCH($B$2, {"Enero", "Febrero", "Marzo", "Abril", "Mayo", "Junio", "Julio", "Agosto", "Septiembre", "Octubre", "Noviembre", "Diciembre"}, 0)>=1), AND('BD Asesor'!H8="Trimestral", MOD(MATCH($B$2, {"Enero", "Febrero", "Marzo", "Abril", "Mayo", "Junio", "Julio", "Agosto", "Septiembre", "Octubre", "Noviembre"}, 0)-MONTH('BD Asesor'!D8), 3)=0), AND('BD Asesor'!H8="Semestral", MOD(MATCH($B$2, {"Enero", "Febrero", "Marzo", "Abril", "Mayo", "Junio", "Julio", "Agosto", "Septiembre", "Octubre", "Noviembre"}, 0)-MONTH('BD Asesor'!D8), 6)=0), AND('BD Asesor'!H8="Anual", MONTH('BD Asesor'!D8)=MATCH($B$2, {"Enero", "Febrero", "Marzo", "Abril", "Mayo", "Junio", "Julio", "Agosto", "Septiembre", "Octubre", "Noviembre"}, 0)) ), 'BD Asesor'!C8, "")} -> Activo | F6: {=IF(OR( AND('BD Asesor'!H8="Mensual", MATCH($B$2, {"Enero", "Febrero", "Marzo", "Abril", "Mayo", "Junio", "Julio", "Agosto", "Septiembre", "Octubre", "Noviembre", "Diciembre"}, 0)>=1), AND('BD Asesor'!H8="Trimestral", MOD(MATCH($B$2, {"Enero", "Febrero", "Marzo", "Abril", "Mayo", "Junio", "Julio", "Agosto", "Septiembre", "Octubre", "Noviembre"}, 0)-MONTH('BD Asesor'!D8), 3)=0), AND('BD Asesor'!H8="Semestral", MOD(MATCH($B$2, {"Enero", "Febrero", "Marzo", "Abril", "Mayo", "Junio", "Julio", "Agosto", "Septiembre", "Octubre", "Noviembre"}, 0)-MONTH('BD Asesor'!D8), 6)=0), AND('BD Asesor'!H8="Anual", MONTH('BD Asesor'!D8)=MATCH($B$2, {"Enero", "Febrero", "Marzo", "Abril", "Mayo", "Junio", "Julio", "Agosto", "Septiembre", "Octubre", "Noviembre"}, 0)) ), 'BD Asesor'!D8, "")} -> 44238 | G6: {=IF(OR( AND('BD Asesor'!H8="Mensual", MATCH($B$2, {"Enero", "Febrero", "Marzo", "Abril", "Mayo", "Junio", "Julio", "Agosto", "Septiembre", "Octubre", "Noviembre", "Diciembre"}, 0)>=1), AND('BD Asesor'!H8="Trimestral", MOD(MATCH($B$2, {"Enero", "Febrero", "Marzo", "Abril", "Mayo", "Junio", "Julio", "Agosto", "Septiembre", "Octubre", "Noviembre"}, 0)-MONTH('BD Asesor'!D8), 3)=0), AND('BD Asesor'!H8="Semestral", MOD(MATCH($B$2, {"Enero", "Febrero", "Marzo", "Abril", "Mayo", "Junio", "Julio", "Agosto", "Septiembre", "Octubre", "Noviembre"}, 0)-MONTH('BD Asesor'!D8), 6)=0), AND('BD Asesor'!H8="Anual", MONTH('BD Asesor'!D8)=MATCH($B$2, {"Enero", "Febrero", "Marzo", "Abril", "Mayo", "Junio", "Julio", "Agosto", "Septiembre", "Octubre", "Noviembre"}, 0)) ), 'BD Asesor'!E8, "")} -> GM0000512930 | H6: {=IF(OR( AND('BD Asesor'!H8="Mensual", MATCH($B$2, {"Enero", "Febrero", "Marzo", "Abril", "Mayo", "Junio", "Julio", "Agosto", "Septiembre", "Octubre", "Noviembre", "Diciembre"}, 0)>=1), AND('BD Asesor'!H8="Trimestral", MOD(MATCH($B$2, {"Enero", "Febrero", "Marzo", "Abril", "Mayo", "Junio", "Julio", "Agosto", "Septiembre", "Octubre", "Noviembre"}, 0)-MONTH('BD Asesor'!D8), 3)=0), AND('BD Asesor'!H8="Semestral", MOD(MATCH($B$2, {"Enero", "Febrero", "Marzo", "Abril", "Mayo", "Junio", "Julio", "Agosto", "Septiembre", "Octubre", "Noviembre"}, 0)-MONTH('BD Asesor'!D8), 6)=0), AND('BD Asesor'!H8="Anual", MONTH('BD Asesor'!D8)=MATCH($B$2, {"Enero", "Febrero", "Marzo", "Abril", "Mayo", "Junio", "Julio", "Agosto", "Septiembre", "Octubre", "Noviembre"}, 0)) ), 'BD Asesor'!F8, "")} -> 16966.92 | I6: {=IF(OR( AND('BD Asesor'!H8="Mensual", MATCH($B$2, {"Enero", "Febrero", "Marzo", "Abril", "Mayo", "Junio", "Julio", "Agosto", "Septiembre", "Octubre", "Noviembre", "Diciembre"}, 0)>=1), AND('BD Asesor'!H8="Trimestral", MOD(MATCH($B$2, {"Enero", "Febrero", "Marzo", "Abril", "Mayo", "Junio", "Julio", "Agosto", "Septiembre", "Octubre", "Noviembre"}, 0)-MONTH('BD Asesor'!D8), 3)=0), AND('BD Asesor'!H8="Semestral", MOD(MATCH($B$2, {"Enero", "Febrero", "Marzo", "Abril", "Mayo", "Junio", "Julio", "Agosto", "Septiembre", "Octubre", "Noviembre"}, 0)-MONTH('BD Asesor'!D8), 6)=0), AND('BD Asesor'!H8="Anual", MONTH('BD Asesor'!D8)=MATCH($B$2, {"Enero", "Febrero", "Marzo", "Abril", "Mayo", "Junio", "Julio", "Agosto", "Septiembre", "Octubre", "Noviembre"}, 0)) ), 'BD Asesor'!G8, "")} -> MXN | J6: {=IF(OR( AND('BD Asesor'!H8="Mensual", MATCH($B$2, {"Enero", "Febrero", "Marzo", "Abril", "Mayo", "Junio", "Julio", "Agosto", "Septiembre", "Octubre", "Noviembre", "Diciembre"}, 0)>=1), AND('BD Asesor'!H8="Trimestral", MOD(MATCH($B$2, {"Enero", "Febrero", "Marzo", "Abril", "Mayo", "Junio", "Julio", "Agosto", "Septiembre", "Octubre", "Noviembre"}, 0)-MONTH('BD Asesor'!D8), 3)=0), AND('BD Asesor'!H8="Semestral", MOD(MATCH($B$2, {"Enero", "Febrero", "Marzo", "Abril", "Mayo", "Junio", "Julio", "Agosto", "Septiembre", "Octubre", "Noviembre"}, 0)-MONTH('BD Asesor'!D8), 6)=0), AND('BD Asesor'!H8="Anual", MONTH('BD Asesor'!D8)=MATCH($B$2, {"Enero", "Febrero", "Marzo", "Abril", "Mayo", "Junio", "Julio", "Agosto", "Septiembre", "Octubre", "Noviembre"}, 0)) ), 'BD Asesor'!H8, "")} -> Mensual | K6: {=IF(OR( AND('BD Asesor'!H8="Mensual", MATCH($B$2, {"Enero", "Febrero", "Marzo", "Abril", "Mayo", "Junio", "Julio", "Agosto", "Septiembre", "Octubre", "Noviembre", "Diciembre"}, 0)>=1), AND('BD Asesor'!H8="Trimestral", MOD(MATCH($B$2, {"Enero", "Febrero", "Marzo", "Abril", "Mayo", "Junio", "Julio", "Agosto", "Septiembre", "Octubre", "Noviembre"}, 0)-MONTH('BD Asesor'!D8), 3)=0), AND('BD Asesor'!H8="Semestral", MOD(MATCH($B$2, {"Enero", "Febrero", "Marzo", "Abril", "Mayo", "Junio", "Julio", "Agosto", "Septiembre", "Octubre", "Noviembre"}, 0)-MONTH('BD Asesor'!D8), 6)=0), AND('BD Asesor'!H8="Anual", MONTH('BD Asesor'!D8)=MATCH($B$2, {"Enero", "Febrero", "Marzo", "Abril", "Mayo", "Junio", "Julio", "Agosto", "Septiembre", "Octubre", "Noviembre"}, 0)) ), 'BD Asesor'!K8, "")} -> TD | L6: {=IF(OR( AND('BD Asesor'!H8="Mensual", MATCH($B$2, {"Enero", "Febrero", "Marzo", "Abril", "Mayo", "Junio", "Julio", "Agosto", "Septiembre", "Octubre", "Noviembre", "Diciembre"}, 0)>=1), AND('BD Asesor'!H8="Trimestral", MOD(MATCH($B$2, {"Enero", "Febrero", "Marzo", "Abril", "Mayo", "Junio", "Julio", "Agosto", "Septiembre", "Octubre", "Noviembre"}, 0)-MONTH('BD Asesor'!D8), 3)=0), AND('BD Asesor'!H8="Semestral", MOD(MATCH($B$2, {"Enero", "Febrero", "Marzo", "Abril", "Mayo", "Junio", "Julio", "Agosto", "Septiembre", "Octubre", "Noviembre"}, 0)-MONTH('BD Asesor'!D8), 6)=0), AND('BD Asesor'!H8="Anual", MONTH('BD Asesor'!D8)=MATCH($B$2, {"Enero", "Febrero", "Marzo", "Abril", "Mayo", "Junio", "Julio", "Agosto", "Septiembre", "Octubre", "Noviembre"}, 0)) ), 'BD Asesor'!L8, "")} -> Gastos Médicos | N6: =IFERROR(__xludf.DUMMYFUNCTION("FILTER(C6:L2000,C6:C2000<>"""",E6:E2000=""Activo"")"),"ABRAHAM GALICIA MANCERA") -> ABRAHAM GALICIA MANCERA | O6: =IFERROR(__xludf.DUMMYFUNCTION("""COMPUTED_VALUE"""),"H") -> H | P6: =IFERROR(__xludf.DUMMYFUNCTION("""COMPUTED_VALUE"""),"Activo") -> Activo | Q6: =IFERROR(__xludf.DUMMYFUNCTION("""COMPUTED_VALUE"""),44238.0) -> 44238 | R6: =IFERROR(__xludf.DUMMYFUNCTION("""COMPUTED_VALUE"""),"GM0000512930") -> GM0000512930 | S6: =IFERROR(__xludf.DUMMYFUNCTION("""COMPUTED_VALUE"""),16966.920000000002) -> 16966.92 | T6: =IFERROR(__xludf.DUMMYFUNCTION("""COMPUTED_VALUE"""),"MXN") -> MXN | U6: =IFERROR(__xludf.DUMMYFUNCTION("""COMPUTED_VALUE"""),"Mensual") -> Mensual | V6: =IFERROR(__xludf.DUMMYFUNCTION("""COMPUTED_VALUE"""),"TD") -> TD | W6: =IFERROR(__xludf.DUMMYFUNCTION("""COMPUTED_VALUE"""),"Gastos Médicos ") -> Gastos Médicos
C7: {=IF(OR( AND('BD Asesor'!H9="Mensual", MATCH($B$2, {"Enero", "Febrero", "Marzo", "Abril", "Mayo", "Junio", "Julio", "Agosto", "Septiembre", "Octubre", "Noviembre", "Diciembre"}, 0)>=1), AND('BD Asesor'!H9="Trimestral", MOD(MATCH($B$2, {"Enero", "Febrero", "Marzo", "Abril", "Mayo", "Junio", "Julio", "Agosto", "Septiembre", "Octubre", "Noviembre"}, 0)-MONTH('BD Asesor'!D9), 3)=0), AND('BD Asesor'!H9="Semestral", MOD(MATCH($B$2, {"Enero", "Febrero", "Marzo", "Abril", "Mayo", "Junio", "Julio", "Agosto", "Septiembre", "Octubre", "Noviembre"}, 0)-MONTH('BD Asesor'!D9), 6)=0), AND('BD Asesor'!H9="Anual", MONTH('BD Asesor'!D9)=MATCH($B$2, {"Enero", "Febrero", "Marzo", "Abril", "Mayo", "Junio", "Julio", "Agosto", "Septiembre", "Octubre", "Noviembre"}, 0)) ), 'BD Asesor'!A9, "")} -> ABRAHAM GALICIA MANCERA | D7: {=IF(OR( AND('BD Asesor'!H9="Mensual", MATCH($B$2, {"Enero", "Febrero", "Marzo", "Abril", "Mayo", "Junio", "Julio", "Agosto", "Septiembre", "Octubre", "Noviembre", "Diciembre"}, 0)>=1), AND('BD Asesor'!H9="Trimestral", MOD(MATCH($B$2, {"Enero", "Febrero", "Marzo", "Abril", "Mayo", "Junio", "Julio", "Agosto", "Septiembre", "Octubre", "Noviembre"}, 0)-MONTH('BD Asesor'!D9), 3)=0), AND('BD Asesor'!H9="Semestral", MOD(MATCH($B$2, {"Enero", "Febrero", "Marzo", "Abril", "Mayo", "Junio", "Julio", "Agosto", "Septiembre", "Octubre", "Noviembre"}, 0)-MONTH('BD Asesor'!D9), 6)=0), AND('BD Asesor'!H9="Anual", MONTH('BD Asesor'!D9)=MATCH($B$2, {"Enero", "Febrero", "Marzo", "Abril", "Mayo", "Junio", "Julio", "Agosto", "Septiembre", "Octubre", "Noviembre"}, 0)) ), 'BD Asesor'!B9, "")} -> H | E7: {=IF(OR( AND('BD Asesor'!H9="Mensual", MATCH($B$2, {"Enero", "Febrero", "Marzo", "Abril", "Mayo", "Junio", "Julio", "Agosto", "Septiembre", "Octubre", "Noviembre", "Diciembre"}, 0)>=1), AND('BD Asesor'!H9="Trimestral", MOD(MATCH($B$2, {"Enero", "Febrero", "Marzo", "Abril", "Mayo", "Junio", "Julio", "Agosto", "Septiembre", "Octubre", "Noviembre"}, 0)-MONTH('BD Asesor'!D9), 3)=0), AND('BD Asesor'!H9="Semestral", MOD(MATCH($B$2, {"Enero", "Febrero", "Marzo", "Abril", "Mayo", "Junio", "Julio", "Agosto", "Septiembre", "Octubre", "Noviembre"}, 0)-MONTH('BD Asesor'!D9), 6)=0), AND('BD Asesor'!H9="Anual", MONTH('BD Asesor'!D9)=MATCH($B$2, {"Enero", "Febrero", "Marzo", "Abril", "Mayo", "Junio", "Julio", "Agosto", "Septiembre", "Octubre", "Noviembre"}, 0)) ), 'BD Asesor'!C9, "")} -> Activo | F7: {=IF(OR( AND('BD Asesor'!H9="Mensual", MATCH($B$2, {"Enero", "Febrero", "Marzo", "Abril", "Mayo", "Junio", "Julio", "Agosto", "Septiembre", "Octubre", "Noviembre", "Diciembre"}, 0)>=1), AND('BD Asesor'!H9="Trimestral", MOD(MATCH($B$2, {"Enero", "Febrero", "Marzo", "Abril", "Mayo", "Junio", "Julio", "Agosto", "Septiembre", "Octubre", "Noviembre"}, 0)-MONTH('BD Asesor'!D9), 3)=0), AND('BD Asesor'!H9="Semestral", MOD(MATCH($B$2, {"Enero", "Febrero", "Marzo", "Abril", "Mayo", "Junio", "Julio", "Agosto", "Septiembre", "Octubre", "Noviembre"}, 0)-MONTH('BD Asesor'!D9), 6)=0), AND('BD Asesor'!H9="Anual", MONTH('BD Asesor'!D9)=MATCH($B$2, {"Enero", "Febrero", "Marzo", "Abril", "Mayo", "Junio", "Julio", "Agosto", "Septiembre", "Octubre", "Noviembre"}, 0)) ), 'BD Asesor'!D9, "")} -> 44247 | G7: {=IF(OR( AND('BD Asesor'!H9="Mensual", MATCH($B$2, {"Enero", "Febrero", "Marzo", "Abril", "Mayo", "Junio", "Julio", "Agosto", "Septiembre", "Octubre", "Noviembre", "Diciembre"}, 0)>=1), AND('BD Asesor'!H9="Trimestral", MOD(MATCH($B$2, {"Enero", "Febrero", "Marzo", "Abril", "Mayo", "Junio", "Julio", "Agosto", "Septiembre", "Octubre", "Noviembre"}, 0)-MONTH('BD Asesor'!D9), 3)=0), AND('BD Asesor'!H9="Semestral", MOD(MATCH($B$2, {"Enero", "Febrero", "Marzo", "Abril", "Mayo", "Junio", "Julio", "Agosto", "Septiembre", "Octubre", "Noviembre"}, 0)-MONTH('BD Asesor'!D9), 6)=0), AND('BD Asesor'!H9="Anual", MONTH('BD Asesor'!D9)=MATCH($B$2, {"Enero", "Febrero", "Marzo", "Abril", "Mayo", "Junio", "Julio", "Agosto", "Septiembre", "Octubre", "Noviembre"}, 0)) ), 'BD Asesor'!E9, "")} -> VI0002585905 | H7: {=IF(OR( AND('BD Asesor'!H9="Mensual", MATCH($B$2, {"Enero", "Febrero", "Marzo", "Abril", "Mayo", "Junio", "Julio", "Agosto", "Septiembre", "Octubre", "Noviembre", "Diciembre"}, 0)>=1), AND('BD Asesor'!H9="Trimestral", MOD(MATCH($B$2, {"Enero", "Febrero", "Marzo", "Abril", "Mayo", "Junio", "Julio", "Agosto", "Septiembre", "Octubre", "Noviembre"}, 0)-MONTH('BD Asesor'!D9), 3)=0), AND('BD Asesor'!H9="Semestral", MOD(MATCH($B$2, {"Enero", "Febrero", "Marzo", "Abril", "Mayo", "Junio", "Julio", "Agosto", "Septiembre", "Octubre", "Noviembre"}, 0)-MONTH('BD Asesor'!D9), 6)=0), AND('BD Asesor'!H9="Anual", MONTH('BD Asesor'!D9)=MATCH($B$2, {"Enero", "Febrero", "Marzo", "Abril", "Mayo", "Junio", "Julio", "Agosto", "Septiembre", "Octubre", "Noviembre"}, 0)) ), 'BD Asesor'!F9, "")} -> 66766.14 | I7: {=IF(OR( AND('BD Asesor'!H9="Mensual", MATCH($B$2, {"Enero", "Febrero", "Marzo", "Abril", "Mayo", "Junio", "Julio", "Agosto", "Septiembre", "Octubre", "Noviembre", "Diciembre"}, 0)>=1), AND('BD Asesor'!H9="Trimestral", MOD(MATCH($B$2, {"Enero", "Febrero", "Marzo", "Abril", "Mayo", "Junio", "Julio", "Agosto", "Septiembre", "Octubre", "Noviembre"}, 0)-MONTH('BD Asesor'!D9), 3)=0), AND('BD Asesor'!H9="Semestral", MOD(MATCH($B$2, {"Enero", "Febrero", "Marzo", "Abril", "Mayo", "Junio", "Julio", "Agosto", "Septiembre", "Octubre", "Noviembre"}, 0)-MONTH('BD Asesor'!D9), 6)=0), AND('BD Asesor'!H9="Anual", MONTH('BD Asesor'!D9)=MATCH($B$2, {"Enero", "Febrero", "Marzo", "Abril", "Mayo", "Junio", "Julio", "Agosto", "Septiembre", "Octubre", "Noviembre"}, 0)) ), 'BD Asesor'!G9, "")} -> UDIS | J7: {=IF(OR( AND('BD Asesor'!H9="Mensual", MATCH($B$2, {"Enero", "Febrero", "Marzo", "Abril", "Mayo", "Junio", "Julio", "Agosto", "Septiembre", "Octubre", "Noviembre", "Diciembre"}, 0)>=1), AND('BD Asesor'!H9="Trimestral", MOD(MATCH($B$2, {"Enero", "Febrero", "Marzo", "Abril", "Mayo", "Junio", "Julio", "Agosto", "Septiembre", "Octubre", "Noviembre"}, 0)-MONTH('BD Asesor'!D9), 3)=0), AND('BD Asesor'!H9="Semestral", MOD(MATCH($B$2, {"Enero", "Febrero", "Marzo", "Abril", "Mayo", "Junio", "Julio", "Agosto", "Septiembre", "Octubre", "Noviembre"}, 0)-MONTH('BD Asesor'!D9), 6)=0), AND('BD Asesor'!H9="Anual", MONTH('BD Asesor'!D9)=MATCH($B$2, {"Enero", "Febrero", "Marzo", "Abril", "Mayo", "Junio", "Julio", "Agosto", "Septiembre", "Octubre", "Noviembre"}, 0)) ), 'BD Asesor'!H9, "")} -> Mensual | K7: {=IF(OR( AND('BD Asesor'!H9="Mensual", MATCH($B$2, {"Enero", "Febrero", "Marzo", "Abril", "Mayo", "Junio", "Julio", "Agosto", "Septiembre", "Octubre", "Noviembre", "Diciembre"}, 0)>=1), AND('BD Asesor'!H9="Trimestral", MOD(MATCH($B$2, {"Enero", "Febrero", "Marzo", "Abril", "Mayo", "Junio", "Julio", "Agosto", "Septiembre", "Octubre", "Noviembre"}, 0)-MONTH('BD Asesor'!D9), 3)=0), AND('BD Asesor'!H9="Semestral", MOD(MATCH($B$2, {"Enero", "Febrero", "Marzo", "Abril", "Mayo", "Junio", "Julio", "Agosto", "Septiembre", "Octubre", "Noviembre"}, 0)-MONTH('BD Asesor'!D9), 6)=0), AND('BD Asesor'!H9="Anual", MONTH('BD Asesor'!D9)=MATCH($B$2, {"Enero", "Febrero", "Marzo", "Abril", "Mayo", "Junio", "Julio", "Agosto", "Septiembre", "Octubre", "Noviembre"}, 0)) ), 'BD Asesor'!K9, "")} -> TD | L7: {=IF(OR( AND('BD Asesor'!H9="Mensual", MATCH($B$2, {"Enero", "Febrero", "Marzo", "Abril", "Mayo", "Junio", "Julio", "Agosto", "Septiembre", "Octubre", "Noviembre", "Diciembre"}, 0)>=1), AND('BD Asesor'!H9="Trimestral", MOD(MATCH($B$2, {"Enero", "Febrero", "Marzo", "Abril", "Mayo", "Junio", "Julio", "Agosto", "Septiembre", "Octubre", "Noviembre"}, 0)-MONTH('BD Asesor'!D9), 3)=0), AND('BD Asesor'!H9="Semestral", MOD(MATCH($B$2, {"Enero", "Febrero", "Marzo", "Abril", "Mayo", "Junio", "Julio", "Agosto", "Septiembre", "Octubre", "Noviembre"}, 0)-MONTH('BD Asesor'!D9), 6)=0), AND('BD Asesor'!H9="Anual", MONTH('BD Asesor'!D9)=MATCH($B$2, {"Enero", "Febrero", "Marzo", "Abril", "Mayo", "Junio", "Julio", "Agosto", "Septiembre", "Octubre", "Noviembre"}, 0)) ), 'BD Asesor'!L9, "")} -> Vida | N7: =IFERROR(__xludf.DUMMYFUNCTION("""COMPUTED_VALUE"""),"ABRAHAM GALICIA MANCERA") -> ABRAHAM GALICIA MANCERA | O7: =IFERROR(__xludf.DUMMYFUNCTION("""COMPUTED_VALUE"""),"H") -> H | P7: =IFERROR(__xludf.DUMMYFUNCTION("""COMPUTED_VALUE"""),"Activo") -> Activo | Q7: =IFERROR(__xludf.DUMMYFUNCTION("""COMPUTED_VALUE"""),44247.0) -> 44247 | R7: =IFERROR(__xludf.DUMMYFUNCTION("""COMPUTED_VALUE"""),"VI0002585905") -> VI0002585905 | S7: =IFERROR(__xludf.DUMMYFUNCTION("""COMPUTED_VALUE"""),66766.13999999998) -> 66766.14 | T7: =IFERROR(__xludf.DUMMYFUNCTION("""COMPUTED_VALUE"""),"UDIS") -> UDIS | U7: =IFERROR(__xludf.DUMMYFUNCTION("""COMPUTED_VALUE"""),"Mensual") -> Mensual | V7: =IFERROR(__xludf.DUMMYFUNCTION("""COMPUTED_VALUE"""),"TD") -> TD | W7: =IFERROR(__xludf.DUMMYFUNCTION("""COMPUTED_VALUE"""),"Vida") -> Vida
C8: {=IF(OR( AND('BD Asesor'!H10="Mensual", MATCH($B$2, {"Enero", "Febrero", "Marzo", "Abril", "Mayo", "Junio", "Julio", "Agosto", "Septiembre", "Octubre", "Noviembre", "Diciembre"}, 0)>=1), AND('BD Asesor'!H10="Trimestral", MOD(MATCH($B$2, {"Enero", "Febrero", "Marzo", "Abril", "Mayo", "Junio", "Julio", "Agosto", "Septiembre", "Octubre", "Noviembre"}, 0)-MONTH('BD Asesor'!D10), 3)=0), AND('BD Asesor'!H10="Semestral", MOD(MATCH($B$2, {"Enero", "Febrero", "Marzo", "Abril", "Mayo", "Junio", "Julio", "Agosto", "Septiembre", "Octubre", "Noviembre"}, 0)-MONTH('BD Asesor'!D10), 6)=0), AND('BD Asesor'!H10="Anual", MONTH('BD Asesor'!D10)=MATCH($B$2, {"Enero", "Febrero", "Marzo", "Abril", "Mayo", "Junio", "Julio", "Agosto", "Septiembre", "Octubre", "Noviembre"}, 0)) ), 'BD Asesor'!A10, "")} | D8: {=IF(OR( AND('BD Asesor'!H10="Mensual", MATCH($B$2, {"Enero", "Febrero", "Marzo", "Abril", "Mayo", "Junio", "Julio", "Agosto", "Septiembre", "Octubre", "Noviembre", "Diciembre"}, 0)>=1), AND('BD Asesor'!H10="Trimestral", MOD(MATCH($B$2, {"Enero", "Febrero", "Marzo", "Abril", "Mayo", "Junio", "Julio", "Agosto", "Septiembre", "Octubre", "Noviembre"}, 0)-MONTH('BD Asesor'!D10), 3)=0), AND('BD Asesor'!H10="Semestral", MOD(MATCH($B$2, {"Enero", "Febrero", "Marzo", "Abril", "Mayo", "Junio", "Julio", "Agosto", "Septiembre", "Octubre", "Noviembre"}, 0)-MONTH('BD Asesor'!D10), 6)=0), AND('BD Asesor'!H10="Anual", MONTH('BD Asesor'!D10)=MATCH($B$2, {"Enero", "Febrero", "Marzo", "Abril", "Mayo", "Junio", "Julio", "Agosto", "Septiembre", "Octubre", "Noviembre"}, 0)) ), 'BD Asesor'!B10, "")} | E8: {=IF(OR( AND('BD Asesor'!H10="Mensual", MATCH($B$2, {"Enero", "Febrero", "Marzo", "Abril", "Mayo", "Junio", "Julio", "Agosto", "Septiembre", "Octubre", "Noviembre", "Diciembre"}, 0)>=1), AND('BD Asesor'!H10="Trimestral", MOD(MATCH($B$2, {"Enero", "Febrero", "Marzo", "Abril", "Mayo", "Junio", "Julio", "Agosto", "Septiembre", "Octubre", "Noviembre"}, 0)-MONTH('BD Asesor'!D10), 3)=0), AND('BD Asesor'!H10="Semestral", MOD(MATCH($B$2, {"Enero", "Febrero", "Marzo", "Abril", "Mayo", "Junio", "Julio", "Agosto", "Septiembre", "Octubre", "Noviembre"}, 0)-MONTH('BD Asesor'!D10), 6)=0), AND('BD Asesor'!H10="Anual", MONTH('BD Asesor'!D10)=MATCH($B$2, {"Enero", "Febrero", "Marzo", "Abril", "Mayo", "Junio", "Julio", "Agosto", "Septiembre", "Octubre", "Noviembre"}, 0)) ), 'BD Asesor'!C10, "")} | F8: {=IF(OR( AND('BD Asesor'!H10="Mensual", MATCH($B$2, {"Enero", "Febrero", "Marzo", "Abril", "Mayo", "Junio", "Julio", "Agosto", "Septiembre", "Octubre", "Noviembre", "Diciembre"}, 0)>=1), AND('BD Asesor'!H10="Trimestral", MOD(MATCH($B$2, {"Enero", "Febrero", "Marzo", "Abril", "Mayo", "Junio", "Julio", "Agosto", "Septiembre", "Octubre", "Noviembre"}, 0)-MONTH('BD Asesor'!D10), 3)=0), AND('BD Asesor'!H10="Semestral", MOD(MATCH($B$2, {"Enero", "Febrero", "Marzo", "Abril", "Mayo", "Junio", "Julio", "Agosto", "Septiembre", "Octubre", "Noviembre"}, 0)-MONTH('BD Asesor'!D10), 6)=0), AND('BD Asesor'!H10="Anual", MONTH('BD Asesor'!D10)=MATCH($B$2, {"Enero", "Febrero", "Marzo", "Abril", "Mayo", "Junio", "Julio", "Agosto", "Septiembre", "Octubre", "Noviembre"}, 0)) ), 'BD Asesor'!D10, "")} | G8: {=IF(OR( AND('BD Asesor'!H10="Mensual", MATCH($B$2, {"Enero", "Febrero", "Marzo", "Abril", "Mayo", "Junio", "Julio", "Agosto", "Septiembre", "Octubre", "Noviembre", "Diciembre"}, 0)>=1), AND('BD Asesor'!H10="Trimestral", MOD(MATCH($B$2, {"Enero", "Febrero", "Marzo", "Abril", "Mayo", "Junio", "Julio", "Agosto", "Septiembre", "Octubre", "Noviembre"}, 0)-MONTH('BD Asesor'!D10), 3)=0), AND('BD Asesor'!H10="Semestral", MOD(MATCH($B$2, {"Enero", "Febrero", "Marzo", "Abril", "Mayo", "Junio", "Julio", "Agosto", "Septiembre", "Octubre", "Noviembre"}, 0)-MONTH('BD Asesor'!D10), 6)=0), AND('BD Asesor'!H10="Anual", MONTH('BD Asesor'!D10)=MATCH($B$2, {"Enero", "Febrero", "Marzo", "Abril", "Mayo", "Junio", "Julio", "Agosto", "Septiembre", "Octubre", "Noviembre"}, 0)) ), 'BD Asesor'!E10, "")} | H8: {=IF(OR( AND('BD Asesor'!H10="Mensual", MATCH($B$2, {"Enero", "Febrero", "Marzo", "Abril", "Mayo", "Junio", "Julio", "Agosto", "Septiembre", "Octubre", "Noviembre", "Diciembre"}, 0)>=1), AND('BD Asesor'!H10="Trimestral", MOD(MATCH($B$2, {"Enero", "Febrero", "Marzo", "Abril", "Mayo", "Junio", "Julio", "Agosto", "Septiembre", "Octubre", "Noviembre"}, 0)-MONTH('BD Asesor'!D10), 3)=0), AND('BD Asesor'!H10="Semestral", MOD(MATCH($B$2, {"Enero", "Febrero", "Marzo", "Abril", "Mayo", "Junio", "Julio", "Agosto", "Septiembre", "Octubre", "Noviembre"}, 0)-MONTH('BD Asesor'!D10), 6)=0), AND('BD Asesor'!H10="Anual", MONTH('BD Asesor'!D10)=MATCH($B$2, {"Enero", "Febrero", "Marzo", "Abril", "Mayo", "Junio", "Julio", "Agosto", "Septiembre", "Octubre", "Noviembre"}, 0)) ), 'BD Asesor'!F10, "")} | I8: {=IF(OR( AND('BD Asesor'!H10="Mensual", MATCH($B$2, {"Enero", "Febrero", "Marzo", "Abril", "Mayo", "Junio", "Julio", "Agosto", "Septiembre", "Octubre", "Noviembre", "Diciembre"}, 0)>=1), AND('BD Asesor'!H10="Trimestral", MOD(MATCH($B$2, {"Enero", "Febrero", "Marzo", "Abril", "Mayo", "Junio", "Julio", "Agosto", "Septiembre", "Octubre", "Noviembre"}, 0)-MONTH('BD Asesor'!D10), 3)=0), AND('BD Asesor'!H10="Semestral", MOD(MATCH($B$2, {"Enero", "Febrero", "Marzo", "Abril", "Mayo", "Junio", "Julio", "Agosto", "Septiembre", "Octubre", "Noviembre"}, 0)-MONTH('BD Asesor'!D10), 6)=0), AND('BD Asesor'!H10="Anual", MONTH('BD Asesor'!D10)=MATCH($B$2, {"Enero", "Febrero", "Marzo", "Abril", "Mayo", "Junio", "Julio", "Agosto", "Septiembre", "Octubre", "Noviembre"}, 0)) ), 'BD Asesor'!G10, "")} | J8: {=IF(OR( AND('BD Asesor'!H10="Mensual", MATCH($B$2, {"Enero", "Febrero", "Marzo", "Abril", "Mayo", "Junio", "Julio", "Agosto", "Septiembre", "Octubre", "Noviembre", "Diciembre"}, 0)>=1), AND('BD Asesor'!H10="Trimestral", MOD(MATCH($B$2, {"Enero", "Febrero", "Marzo", "Abril", "Mayo", "Junio", "Julio", "Agosto", "Septiembre", "Octubre", "Noviembre"}, 0)-MONTH('BD Asesor'!D10), 3)=0), AND('BD Asesor'!H10="Semestral", MOD(MATCH($B$2, {"Enero", "Febrero", "Marzo", "Abril", "Mayo", "Junio", "Julio", "Agosto", "Septiembre", "Octubre", "Noviembre"}, 0)-MONTH('BD Asesor'!D10), 6)=0), AND('BD Asesor'!H10="Anual", MONTH('BD Asesor'!D10)=MATCH($B$2, {"Enero", "Febrero", "Marzo", "Abril", "Mayo", "Junio", "Julio", "Agosto", "Septiembre", "Octubre", "Noviembre"}, 0)) ), 'BD Asesor'!H10, "")} | K8: {=IF(OR( AND('BD Asesor'!H10="Mensual", MATCH($B$2, {"Enero", "Febrero", "Marzo", "Abril", "Mayo", "Junio", "Julio", "Agosto", "Septiembre", "Octubre", "Noviembre", "Diciembre"}, 0)>=1), AND('BD Asesor'!H10="Trimestral", MOD(MATCH($B$2, {"Enero", "Febrero", "Marzo", "Abril", "Mayo", "Junio", "Julio", "Agosto", "Septiembre", "Octubre", "Noviembre"}, 0)-MONTH('BD Asesor'!D10), 3)=0), AND('BD Asesor'!H10="Semestral", MOD(MATCH($B$2, {"Enero", "Febrero", "Marzo", "Abril", "Mayo", "Junio", "Julio", "Agosto", "Septiembre", "Octubre", "Noviembre"}, 0)-MONTH('BD Asesor'!D10), 6)=0), AND('BD Asesor'!H10="Anual", MONTH('BD Asesor'!D10)=MATCH($B$2, {"Enero", "Febrero", "Marzo", "Abril", "Mayo", "Junio", "Julio", "Agosto", "Septiembre", "Octubre", "Noviembre"}, 0)) ), 'BD Asesor'!K10, "")} | L8: {=IF(OR( AND('BD Asesor'!H10="Mensual", MATCH($B$2, {"Enero", "Febrero", "Marzo", "Abril", "Mayo", "Junio", "Julio", "Agosto", "Septiembre", "Octubre", "Noviembre", "Diciembre"}, 0)>=1), AND('BD Asesor'!H10="Trimestral", MOD(MATCH($B$2, {"Enero", "Febrero", "Marzo", "Abril", "Mayo", "Junio", "Julio", "Agosto", "Septiembre", "Octubre", "Noviembre"}, 0)-MONTH('BD Asesor'!D10), 3)=0), AND('BD Asesor'!H10="Semestral", MOD(MATCH($B$2, {"Enero", "Febrero", "Marzo", "Abril", "Mayo", "Junio", "Julio", "Agosto", "Septiembre", "Octubre", "Noviembre"}, 0)-MONTH('BD Asesor'!D10), 6)=0), AND('BD Asesor'!H10="Anual", MONTH('BD Asesor'!D10)=MATCH($B$2, {"Enero", "Febrero", "Marzo", "Abril", "Mayo", "Junio", "Julio", "Agosto", "Septiembre", "Octubre", "Noviembre"}, 0)) ), 'BD Asesor'!L10, "")} | N8: =IFERROR(__xludf.DUMMYFUNCTION("""COMPUTED_VALUE"""),"ADRIAN ALEJANDRO RAMIREZ MORALES") -> ADRIAN ALEJANDRO RAMIREZ MORALES | O8: =IFERROR(__xludf.DUMMYFUNCTION("""COMPUTED_VALUE"""),"H") -> H | P8: =IFERROR(__xludf.DUMMYFUNCTION("""COMPUTED_VALUE"""),"Activo") -> Activo | Q8: =IFERROR(__xludf.DUMMYFUNCTION("""COMPUTED_VALUE"""),44576.0) -> 44576 | R8: =IFERROR(__xludf.DUMMYFUNCTION("""COMPUTED_VALUE"""),"VI0002645864") -> VI0002645864 | S8: =IFERROR(__xludf.DUMMYFUNCTION("""COMPUTED_VALUE"""),52580.286) -> 52580.286 | T8: =IFERROR(__xludf.DUMMYFUNCTION("""COMPUTED_VALUE"""),"UDIS") -> UDIS | U8: =IFERROR(__xludf.DUMMYFUNCTION("""COMPUTED_VALUE"""),"Mensual") -> Mensual | V8: =IFERROR(__xludf.DUMMYFUNCTION("""COMPUTED_VALUE"""),"TC") -> TC | W8: =IFERROR(__xludf.DUMMYFUNCTION("""COMPUTED_VALUE"""),"Vida") -> Vida
C9: {=IF(OR( AND('BD Asesor'!H11="Mensual", MATCH($B$2, {"Enero", "Febrero", "Marzo", "Abril", "Mayo", "Junio", "Julio", "Agosto", "Septiembre", "Octubre", "Noviembre", "Diciembre"}, 0)>=1), AND('BD Asesor'!H11="Trimestral", MOD(MATCH($B$2, {"Enero", "Febrero", "Marzo", "Abril", "Mayo", "Junio", "Julio", "Agosto", "Septiembre", "Octubre", "Noviembre"}, 0)-MONTH('BD Asesor'!D11), 3)=0), AND('BD Asesor'!H11="Semestral", MOD(MATCH($B$2, {"Enero", "Febrero", "Marzo", "Abril", "Mayo", "Junio", "Julio", "Agosto", "Septiembre", "Octubre", "Noviembre"}, 0)-MONTH('BD Asesor'!D11), 6)=0), AND('BD Asesor'!H11="Anual", MONTH('BD Asesor'!D11)=MATCH($B$2, {"Enero", "Febrero", "Marzo", "Abril", "Mayo", "Junio", "Julio", "Agosto", "Septiembre", "Octubre", "Noviembre"}, 0)) ), 'BD Asesor'!A11, "")} -> ADRIAN ALEJANDRO RAMIREZ MORALES | D9: {=IF(OR( AND('BD Asesor'!H11="Mensual", MATCH($B$2, {"Enero", "Febrero", "Marzo", "Abril", "Mayo", "Junio", "Julio", "Agosto", "Septiembre", "Octubre", "Noviembre", "Diciembre"}, 0)>=1), AND('BD Asesor'!H11="Trimestral", MOD(MATCH($B$2, {"Enero", "Febrero", "Marzo", "Abril", "Mayo", "Junio", "Julio", "Agosto", "Septiembre", "Octubre", "Noviembre"}, 0)-MONTH('BD Asesor'!D11), 3)=0), AND('BD Asesor'!H11="Semestral", MOD(MATCH($B$2, {"Enero", "Febrero", "Marzo", "Abril", "Mayo", "Junio", "Julio", "Agosto", "Septiembre", "Octubre", "Noviembre"}, 0)-MONTH('BD Asesor'!D11), 6)=0), AND('BD Asesor'!H11="Anual", MONTH('BD Asesor'!D11)=MATCH($B$2, {"Enero", "Febrero", "Marzo", "Abril", "Mayo", "Junio", "Julio", "Agosto", "Septiembre", "Octubre", "Noviembre"}, 0)) ), 'BD Asesor'!B11, "")} -> H | E9: {=IF(OR( AND('BD Asesor'!H11="Mensual", MATCH($B$2, {"Enero", "Febrero", "Marzo", "Abril", "Mayo", "Junio", "Julio", "Agosto", "Septiembre", "Octubre", "Noviembre", "Diciembre"}, 0)>=1), AND('BD Asesor'!H11="Trimestral", MOD(MATCH($B$2, {"Enero", "Febrero", "Marzo", "Abril", "Mayo", "Junio", "Julio", "Agosto", "Septiembre", "Octubre", "Noviembre"}, 0)-MONTH('BD Asesor'!D11), 3)=0), AND('BD Asesor'!H11="Semestral", MOD(MATCH($B$2, {"Enero", "Febrero", "Marzo", "Abril", "Mayo", "Junio", "Julio", "Agosto", "Septiembre", "Octubre", "Noviembre"}, 0)-MONTH('BD Asesor'!D11), 6)=0), AND('BD Asesor'!H11="Anual", MONTH('BD Asesor'!D11)=MATCH($B$2, {"Enero", "Febrero", "Marzo", "Abril", "Mayo", "Junio", "Julio", "Agosto", "Septiembre", "Octubre", "Noviembre"}, 0)) ), 'BD Asesor'!C11, "")} -> Activo | F9: {=IF(OR( AND('BD Asesor'!H11="Mensual", MATCH($B$2, {"Enero", "Febrero", "Marzo", "Abril", "Mayo", "Junio", "Julio", "Agosto", "Septiembre", "Octubre", "Noviembre", "Diciembre"}, 0)>=1), AND('BD Asesor'!H11="Trimestral", MOD(MATCH($B$2, {"Enero", "Febrero", "Marzo", "Abril", "Mayo", "Junio", "Julio", "Agosto", "Septiembre", "Octubre", "Noviembre"}, 0)-MONTH('BD Asesor'!D11), 3)=0), AND('BD Asesor'!H11="Semestral", MOD(MATCH($B$2, {"Enero", "Febrero", "Marzo", "Abril", "Mayo", "Junio", "Julio", "Agosto", "Septiembre", "Octubre", "Noviembre"}, 0)-MONTH('BD Asesor'!D11), 6)=0), AND('BD Asesor'!H11="Anual", MONTH('BD Asesor'!D11)=MATCH($B$2, {"Enero", "Febrero", "Marzo", "Abril", "Mayo", "Junio", "Julio", "Agosto", "Septiembre", "Octubre", "Noviembre"}, 0)) ), 'BD Asesor'!D11, "")} -> 44576 | G9: {=IF(OR( AND('BD Asesor'!H11="Mensual", MATCH($B$2, {"Enero", "Febrero", "Marzo", "Abril", "Mayo", "Junio", "Julio", "Agosto", "Septiembre", "Octubre", "Noviembre", "Diciembre"}, 0)>=1), AND('BD Asesor'!H11="Trimestral", MOD(MATCH($B$2, {"Enero", "Febrero", "Marzo", "Abril", "Mayo", "Junio", "Julio", "Agosto", "Septiembre", "Octubre", "Noviembre"}, 0)-MONTH('BD Asesor'!D11), 3)=0), AND('BD Asesor'!H11="Semestral", MOD(MATCH($B$2, {"Enero", "Febrero", "Marzo", "Abril", "Mayo", "Junio", "Julio", "Agosto", "Septiembre", "Octubre", "Noviembre"}, 0)-MONTH('BD Asesor'!D11), 6)=0), AND('BD Asesor'!H11="Anual", MONTH('BD Asesor'!D11)=MATCH($B$2, {"Enero", "Febrero", "Marzo", "Abril", "Mayo", "Junio", "Julio", "Agosto", "Septiembre", "Octubre", "Noviembre"}, 0)) ), 'BD Asesor'!E11, "")} -> VI0002645864 | H9: {=IF(OR( AND('BD Asesor'!H11="Mensual", MATCH($B$2, {"Enero", "Febrero", "Marzo", "Abril", "Mayo", "Junio", "Julio", "Agosto", "Septiembre", "Octubre", "Noviembre", "Diciembre"}, 0)>=1), AND('BD Asesor'!H11="Trimestral", MOD(MATCH($B$2, {"Enero", "Febrero", "Marzo", "Abril", "Mayo", "Junio", "Julio", "Agosto", "Septiembre", "Octubre", "Noviembre"}, 0)-MONTH('BD Asesor'!D11), 3)=0), AND('BD Asesor'!H11="Semestral", MOD(MATCH($B$2, {"Enero", "Febrero", "Marzo", "Abril", "Mayo", "Junio", "Julio", "Agosto", "Septiembre", "Octubre", "Noviembre"}, 0)-MONTH('BD Asesor'!D11), 6)=0), AND('BD Asesor'!H11="Anual", MONTH('BD Asesor'!D11)=MATCH($B$2, {"Enero", "Febrero", "Marzo", "Abril", "Mayo", "Junio", "Julio", "Agosto", "Septiembre", "Octubre", "Noviembre"}, 0)) ), 'BD Asesor'!F11, "")} -> 52580.286 | I9: {=IF(OR( AND('BD Asesor'!H11="Mensual", MATCH($B$2, {"Enero", "Febrero", "Marzo", "Abril", "Mayo", "Junio", "Julio", "Agosto", "Septiembre", "Octubre", "Noviembre", "Diciembre"}, 0)>=1), AND('BD Asesor'!H11="Trimestral", MOD(MATCH($B$2, {"Enero", "Febrero", "Marzo", "Abril", "Mayo", "Junio", "Julio", "Agosto", "Septiembre", "Octubre", "Noviembre"}, 0)-MONTH('BD Asesor'!D11), 3)=0), AND('BD Asesor'!H11="Semestral", MOD(MATCH($B$2, {"Enero", "Febrero", "Marzo", "Abril", "Mayo", "Junio", "Julio", "Agosto", "Septiembre", "Octubre", "Noviembre"}, 0)-MONTH('BD Asesor'!D11), 6)=0), AND('BD Asesor'!H11="Anual", MONTH('BD Asesor'!D11)=MATCH($B$2, {"Enero", "Febrero", "Marzo", "Abril", "Mayo", "Junio", "Julio", "Agosto", "Septiembre", "Octubre", "Noviembre"}, 0)) ), 'BD Asesor'!G11, "")} -> UDIS | J9: {=IF(OR( AND('BD Asesor'!H11="Mensual", MATCH($B$2, {"Enero", "Febrero", "Marzo", "Abril", "Mayo", "Junio", "Julio", "Agosto", "Septiembre", "Octubre", "Noviembre", "Diciembre"}, 0)>=1), AND('BD Asesor'!H11="Trimestral", MOD(MATCH($B$2, {"Enero", "Febrero", "Marzo", "Abril", "Mayo", "Junio", "Julio", "Agosto", "Septiembre", "Octubre", "Noviembre"}, 0)-MONTH('BD Asesor'!D11), 3)=0), AND('BD Asesor'!H11="Semestral", MOD(MATCH($B$2, {"Enero", "Febrero", "Marzo", "Abril", "Mayo", "Junio", "Julio", "Agosto", "Septiembre", "Octubre", "Noviembre"}, 0)-MONTH('BD Asesor'!D11), 6)=0), AND('BD Asesor'!H11="Anual", MONTH('BD Asesor'!D11)=MATCH($B$2, {"Enero", "Febrero", "Marzo", "Abril", "Mayo", "Junio", "Julio", "Agosto", "Septiembre", "Octubre", "Noviembre"}, 0)) ), 'BD Asesor'!H11, "")} -> Mensual | K9: {=IF(OR( AND('BD Asesor'!H11="Mensual", MATCH($B$2, {"Enero", "Febrero", "Marzo", "Abril", "Mayo", "Junio", "Julio", "Agosto", "Septiembre", "Octubre", "Noviembre", "Diciembre"}, 0)>=1), AND('BD Asesor'!H11="Trimestral", MOD(MATCH($B$2, {"Enero", "Febrero", "Marzo", "Abril", "Mayo", "Junio", "Julio", "Agosto", "Septiembre", "Octubre", "Noviembre"}, 0)-MONTH('BD Asesor'!D11), 3)=0), AND('BD Asesor'!H11="Semestral", MOD(MATCH($B$2, {"Enero", "Febrero", "Marzo", "Abril", "Mayo", "Junio", "Julio", "Agosto", "Septiembre", "Octubre", "Noviembre"}, 0)-MONTH('BD Asesor'!D11), 6)=0), AND('BD Asesor'!H11="Anual", MONTH('BD Asesor'!D11)=MATCH($B$2, {"Enero", "Febrero", "Marzo", "Abril", "Mayo", "Junio", "Julio", "Agosto", "Septiembre", "Octubre", "Noviembre"}, 0)) ), 'BD Asesor'!K11, "")} -> TC | L9: {=IF(OR( AND('BD Asesor'!H11="Mensual", MATCH($B$2, {"Enero", "Febrero", "Marzo", "Abril", "Mayo", "Junio", "Julio", "Agosto", "Septiembre", "Octubre", "Noviembre", "Diciembre"}, 0)>=1), AND('BD Asesor'!H11="Trimestral", MOD(MATCH($B$2, {"Enero", "Febrero", "Marzo", "Abril", "Mayo", "Junio", "Julio", "Agosto", "Septiembre", "Octubre", "Noviembre"}, 0)-MONTH('BD Asesor'!D11), 3)=0), AND('BD Asesor'!H11="Semestral", MOD(MATCH($B$2, {"Enero", "Febrero", "Marzo", "Abril", "Mayo", "Junio", "Julio", "Agosto", "Septiembre", "Octubre", "Noviembre"}, 0)-MONTH('BD Asesor'!D11), 6)=0), AND('BD Asesor'!H11="Anual", MONTH('BD Asesor'!D11)=MATCH($B$2, {"Enero", "Febrero", "Marzo", "Abril", "Mayo", "Junio", "Julio", "Agosto", "Septiembre", "Octubre", "Noviembre"}, 0)) ), 'BD Asesor'!L11, "")} -> Vida | N9: =IFERROR(__xludf.DUMMYFUNCTION("""COMPUTED_VALUE"""),"ALEJANDRA DEL CARMEN UREÑA CASILLAS") -> ALEJANDRA DEL CARMEN UREÑA CASILLAS | O9: =IFERROR(__xludf.DUMMYFUNCTION("""COMPUTED_VALUE"""),"M") -> M | P9: =IFERROR(__xludf.DUMMYFUNCTION("""COMPUTED_VALUE"""),"Activo") -> Activo | Q9: =IFERROR(__xludf.DUMMYFUNCTION("""COMPUTED_VALUE"""),43893.0) -> 43893 | R9: =IFERROR(__xludf.DUMMYFUNCTION("""COMPUTED_VALUE"""),"VI0002521501") -> VI0002521501 | S9: =IFERROR(__xludf.DUMMYFUNCTION("""COMPUTED_VALUE"""),40562.97750000001) -> 40562.978 | T9: =IFERROR(__xludf.DUMMYFUNCTION("""COMPUTED_VALUE"""),"UDIS") -> UDIS | U9: =IFERROR(__xludf.DUMMYFUNCTION("""COMPUTED_VALUE"""),"Anual") -> Anual | V9: =IFERROR(__xludf.DUMMYFUNCTION("""COMPUTED_VALUE"""),"TD") -> TD | W9: =IFERROR(__xludf.DUMMYFUNCTION("""COMPUTED_VALUE"""),"Vida") -> Vida
C10: {=IF(OR( AND('BD Asesor'!H12="Mensual", MATCH($B$2, {"Enero", "Febrero", "Marzo", "Abril", "Mayo", "Junio", "Julio", "Agosto", "Septiembre", "Octubre", "Noviembre", "Diciembre"}, 0)>=1), AND('BD Asesor'!H12="Trimestral", MOD(MATCH($B$2, {"Enero", "Febrero", "Marzo", "Abril", "Mayo", "Junio", "Julio", "Agosto", "Septiembre", "Octubre", "Noviembre"}, 0)-MONTH('BD Asesor'!D12), 3)=0), AND('BD Asesor'!H12="Semestral", MOD(MATCH($B$2, {"Enero", "Febrero", "Marzo", "Abril", "Mayo", "Junio", "Julio", "Agosto", "Septiembre", "Octubre", "Noviembre"}, 0)-MONTH('BD Asesor'!D12), 6)=0), AND('BD Asesor'!H12="Anual", MONTH('BD Asesor'!D12)=MATCH($B$2, {"Enero", "Febrero", "Marzo", "Abril", "Mayo", "Junio", "Julio", "Agosto", "Septiembre", "Octubre", "Noviembre"}, 0)) ), 'BD Asesor'!A12, "")} | D10: {=IF(OR( AND('BD Asesor'!H12="Mensual", MATCH($B$2, {"Enero", "Febrero", "Marzo", "Abril", "Mayo", "Junio", "Julio", "Agosto", "Septiembre", "Octubre", "Noviembre", "Diciembre"}, 0)>=1), AND('BD Asesor'!H12="Trimestral", MOD(MATCH($B$2, {"Enero", "Febrero", "Marzo", "Abril", "Mayo", "Junio", "Julio", "Agosto", "Septiembre", "Octubre", "Noviembre"}, 0)-MONTH('BD Asesor'!D12), 3)=0), AND('BD Asesor'!H12="Semestral", MOD(MATCH($B$2, {"Enero", "Febrero", "Marzo", "Abril", "Mayo", "Junio", "Julio", "Agosto", "Septiembre", "Octubre", "Noviembre"}, 0)-MONTH('BD Asesor'!D12), 6)=0), AND('BD Asesor'!H12="Anual", MONTH('BD Asesor'!D12)=MATCH($B$2, {"Enero", "Febrero", "Marzo", "Abril", "Mayo", "Junio", "Julio", "Agosto", "Septiembre", "Octubre", "Noviembre"}, 0)) ), 'BD Asesor'!B12, "")} | E10: {=IF(OR( AND('BD Asesor'!H12="Mensual", MATCH($B$2, {"Enero", "Febrero", "Marzo", "Abril", "Mayo", "Junio", "Julio", "Agosto", "Septiembre", "Octubre", "Noviembre", "Diciembre"}, 0)>=1), AND('BD Asesor'!H12="Trimestral", MOD(MATCH($B$2, {"Enero", "Febrero", "Marzo", "Abril", "Mayo", "Junio", "Julio", "Agosto", "Septiembre", "Octubre", "Noviembre"}, 0)-MONTH('BD Asesor'!D12), 3)=0), AND('BD Asesor'!H12="Semestral", MOD(MATCH($B$2, {"Enero", "Febrero", "Marzo", "Abril", "Mayo", "Junio", "Julio", "Agosto", "Septiembre", "Octubre", "Noviembre"}, 0)-MONTH('BD Asesor'!D12), 6)=0), AND('BD Asesor'!H12="Anual", MONTH('BD Asesor'!D12)=MATCH($B$2, {"Enero", "Febrero", "Marzo", "Abril", "Mayo", "Junio", "Julio", "Agosto", "Septiembre", "Octubre", "Noviembre"}, 0)) ), 'BD Asesor'!C12, "")} | F10: {=IF(OR( AND('BD Asesor'!H12="Mensual", MATCH($B$2, {"Enero", "Febrero", "Marzo", "Abril", "Mayo", "Junio", "Julio", "Agosto", "Septiembre", "Octubre", "Noviembre", "Diciembre"}, 0)>=1), AND('BD Asesor'!H12="Trimestral", MOD(MATCH($B$2, {"Enero", "Febrero", "Marzo", "Abril", "Mayo", "Junio", "Julio", "Agosto", "Septiembre", "Octubre", "Noviembre"}, 0)-MONTH('BD Asesor'!D12), 3)=0), AND('BD Asesor'!H12="Semestral", MOD(MATCH($B$2, {"Enero", "Febrero", "Marzo", "Abril", "Mayo", "Junio", "Julio", "Agosto", "Septiembre", "Octubre", "Noviembre"}, 0)-MONTH('BD Asesor'!D12), 6)=0), AND('BD Asesor'!H12="Anual", MONTH('BD Asesor'!D12)=MATCH($B$2, {"Enero", "Febrero", "Marzo", "Abril", "Mayo", "Junio", "Julio", "Agosto", "Septiembre", "Octubre", "Noviembre"}, 0)) ), 'BD Asesor'!D12, "")} | G10: {=IF(OR( AND('BD Asesor'!H12="Mensual", MATCH($B$2, {"Enero", "Febrero", "Marzo", "Abril", "Mayo", "Junio", "Julio", "Agosto", "Septiembre", "Octubre", "Noviembre", "Diciembre"}, 0)>=1), AND('BD Asesor'!H12="Trimestral", MOD(MATCH($B$2, {"Enero", "Febrero", "Marzo", "Abril", "Mayo", "Junio", "Julio", "Agosto", "Septiembre", "Octubre", "Noviembre"}, 0)-MONTH('BD Asesor'!D12), 3)=0), AND('BD Asesor'!H12="Semestral", MOD(MATCH($B$2, {"Enero", "Febrero", "Marzo", "Abril", "Mayo", "Junio", "Julio", "Agosto", "Septiembre", "Octubre", "Noviembre"}, 0)-MONTH('BD Asesor'!D12), 6)=0), AND('BD Asesor'!H12="Anual", MONTH('BD Asesor'!D12)=MATCH($B$2, {"Enero", "Febrero", "Marzo", "Abril", "Mayo", "Junio", "Julio", "Agosto", "Septiembre", "Octubre", "Noviembre"}, 0)) ), 'BD Asesor'!E12, "")} | H10: {=IF(OR( AND('BD Asesor'!H12="Mensual", MATCH($B$2, {"Enero", "Febrero", "Marzo", "Abril", "Mayo", "Junio", "Julio", "Agosto", "Septiembre", "Octubre", "Noviembre", "Diciembre"}, 0)>=1), AND('BD Asesor'!H12="Trimestral", MOD(MATCH($B$2, {"Enero", "Febrero", "Marzo", "Abril", "Mayo", "Junio", "Julio", "Agosto", "Septiembre", "Octubre", "Noviembre"}, 0)-MONTH('BD Asesor'!D12), 3)=0), AND('BD Asesor'!H12="Semestral", MOD(MATCH($B$2, {"Enero", "Febrero", "Marzo", "Abril", "Mayo", "Junio", "Julio", "Agosto", "Septiembre", "Octubre", "Noviembre"}, 0)-MONTH('BD Asesor'!D12), 6)=0), AND('BD Asesor'!H12="Anual", MONTH('BD Asesor'!D12)=MATCH($B$2, {"Enero", "Febrero", "Marzo", "Abril", "Mayo", "Junio", "Julio", "Agosto", "Septiembre", "Octubre", "Noviembre"}, 0)) ), 'BD Asesor'!F12, "")} | I10: {=IF(OR( AND('BD Asesor'!H12="Mensual", MATCH($B$2, {"Enero", "Febrero", "Marzo", "Abril", "Mayo", "Junio", "Julio", "Agosto", "Septiembre", "Octubre", "Noviembre", "Diciembre"}, 0)>=1), AND('BD Asesor'!H12="Trimestral", MOD(MATCH($B$2, {"Enero", "Febrero", "Marzo", "Abril", "Mayo", "Junio", "Julio", "Agosto", "Septiembre", "Octubre", "Noviembre"}, 0)-MONTH('BD Asesor'!D12), 3)=0), AND('BD Asesor'!H12="Semestral", MOD(MATCH($B$2, {"Enero", "Febrero", "Marzo", "Abril", "Mayo", "Junio", "Julio", "Agosto", "Septiembre", "Octubre", "Noviembre"}, 0)-MONTH('BD Asesor'!D12), 6)=0), AND('BD Asesor'!H12="Anual", MONTH('BD Asesor'!D12)=MATCH($B$2, {"Enero", "Febrero", "Marzo", "Abril", "Mayo", "Junio", "Julio", "Agosto", "Septiembre", "Octubre", "Noviembre"}, 0)) ), 'BD Asesor'!G12, "")} | J10: {=IF(OR( AND('BD Asesor'!H12="Mensual", MATCH($B$2, {"Enero", "Febrero", "Marzo", "Abril", "Mayo", "Junio", "Julio", "Agosto", "Septiembre", "Octubre", "Noviembre", "Diciembre"}, 0)>=1), AND('BD Asesor'!H12="Trimestral", MOD(MATCH($B$2, {"Enero", "Febrero", "Marzo", "Abril", "Mayo", "Junio", "Julio", "Agosto", "Septiembre", "Octubre", "Noviembre"}, 0)-MONTH('BD Asesor'!D12), 3)=0), AND('BD Asesor'!H12="Semestral", MOD(MATCH($B$2, {"Enero", "Febrero", "Marzo", "Abril", "Mayo", "Junio", "Julio", "Agosto", "Septiembre", "Octubre", "Noviembre"}, 0)-MONTH('BD Asesor'!D12), 6)=0), AND('BD Asesor'!H12="Anual", MONTH('BD Asesor'!D12)=MATCH($B$2, {"Enero", "Febrero", "Marzo", "Abril", "Mayo", "Junio", "Julio", "Agosto", "Septiembre", "Octubre", "Noviembre"}, 0)) ), 'BD Asesor'!H12, "")} | K10: {=IF(OR( AND('BD Asesor'!H12="Mensual", MATCH($B$2, {"Enero", "Febrero", "Marzo", "Abril", "Mayo", "Junio", "Julio", "Agosto", "Septiembre", "Octubre", "Noviembre", "Diciembre"}, 0)>=1), AND('BD Asesor'!H12="Trimestral", MOD(MATCH($B$2, {"Enero", "Febrero", "Marzo", "Abril", "Mayo", "Junio", "Julio", "Agosto", "Septiembre", "Octubre", "Noviembre"}, 0)-MONTH('BD Asesor'!D12), 3)=0), AND('BD Asesor'!H12="Semestral", MOD(MATCH($B$2, {"Enero", "Febrero", "Marzo", "Abril", "Mayo", "Junio", "Julio", "Agosto", "Septiembre", "Octubre", "Noviembre"}, 0)-MONTH('BD Asesor'!D12), 6)=0), AND('BD Asesor'!H12="Anual", MONTH('BD Asesor'!D12)=MATCH($B$2, {"Enero", "Febrero", "Marzo", "Abril", "Mayo", "Junio", "Julio", "Agosto", "Septiembre", "Octubre", "Noviembre"}, 0)) ), 'BD Asesor'!K12, "")} | L10: {=IF(OR( AND('BD Asesor'!H12="Mensual", MATCH($B$2, {"Enero", "Febrero", "Marzo", "Abril", "Mayo", "Junio", "Julio", "Agosto", "Septiembre", "Octubre", "Noviembre", "Diciembre"}, 0)>=1), AND('BD Asesor'!H12="Trimestral", MOD(MATCH($B$2, {"Enero", "Febrero", "Marzo", "Abril", "Mayo", "Junio", "Julio", "Agosto", "Septiembre", "Octubre", "Noviembre"}, 0)-MONTH('BD Asesor'!D12), 3)=0), AND('BD Asesor'!H12="Semestral", MOD(MATCH($B$2, {"Enero", "Febrero", "Marzo", "Abril", "Mayo", "Junio", "Julio", "Agosto", "Septiembre", "Octubre", "Noviembre"}, 0)-MONTH('BD Asesor'!D12), 6)=0), AND('BD Asesor'!H12="Anual", MONTH('BD Asesor'!D12)=MATCH($B$2, {"Enero", "Febrero", "Marzo", "Abril", "Mayo", "Junio", "Julio", "Agosto", "Septiembre", "Octubre", "Noviembre"}, 0)) ), 'BD Asesor'!L12, "")} | N10: =IFERROR(__xludf.DUMMYFUNCTION("""COMPUTED_VALUE"""),"ALEJANDRO SOTO ELIZALDE") -> ALEJANDRO SOTO ELIZALDE | O10: =IFERROR(__xludf.DUMMYFUNCTION("""COMPUTED_VALUE"""),"H") -> H | P10: =IFERROR(__xludf.DUMMYFUNCTION("""COMPUTED_VALUE"""),"Activo") -> Activo | Q10: =IFERROR(__xludf.DUMMYFUNCTION("""COMPUTED_VALUE"""),44467.0) -> 44467 | R10: =IFERROR(__xludf.DUMMYFUNCTION("""COMPUTED_VALUE"""),"GM0000540142") -> GM0000540142 | S10: =IFERROR(__xludf.DUMMYFUNCTION("""COMPUTED_VALUE"""),15641.78) -> 15641.78 | T10: =IFERROR(__xludf.DUMMYFUNCTION("""COMPUTED_VALUE"""),"MXN") -> MXN | U10: =IFERROR(__xludf.DUMMYFUNCTION("""COMPUTED_VALUE"""),"Semestral") -> Semestral | V10: =IFERROR(__xludf.DUMMYFUNCTION("""COMPUTED_VALUE"""),"TD") -> TD | W10: =IFERROR(__xludf.DUMMYFUNCTION("""COMPUTED_VALUE"""),"Gastos Médicos ") -> Gastos Médicos
C11: {=IF(OR( AND('BD Asesor'!H13="Mensual", MATCH($B$2, {"Enero", "Febrero", "Marzo", "Abril", "Mayo", "Junio", "Julio", "Agosto", "Septiembre", "Octubre", "Noviembre", "Diciembre"}, 0)>=1), AND('BD Asesor'!H13="Trimestral", MOD(MATCH($B$2, {"Enero", "Febrero", "Marzo", "Abril", "Mayo", "Junio", "Julio", "Agosto", "Septiembre", "Octubre", "Noviembre"}, 0)-MONTH('BD Asesor'!D13), 3)=0), AND('BD Asesor'!H13="Semestral", MOD(MATCH($B$2, {"Enero", "Febrero", "Marzo", "Abril", "Mayo", "Junio", "Julio", "Agosto", "Septiembre", "Octubre", "Noviembre"}, 0)-MONTH('BD Asesor'!D13), 6)=0), AND('BD Asesor'!H13="Anual", MONTH('BD Asesor'!D13)=MATCH($B$2, {"Enero", "Febrero", "Marzo", "Abril", "Mayo", "Junio", "Julio", "Agosto", "Septiembre", "Octubre", "Noviembre"}, 0)) ), 'BD Asesor'!A13, "")} | D11: {=IF(OR( AND('BD Asesor'!H13="Mensual", MATCH($B$2, {"Enero", "Febrero", "Marzo", "Abril", "Mayo", "Junio", "Julio", "Agosto", "Septiembre", "Octubre", "Noviembre", "Diciembre"}, 0)>=1), AND('BD Asesor'!H13="Trimestral", MOD(MATCH($B$2, {"Enero", "Febrero", "Marzo", "Abril", "Mayo", "Junio", "Julio", "Agosto", "Septiembre", "Octubre", "Noviembre"}, 0)-MONTH('BD Asesor'!D13), 3)=0), AND('BD Asesor'!H13="Semestral", MOD(MATCH($B$2, {"Enero", "Febrero", "Marzo", "Abril", "Mayo", "Junio", "Julio", "Agosto", "Septiembre", "Octubre", "Noviembre"}, 0)-MONTH('BD Asesor'!D13), 6)=0), AND('BD Asesor'!H13="Anual", MONTH('BD Asesor'!D13)=MATCH($B$2, {"Enero", "Febrero", "Marzo", "Abril", "Mayo", "Junio", "Julio", "Agosto", "Septiembre", "Octubre", "Noviembre"}, 0)) ), 'BD Asesor'!B13, "")} | E11: {=IF(OR( AND('BD Asesor'!H13="Mensual", MATCH($B$2, {"Enero", "Febrero", "Marzo", "Abril", "Mayo", "Junio", "Julio", "Agosto", "Septiembre", "Octubre", "Noviembre", "Diciembre"}, 0)>=1), AND('BD Asesor'!H13="Trimestral", MOD(MATCH($B$2, {"Enero", "Febrero", "Marzo", "Abril", "Mayo", "Junio", "Julio", "Agosto", "Septiembre", "Octubre", "Noviembre"}, 0)-MONTH('BD Asesor'!D13), 3)=0), AND('BD Asesor'!H13="Semestral", MOD(MATCH($B$2, {"Enero", "Febrero", "Marzo", "Abril", "Mayo", "Junio", "Julio", "Agosto", "Septiembre", "Octubre", "Noviembre"}, 0)-MONTH('BD Asesor'!D13), 6)=0), AND('BD Asesor'!H13="Anual", MONTH('BD Asesor'!D13)=MATCH($B$2, {"Enero", "Febrero", "Marzo", "Abril", "Mayo", "Junio", "Julio", "Agosto", "Septiembre", "Octubre", "Noviembre"}, 0)) ), 'BD Asesor'!C13, "")} | F11: {=IF(OR( AND('BD Asesor'!H13="Mensual", MATCH($B$2, {"Enero", "Febrero", "Marzo", "Abril", "Mayo", "Junio", "Julio", "Agosto", "Septiembre", "Octubre", "Noviembre", "Diciembre"}, 0)>=1), AND('BD Asesor'!H13="Trimestral", MOD(MATCH($B$2, {"Enero", "Febrero", "Marzo", "Abril", "Mayo", "Junio", "Julio", "Agosto", "Septiembre", "Octubre", "Noviembre"}, 0)-MONTH('BD Asesor'!D13), 3)=0), AND('BD Asesor'!H13="Semestral", MOD(MATCH($B$2, {"Enero", "Febrero", "Marzo", "Abril", "Mayo", "Junio", "Julio", "Agosto", "Septiembre", "Octubre", "Noviembre"}, 0)-MONTH('BD Asesor'!D13), 6)=0), AND('BD Asesor'!H13="Anual", MONTH('BD Asesor'!D13)=MATCH($B$2, {"Enero", "Febrero", "Marzo", "Abril", "Mayo", "Junio", "Julio", "Agosto", "Septiembre", "Octubre", "Noviembre"}, 0)) ), 'BD Asesor'!D13, "")} | G11: {=IF(OR( AND('BD Asesor'!H13="Mensual", MATCH($B$2, {"Enero", "Febrero", "Marzo", "Abril", "Mayo", "Junio", "Julio", "Agosto", "Septiembre", "Octubre", "Noviembre", "Diciembre"}, 0)>=1), AND('BD Asesor'!H13="Trimestral", MOD(MATCH($B$2, {"Enero", "Febrero", "Marzo", "Abril", "Mayo", "Junio", "Julio", "Agosto", "Septiembre", "Octubre", "Noviembre"}, 0)-MONTH('BD Asesor'!D13), 3)=0), AND('BD Asesor'!H13="Semestral", MOD(MATCH($B$2, {"Enero", "Febrero", "Marzo", "Abril", "Mayo", "Junio", "Julio", "Agosto", "Septiembre", "Octubre", "Noviembre"}, 0)-MONTH('BD Asesor'!D13), 6)=0), AND('BD Asesor'!H13="Anual", MONTH('BD Asesor'!D13)=MATCH($B$2, {"Enero", "Febrero", "Marzo", "Abril", "Mayo", "Junio", "Julio", "Agosto", "Septiembre", "Octubre", "Noviembre"}, 0)) ), 'BD Asesor'!E13, "")} | H11: {=IF(OR( AND('BD Asesor'!H13="Mensual", MATCH($B$2, {"Enero", "Febrero", "Marzo", "Abril", "Mayo", "Junio", "Julio", "Agosto", "Septiembre", "Octubre", "Noviembre", "Diciembre"}, 0)>=1), AND('BD Asesor'!H13="Trimestral", MOD(MATCH($B$2, {"Enero", "Febrero", "Marzo", "Abril", "Mayo", "Junio", "Julio", "Agosto", "Septiembre", "Octubre", "Noviembre"}, 0)-MONTH('BD Asesor'!D13), 3)=0), AND('BD Asesor'!H13="Semestral", MOD(MATCH($B$2, {"Enero", "Febrero", "Marzo", "Abril", "Mayo", "Junio", "Julio", "Agosto", "Septiembre", "Octubre", "Noviembre"}, 0)-MONTH('BD Asesor'!D13), 6)=0), AND('BD Asesor'!H13="Anual", MONTH('BD Asesor'!D13)=MATCH($B$2, {"Enero", "Febrero", "Marzo", "Abril", "Mayo", "Junio", "Julio", "Agosto", "Septiembre", "Octubre", "Noviembre"}, 0)) ), 'BD Asesor'!F13, "")} | I11: {=IF(OR( AND('BD Asesor'!H13="Mensual", MATCH($B$2, {"Enero", "Febrero", "Marzo", "Abril", "Mayo", "Junio", "Julio", "Agosto", "Septiembre", "Octubre", "Noviembre", "Diciembre"}, 0)>=1), AND('BD Asesor'!H13="Trimestral", MOD(MATCH($B$2, {"Enero", "Febrero", "Marzo", "Abril", "Mayo", "Junio", "Julio", "Agosto", "Septiembre", "Octubre", "Noviembre"}, 0)-MONTH('BD Asesor'!D13), 3)=0), AND('BD Asesor'!H13="Semestral", MOD(MATCH($B$2, {"Enero", "Febrero", "Marzo", "Abril", "Mayo", "Junio", "Julio", "Agosto", "Septiembre", "Octubre", "Noviembre"}, 0)-MONTH('BD Asesor'!D13), 6)=0), AND('BD Asesor'!H13="Anual", MONTH('BD Asesor'!D13)=MATCH($B$2, {"Enero", "Febrero", "Marzo", "Abril", "Mayo", "Junio", "Julio", "Agosto", "Septiembre", "Octubre", "Noviembre"}, 0)) ), 'BD Asesor'!G13, "")} | J11: {=IF(OR( AND('BD Asesor'!H13="Mensual", MATCH($B$2, {"Enero", "Febrero", "Marzo", "Abril", "Mayo", "Junio", "Julio", "Agosto", "Septiembre", "Octubre", "Noviembre", "Diciembre"}, 0)>=1), AND('BD Asesor'!H13="Trimestral", MOD(MATCH($B$2, {"Enero", "Febrero", "Marzo", "Abril", "Mayo", "Junio", "Julio", "Agosto", "Septiembre", "Octubre", "Noviembre"}, 0)-MONTH('BD Asesor'!D13), 3)=0), AND('BD Asesor'!H13="Semestral", MOD(MATCH($B$2, {"Enero", "Febrero", "Marzo", "Abril", "Mayo", "Junio", "Julio", "Agosto", "Septiembre", "Octubre", "Noviembre"}, 0)-MONTH('BD Asesor'!D13), 6)=0), AND('BD Asesor'!H13="Anual", MONTH('BD Asesor'!D13)=MATCH($B$2, {"Enero", "Febrero", "Marzo", "Abril", "Mayo", "Junio", "Julio", "Agosto", "Septiembre", "Octubre", "Noviembre"}, 0)) ), 'BD Asesor'!H13, "")} | K11: {=IF(OR( AND('BD Asesor'!H13="Mensual", MATCH($B$2, {"Enero", "Febrero", "Marzo", "Abril", "Mayo", "Junio", "Julio", "Agosto", "Septiembre", "Octubre", "Noviembre", "Diciembre"}, 0)>=1), AND('BD Asesor'!H13="Trimestral", MOD(MATCH($B$2, {"Enero", "Febrero", "Marzo", "Abril", "Mayo", "Junio", "Julio", "Agosto", "Septiembre", "Octubre", "Noviembre"}, 0)-MONTH('BD Asesor'!D13), 3)=0), AND('BD Asesor'!H13="Semestral", MOD(MATCH($B$2, {"Enero", "Febrero", "Marzo", "Abril", "Mayo", "Junio", "Julio", "Agosto", "Septiembre", "Octubre", "Noviembre"}, 0)-MONTH('BD Asesor'!D13), 6)=0), AND('BD Asesor'!H13="Anual", MONTH('BD Asesor'!D13)=MATCH($B$2, {"Enero", "Febrero", "Marzo", "Abril", "Mayo", "Junio", "Julio", "Agosto", "Septiembre", "Octubre", "Noviembre"}, 0)) ), 'BD Asesor'!K13, "")} | L11: {=IF(OR( AND('BD Asesor'!H13="Mensual", MATCH($B$2, {"Enero", "Febrero", "Marzo", "Abril", "Mayo", "Junio", "Julio", "Agosto", "Septiembre", "Octubre", "Noviembre", "Diciembre"}, 0)>=1), AND('BD Asesor'!H13="Trimestral", MOD(MATCH($B$2, {"Enero", "Febrero", "Marzo", "Abril", "Mayo", "Junio", "Julio", "Agosto", "Septiembre", "Octubre", "Noviembre"}, 0)-MONTH('BD Asesor'!D13), 3)=0), AND('BD Asesor'!H13="Semestral", MOD(MATCH($B$2, {"Enero", "Febrero", "Marzo", "Abril", "Mayo", "Junio", "Julio", "Agosto", "Septiembre", "Octubre", "Noviembre"}, 0)-MONTH('BD Asesor'!D13), 6)=0), AND('BD Asesor'!H13="Anual", MONTH('BD Asesor'!D13)=MATCH($B$2, {"Enero", "Febrero", "Marzo", "Abril", "Mayo", "Junio", "Julio", "Agosto", "Septiembre", "Octubre", "Noviembre"}, 0)) ), 'BD Asesor'!L13, "")} | N11: =IFERROR(__xludf.DUMMYFUNCTION("""COMPUTED_VALUE"""),"ALEJANDRO VAZQUEZ RODRIGUEZ") -> ALEJANDRO VAZQUEZ RODRIGUEZ | O11: =IFERROR(__xludf.DUMMYFUNCTION("""COMPUTED_VALUE"""),"H") -> H | P11: =IFERROR(__xludf.DUMMYFUNCTION("""COMPUTED_VALUE"""),"Activo") -> Activo | Q11: =IFERROR(__xludf.DUMMYFUNCTION("""COMPUTED_VALUE"""),44042.0) -> 44042 | R11: =IFERROR(__xludf.DUMMYFUNCTION("""COMPUTED_VALUE"""),"VI0002546462") -> VI0002546462 | S11: =IFERROR(__xludf.DUMMYFUNCTION("""COMPUTED_VALUE"""),29765.232000000004) -> 29765.232 | T11: =IFERROR(__xludf.DUMMYFUNCTION("""COMPUTED_VALUE"""),"UDIS") -> UDIS | U11: =IFERROR(__xludf.DUMMYFUNCTION("""COMPUTED_VALUE"""),"Mensual") -> Mensual | V11: =IFERROR(__xludf.DUMMYFUNCTION("""COMPUTED_VALUE"""),"TC") -> TC | W11: =IFERROR(__xludf.DUMMYFUNCTION("""COMPUTED_VALUE"""),"Vida") -> Vida
